[
  {
    "Type": "AdvancedDataFile",
    "Version": "2.0",
    "TestDescription": "Creating a View under MyViews",
    "Globals": {
      "ViewName": "ListofStudentwithFirstNameSearch",
      "DataQueryGroup": "Common"	  
	  },
    "Apis": [
      {
        "RequestId": "cd47f2e6-1d88-4efd-9ba3-68c3892acbab",
        "RequestMethod": "GET",
        "RequestUrl": "/ds/campusnexus/Staff/CampusNexus.GetCurrentLoggedInUserStaff?$select=PersonId",
        "RequestBody": null,
        "ResponseStatus": 200,
        "ResponseTimeMs": 15000,
        "ResponseBody": "{\"value\":[]}"
      },
      {
        "RequestId": "199eddb9-73cc-4141-9a3e-7a46e822e6f9",
        "RequestMethod": "GET",
        "RequestUrl": "/ds/campusnexus/Students?$select=DateOfBirth,FirstName,FullName,LastName,Id&$filter=FirstName eq 'Automated'",
        "RequestBody": null,
        "ResponseStatus": 200,
        "ResponseTimeMs": 15000,
        "ResponseBody": "{\"value\":[]}"
      },
	  {
        "RequestId": "199eddb9-73cc-4141-9a3e-7a46e822e6f8",
        "RequestMethod": "GET",
        "RequestUrl": "/ds/views/DataQueryGroups?$select=Id,Name&$filter=Name eq '{{gDataQueryGroup}}'",
        "RequestBody": null,
        "ResponseStatus": 200,
        "ResponseTimeMs": 15000,
        "ResponseBody": "{\"value\":[]}"
      },
      {
        "RequestId": "c0975fa0-be1d-480a-94b7-23924539a999",
        "RequestMethod": "POST",
        "RequestUrl": "/ds/views/DataQueries",
        "RequestBody": {
							"Name": "{{gViewName}}",
							"Query": "/Students?$filter=FirstName eq 'nitin'&$select=DateOfBirth,FirstName,FullName,LastName,Id",
							"RootEntity": "Student",
							"SelectedColumns": "[[{\"name\":\"Student\",\"key\":[{\"propertyRef\":[{\"name\":\"Id\"}]}],\"property\":[{\"name\":\"Id\",\"type\":\"Edm.Int32\"},{\"name\":\"AcgEligReasonCode\",\"type\":\"Edm.String\"},{\"name\":\"AgencyId\",\"type\":\"Edm.Int32\"},{\"name\":\"AlienNumber\",\"type\":\"Edm.String\"},{\"name\":\"ArAccountStatus\",\"type\":\"Edm.String\"},{\"name\":\"ArBalance\",\"type\":\"Edm.Decimal\"},{\"name\":\"ArNextTransactionNumber\",\"type\":\"Edm.Int16\"},{\"name\":\"AssignedAdmissionsRepId\",\"type\":\"Edm.Int32\"},{\"name\":\"AthleticIdentifier\",\"type\":\"Edm.String\"},{\"name\":\"BestTimeToContact\",\"type\":\"Edm.String\"},{\"name\":\"CampusId\",\"type\":\"Edm.Int32\"},{\"name\":\"CitizenId\",\"type\":\"Edm.Int32\"},{\"name\":\"City\",\"type\":\"Edm.String\"},{\"name\":\"CollegeId\",\"type\":\"Edm.Int32\"},{\"name\":\"CountryId\",\"type\":\"Edm.Int32\"},{\"name\":\"CountyId\",\"type\":\"Edm.Int32\"},{\"name\":\"CreatedDateTime\",\"type\":\"Edm.DateTimeOffset\"},{\"name\":\"CumulativeGpa\",\"type\":\"Edm.Decimal\"},{\"name\":\"CumulativeGpaPoints\",\"type\":\"Edm.Decimal\"},{\"name\":\"CurrencyCodeId\",\"type\":\"Edm.Int32\"},{\"name\":\"CurrentLda\",\"type\":\"Edm.DateTimeOffset\"},{\"name\":\"DataBlockIndicator\",\"type\":\"Edm.Boolean\"},{\"name\":\"DateOfBirth\",\"type\":\"Edm.DateTimeOffset\"},{\"name\":\"DbiModifiedDate\",\"type\":\"Edm.DateTimeOffset\"},{\"name\":\"DefaultAddressCode\",\"type\":\"Edm.String\"},{\"name\":\"DefaultMasterStudentAddressId\",\"type\":\"Edm.Int32\"},{\"name\":\"DefaultStudentAddressId\",\"type\":\"Edm.Int32\"},{\"name\":\"Disabled\",\"type\":\"Edm.String\"},{\"name\":\"DriverLicenseNumber\",\"type\":\"Edm.String\"},{\"name\":\"DriverLicenseState\",\"type\":\"Edm.String\"},{\"name\":\"EmailAddress\",\"type\":\"Edm.String\"},{\"name\":\"EmployerId\",\"type\":\"Edm.Int32\"},{\"name\":\"EmploymentStatusId\",\"type\":\"Edm.Int32\"},{\"name\":\"ExtraCurricularActivityId\",\"type\":\"Edm.Int32\"},{\"name\":\"FaGradPlusCounselingDate\",\"type\":\"Edm.DateTimeOffset\"},{\"name\":\"FaRigorousHighSchoolProgramCodeId\",\"type\":\"Edm.Int32\"},{\"name\":\"FirstName\",\"type\":\"Edm.String\"},{\"name\":\"FullName\",\"type\":\"Edm.String\"},{\"name\":\"GenderId\",\"type\":\"Edm.Int32\"},{\"name\":\"GpaCredits\",\"type\":\"Edm.Decimal\"},{\"name\":\"HispanicLatino\",\"type\":\"Edm.String\"},{\"name\":\"HsAcademicGpa\",\"type\":\"Edm.Decimal\"},{\"name\":\"IsActive\",\"type\":\"Edm.Boolean\"},{\"name\":\"IsAllowedBulkRegistrationByTrack\",\"type\":\"Edm.Boolean\"},{\"name\":\"IsBadAddress\",\"type\":\"Edm.Boolean\"},{\"name\":\"IsBadPhone\",\"type\":\"Edm.Boolean\"},{\"name\":\"IsDdVeteran\",\"type\":\"Edm.Boolean\"},{\"name\":\"IsEftDefaultForStipends\",\"type\":\"Edm.Boolean\"},{\"name\":\"IsExcludedCrmIntegration\",\"type\":\"Edm.Boolean\"},{\"name\":\"IsInDistrict\",\"type\":\"Edm.Boolean\"},{\"name\":\"IsSscrError11Received\",\"type\":\"Edm.Boolean\"},{\"name\":\"LastActivityDate\",\"type\":\"Edm.DateTimeOffset\"},{\"name\":\"LastInterestDate\",\"type\":\"Edm.DateTimeOffset\"},{\"name\":\"LastModifiedDateTime\",\"type\":\"Edm.DateTimeOffset\"},{\"name\":\"LastModifiedUserId\",\"type\":\"Edm.Int32\"},{\"name\":\"LastName\",\"type\":\"Edm.String\"},{\"name\":\"LastNameFirstFour\",\"type\":\"Edm.String\"},{\"name\":\"LastStatementBeginDate\",\"type\":\"Edm.DateTimeOffset\"},{\"name\":\"LastStatementCloseDate\",\"type\":\"Edm.DateTimeOffset\"},{\"name\":\"LastStatementDate\",\"type\":\"Edm.DateTimeOffset\"},{\"name\":\"LeadDate\",\"type\":\"Edm.DateTimeOffset\"},{\"name\":\"LeadSourceId\",\"type\":\"Edm.Int32\"},{\"name\":\"LeadTypeId\",\"type\":\"Edm.Int32\"},{\"name\":\"MaidenName\",\"type\":\"Edm.String\"},{\"name\":\"MaritalStatusId\",\"type\":\"Edm.Int32\"},{\"name\":\"Mi\",\"type\":\"Edm.String\"},{\"name\":\"MiddleName\",\"type\":\"Edm.String\"},{\"name\":\"MobilePhoneNumber\",\"type\":\"Edm.String\"},{\"name\":\"NationalityId\",\"type\":\"Edm.Int32\"},{\"name\":\"NickName\",\"type\":\"Edm.String\"},{\"name\":\"NiStudent\",\"type\":\"Edm.Boolean\"},{\"name\":\"Note\",\"type\":\"Edm.String\"},{\"name\":\"OriginalAssignedAdmissionsRepId\",\"type\":\"Edm.Int32\"},{\"name\":\"OriginalExpectedStartDate\",\"type\":\"Edm.DateTimeOffset\"},{\"name\":\"OriginalStartDate\",\"type\":\"Edm.DateTimeOffset\"},{\"name\":\"OtherEmailAddress\",\"type\":\"Edm.String\"},{\"name\":\"OtherPhoneNumber\",\"type\":\"Edm.String\"},{\"name\":\"PersonId\",\"type\":\"Edm.Int32\"},{\"name\":\"PhoneNumber\",\"type\":\"Edm.String\"},{\"name\":\"Pin\",\"type\":\"Edm.Decimal\"},{\"name\":\"PostalCode\",\"type\":\"Edm.String\"},{\"name\":\"PostalCodeFirstThree\",\"type\":\"Edm.String\"},{\"name\":\"PreviousEducationGpa\",\"type\":\"Edm.Decimal\"},{\"name\":\"PreviousEducationId\",\"type\":\"Edm.Int32\"},{\"name\":\"ProgramGroupId\",\"type\":\"Edm.Int32\"},{\"name\":\"ProgramId\",\"type\":\"Edm.Int32\"},{\"name\":\"RawFirstName\",\"type\":\"Edm.String\"},{\"name\":\"RawLastName\",\"type\":\"Edm.String\"},{\"name\":\"RawPhoneNumber\",\"type\":\"Edm.String\"},{\"name\":\"SchoolStatusId\",\"type\":\"Edm.Int32\"},{\"name\":\"ShiftId\",\"type\":\"Edm.Int32\"},{\"name\":\"SmsServiceProviderId\",\"type\":\"Edm.Int32\"},{\"name\":\"SourceSystem\",\"type\":\"Edm.String\"},{\"name\":\"Ssn\",\"type\":\"Edm.String\"},{\"name\":\"StartDate\",\"type\":\"Edm.DateTimeOffset\"},{\"name\":\"State\",\"type\":\"Edm.String\"},{\"name\":\"StatementComment\",\"type\":\"Edm.String\"},{\"name\":\"StreetAddress\",\"type\":\"Edm.String\"},{\"name\":\"StreetAddress2\",\"type\":\"Edm.String\"},{\"name\":\"StudentIdentifier\",\"type\":\"Edm.String\"},{\"name\":\"StudentNumber\",\"type\":\"Edm.String\"},{\"name\":\"SubscribeToSms\",\"type\":\"Edm.Boolean\"},{\"name\":\"Suffix\",\"type\":\"Edm.String\"},{\"name\":\"SuffixId\",\"type\":\"Edm.Int32\"},{\"name\":\"TitleId\",\"type\":\"Edm.Int32\"},{\"name\":\"Veteran\",\"type\":\"Edm.String\"},{\"name\":\"WorkPhoneNumber\",\"type\":\"Edm.String\"},{\"name\":\"WorkPhoneNumberExtension\",\"type\":\"Edm.String\"}],\"navigationProperty\":[{\"name\":\"CurrencyCode\",\"type\":\"Cmc.Nexus.Models.Common.CurrencyCode\",\"referentialConstraint\":[{\"property\":\"CurrencyCodeId\",\"referencedProperty\":\"Id\"}]},{\"name\":\"Shift\",\"type\":\"Cmc.Nexus.Models.Academics.Shift\",\"referentialConstraint\":[{\"property\":\"ShiftId\",\"referencedProperty\":\"Id\"}]},{\"name\":\"SchoolStatus\",\"type\":\"Cmc.Nexus.Models.Common.SchoolStatus\",\"referentialConstraint\":[{\"property\":\"SchoolStatusId\",\"referencedProperty\":\"Id\"}]},{\"name\":\"Person\",\"type\":\"Cmc.Nexus.Models.Common.Person\",\"referentialConstraint\":[{\"property\":\"PersonId\",\"referencedProperty\":\"Id\"}]},{\"name\":\"Tasks\",\"type\":\"Collection(Cmc.Nexus.Models.Crm.Task)\"},{\"name\":\"StudentEthnicities\",\"type\":\"Collection(Cmc.Nexus.Models.Common.StudentEthnicity)\"},{\"name\":\"Documents\",\"type\":\"Collection(Cmc.Nexus.Models.Crm.Document)\"},{\"name\":\"EnrollmentPeriods\",\"type\":\"Collection(Cmc.Nexus.Models.Academics.StudentEnrollmentPeriod)\"},{\"name\":\"TermSummaries\",\"type\":\"Collection(Cmc.Nexus.Models.Academics.StudentEnrollmentTermSummary)\"},{\"name\":\"StudentCourses\",\"type\":\"Collection(Cmc.Nexus.Models.Academics.StudentCourse)\"},{\"name\":\"StudentCourseStatusChanges\",\"type\":\"Collection(Cmc.Nexus.Models.Academics.StudentCourseStatusChange)\"},{\"name\":\"StudentGPAs\",\"type\":\"Collection(Cmc.Nexus.Models.Academics.StudentGpa)\"},{\"name\":\"TransferCredits\",\"type\":\"Collection(Cmc.Nexus.Models.Admissions.StudentTransferCredit)\"},{\"name\":\"SecondaryLeadSources\",\"type\":\"Collection(Cmc.Nexus.Models.Admissions.ProspectInquiryLeadSource)\"},{\"name\":\"StudentPreviousEducation\",\"type\":\"Collection(Cmc.Nexus.Models.Admissions.StudentPreviousEducation)\"},{\"name\":\"TranscriptRequests\",\"type\":\"Collection(Cmc.Nexus.Models.Crm.TranscriptRequest)\"},{\"name\":\"ClearingHouseExportDetailRecords\",\"type\":\"Collection(Cmc.Nexus.Models.FinancialAid.ClearinghouseExportRecord)\"},{\"name\":\"PaidDisbursements\",\"type\":\"Collection(Cmc.Nexus.Models.FinancialAid.PaidDisbursement)\"},{\"name\":\"Advisors\",\"type\":\"Collection(Cmc.Nexus.Models.Common.StudentEnrollmentPeriodAdvisor)\"},{\"name\":\"FaAwards\",\"type\":\"Collection(Cmc.Nexus.Models.FinancialAid.StudentAward)\"},{\"name\":\"Campus\",\"type\":\"Cmc.Nexus.Models.Common.Campus\",\"referentialConstraint\":[{\"property\":\"CampusId\",\"referencedProperty\":\"Id\"}]},{\"name\":\"FaApplicationProcess\",\"type\":\"Collection(Cmc.Nexus.Models.FinancialAid.StudentAwardPell)\"},{\"name\":\"CollectionAccounts\",\"type\":\"Collection(Cmc.Nexus.Models.StudentAccounts.CollectionAccount)\"},{\"name\":\"StudentAccountTransactions\",\"type\":\"Collection(Cmc.Nexus.Models.StudentAccounts.StudentAccountTransaction)\"},{\"name\":\"StudentAccountPendingTransactions\",\"type\":\"Collection(Cmc.Nexus.Models.StudentAccounts.StudentAccountPendingTransaction)\"},{\"name\":\"ExtraCurricularActivities\",\"type\":\"Collection(Cmc.Nexus.Models.Admissions.StudentExtraCurricularActivity)\"},{\"name\":\"StudentRt4Calculation\",\"type\":\"Collection(Cmc.Nexus.Models.StudentAccounts.StudentRt4Calculation)\"},{\"name\":\"StipendSummary\",\"type\":\"Collection(Cmc.Nexus.Models.StudentAccounts.StipendSummary)\"},{\"name\":\"Employer\",\"type\":\"Cmc.Nexus.Models.CareerServices.Employer\",\"referentialConstraint\":[{\"property\":\"EmployerId\",\"referencedProperty\":\"Id\"}]},{\"name\":\"EmploymentStatus\",\"type\":\"Cmc.Nexus.Models.CareerServices.EmploymentStatus\",\"referentialConstraint\":[{\"property\":\"EmploymentStatusId\",\"referencedProperty\":\"Id\"}]},{\"name\":\"StudentPlacementSummary\",\"type\":\"Collection(Cmc.Nexus.Models.CareerServices.StudentPlacementSummary)\"},{\"name\":\"EnrollmentPeriodFees\",\"type\":\"Collection(Cmc.Nexus.Models.Academics.StudentEnrollmentPeriodFee)\"},{\"name\":\"StudentServiceTypes\",\"type\":\"Collection(Cmc.Nexus.Models.StudentServices.StudentServiceType)\"},{\"name\":\"VeteranDetails\",\"type\":\"Collection(Cmc.Nexus.Models.StudentServices.StudentVeteranDetail)\"},{\"name\":\"DisabilityDetails\",\"type\":\"Collection(Cmc.Nexus.Models.StudentServices.StudentDisabilityDetail)\"},{\"name\":\"SchoolStatusHistory\",\"type\":\"Collection(Cmc.Nexus.Models.Common.StudentSchoolStatusHistory)\"},{\"name\":\"SchoolDefinedFieldValues\",\"type\":\"Collection(Cmc.Nexus.Models.Common.StudentSchoolDefinedFieldValue)\"},{\"name\":\"StudentGroups\",\"type\":\"Collection(Cmc.Nexus.Models.Common.StudentGroupMember)\"},{\"name\":\"RegistrationRules\",\"type\":\"Collection(Cmc.Nexus.Models.Academics.RegistrationRule)\"},{\"name\":\"SmsServiceProvider\",\"type\":\"Cmc.Nexus.Models.Crm.SmsServiceProvider\",\"referentialConstraint\":[{\"property\":\"SmsServiceProviderId\",\"referencedProperty\":\"Id\"}]},{\"name\":\"Program\",\"type\":\"Cmc.Nexus.Models.Academics.Program\",\"referentialConstraint\":[{\"property\":\"ProgramId\",\"referencedProperty\":\"Id\"}]},{\"name\":\"AgencyBranches\",\"type\":\"Collection(Cmc.Nexus.Models.Common.StudentAgencyBranch)\"},{\"name\":\"Country\",\"type\":\"Cmc.Nexus.Models.Common.Country\",\"referentialConstraint\":[{\"property\":\"CountryId\",\"referencedProperty\":\"Id\"}]},{\"name\":\"County\",\"type\":\"Cmc.Nexus.Models.Common.County\",\"referentialConstraint\":[{\"property\":\"CountyId\",\"referencedProperty\":\"Id\"}]},{\"name\":\"DataChanges\",\"type\":\"Collection(Cmc.Nexus.Models.Common.StudentDataChange)\"},{\"name\":\"Title\",\"type\":\"Cmc.Nexus.Models.Common.Title\",\"referentialConstraint\":[{\"property\":\"TitleId\",\"referencedProperty\":\"Id\"}]}]},{\"name\":\"DateOfBirth\",\"type\":\"Edm.DateTimeOffset\"}],[{\"name\":\"Student\",\"key\":[{\"propertyRef\":[{\"name\":\"Id\"}]}],\"property\":[{\"name\":\"Id\",\"type\":\"Edm.Int32\"},{\"name\":\"AcgEligReasonCode\",\"type\":\"Edm.String\"},{\"name\":\"AgencyId\",\"type\":\"Edm.Int32\"},{\"name\":\"AlienNumber\",\"type\":\"Edm.String\"},{\"name\":\"ArAccountStatus\",\"type\":\"Edm.String\"},{\"name\":\"ArBalance\",\"type\":\"Edm.Decimal\"},{\"name\":\"ArNextTransactionNumber\",\"type\":\"Edm.Int16\"},{\"name\":\"AssignedAdmissionsRepId\",\"type\":\"Edm.Int32\"},{\"name\":\"AthleticIdentifier\",\"type\":\"Edm.String\"},{\"name\":\"BestTimeToContact\",\"type\":\"Edm.String\"},{\"name\":\"CampusId\",\"type\":\"Edm.Int32\"},{\"name\":\"CitizenId\",\"type\":\"Edm.Int32\"},{\"name\":\"City\",\"type\":\"Edm.String\"},{\"name\":\"CollegeId\",\"type\":\"Edm.Int32\"},{\"name\":\"CountryId\",\"type\":\"Edm.Int32\"},{\"name\":\"CountyId\",\"type\":\"Edm.Int32\"},{\"name\":\"CreatedDateTime\",\"type\":\"Edm.DateTimeOffset\"},{\"name\":\"CumulativeGpa\",\"type\":\"Edm.Decimal\"},{\"name\":\"CumulativeGpaPoints\",\"type\":\"Edm.Decimal\"},{\"name\":\"CurrencyCodeId\",\"type\":\"Edm.Int32\"},{\"name\":\"CurrentLda\",\"type\":\"Edm.DateTimeOffset\"},{\"name\":\"DataBlockIndicator\",\"type\":\"Edm.Boolean\"},{\"name\":\"DateOfBirth\",\"type\":\"Edm.DateTimeOffset\"},{\"name\":\"DbiModifiedDate\",\"type\":\"Edm.DateTimeOffset\"},{\"name\":\"DefaultAddressCode\",\"type\":\"Edm.String\"},{\"name\":\"DefaultMasterStudentAddressId\",\"type\":\"Edm.Int32\"},{\"name\":\"DefaultStudentAddressId\",\"type\":\"Edm.Int32\"},{\"name\":\"Disabled\",\"type\":\"Edm.String\"},{\"name\":\"DriverLicenseNumber\",\"type\":\"Edm.String\"},{\"name\":\"DriverLicenseState\",\"type\":\"Edm.String\"},{\"name\":\"EmailAddress\",\"type\":\"Edm.String\"},{\"name\":\"EmployerId\",\"type\":\"Edm.Int32\"},{\"name\":\"EmploymentStatusId\",\"type\":\"Edm.Int32\"},{\"name\":\"ExtraCurricularActivityId\",\"type\":\"Edm.Int32\"},{\"name\":\"FaGradPlusCounselingDate\",\"type\":\"Edm.DateTimeOffset\"},{\"name\":\"FaRigorousHighSchoolProgramCodeId\",\"type\":\"Edm.Int32\"},{\"name\":\"FirstName\",\"type\":\"Edm.String\"},{\"name\":\"FullName\",\"type\":\"Edm.String\"},{\"name\":\"GenderId\",\"type\":\"Edm.Int32\"},{\"name\":\"GpaCredits\",\"type\":\"Edm.Decimal\"},{\"name\":\"HispanicLatino\",\"type\":\"Edm.String\"},{\"name\":\"HsAcademicGpa\",\"type\":\"Edm.Decimal\"},{\"name\":\"IsActive\",\"type\":\"Edm.Boolean\"},{\"name\":\"IsAllowedBulkRegistrationByTrack\",\"type\":\"Edm.Boolean\"},{\"name\":\"IsBadAddress\",\"type\":\"Edm.Boolean\"},{\"name\":\"IsBadPhone\",\"type\":\"Edm.Boolean\"},{\"name\":\"IsDdVeteran\",\"type\":\"Edm.Boolean\"},{\"name\":\"IsEftDefaultForStipends\",\"type\":\"Edm.Boolean\"},{\"name\":\"IsExcludedCrmIntegration\",\"type\":\"Edm.Boolean\"},{\"name\":\"IsInDistrict\",\"type\":\"Edm.Boolean\"},{\"name\":\"IsSscrError11Received\",\"type\":\"Edm.Boolean\"},{\"name\":\"LastActivityDate\",\"type\":\"Edm.DateTimeOffset\"},{\"name\":\"LastInterestDate\",\"type\":\"Edm.DateTimeOffset\"},{\"name\":\"LastModifiedDateTime\",\"type\":\"Edm.DateTimeOffset\"},{\"name\":\"LastModifiedUserId\",\"type\":\"Edm.Int32\"},{\"name\":\"LastName\",\"type\":\"Edm.String\"},{\"name\":\"LastNameFirstFour\",\"type\":\"Edm.String\"},{\"name\":\"LastStatementBeginDate\",\"type\":\"Edm.DateTimeOffset\"},{\"name\":\"LastStatementCloseDate\",\"type\":\"Edm.DateTimeOffset\"},{\"name\":\"LastStatementDate\",\"type\":\"Edm.DateTimeOffset\"},{\"name\":\"LeadDate\",\"type\":\"Edm.DateTimeOffset\"},{\"name\":\"LeadSourceId\",\"type\":\"Edm.Int32\"},{\"name\":\"LeadTypeId\",\"type\":\"Edm.Int32\"},{\"name\":\"MaidenName\",\"type\":\"Edm.String\"},{\"name\":\"MaritalStatusId\",\"type\":\"Edm.Int32\"},{\"name\":\"Mi\",\"type\":\"Edm.String\"},{\"name\":\"MiddleName\",\"type\":\"Edm.String\"},{\"name\":\"MobilePhoneNumber\",\"type\":\"Edm.String\"},{\"name\":\"NationalityId\",\"type\":\"Edm.Int32\"},{\"name\":\"NickName\",\"type\":\"Edm.String\"},{\"name\":\"NiStudent\",\"type\":\"Edm.Boolean\"},{\"name\":\"Note\",\"type\":\"Edm.String\"},{\"name\":\"OriginalAssignedAdmissionsRepId\",\"type\":\"Edm.Int32\"},{\"name\":\"OriginalExpectedStartDate\",\"type\":\"Edm.DateTimeOffset\"},{\"name\":\"OriginalStartDate\",\"type\":\"Edm.DateTimeOffset\"},{\"name\":\"OtherEmailAddress\",\"type\":\"Edm.String\"},{\"name\":\"OtherPhoneNumber\",\"type\":\"Edm.String\"},{\"name\":\"PersonId\",\"type\":\"Edm.Int32\"},{\"name\":\"PhoneNumber\",\"type\":\"Edm.String\"},{\"name\":\"Pin\",\"type\":\"Edm.Decimal\"},{\"name\":\"PostalCode\",\"type\":\"Edm.String\"},{\"name\":\"PostalCodeFirstThree\",\"type\":\"Edm.String\"},{\"name\":\"PreviousEducationGpa\",\"type\":\"Edm.Decimal\"},{\"name\":\"PreviousEducationId\",\"type\":\"Edm.Int32\"},{\"name\":\"ProgramGroupId\",\"type\":\"Edm.Int32\"},{\"name\":\"ProgramId\",\"type\":\"Edm.Int32\"},{\"name\":\"RawFirstName\",\"type\":\"Edm.String\"},{\"name\":\"RawLastName\",\"type\":\"Edm.String\"},{\"name\":\"RawPhoneNumber\",\"type\":\"Edm.String\"},{\"name\":\"SchoolStatusId\",\"type\":\"Edm.Int32\"},{\"name\":\"ShiftId\",\"type\":\"Edm.Int32\"},{\"name\":\"SmsServiceProviderId\",\"type\":\"Edm.Int32\"},{\"name\":\"SourceSystem\",\"type\":\"Edm.String\"},{\"name\":\"Ssn\",\"type\":\"Edm.String\"},{\"name\":\"StartDate\",\"type\":\"Edm.DateTimeOffset\"},{\"name\":\"State\",\"type\":\"Edm.String\"},{\"name\":\"StatementComment\",\"type\":\"Edm.String\"},{\"name\":\"StreetAddress\",\"type\":\"Edm.String\"},{\"name\":\"StreetAddress2\",\"type\":\"Edm.String\"},{\"name\":\"StudentIdentifier\",\"type\":\"Edm.String\"},{\"name\":\"StudentNumber\",\"type\":\"Edm.String\"},{\"name\":\"SubscribeToSms\",\"type\":\"Edm.Boolean\"},{\"name\":\"Suffix\",\"type\":\"Edm.String\"},{\"name\":\"SuffixId\",\"type\":\"Edm.Int32\"},{\"name\":\"TitleId\",\"type\":\"Edm.Int32\"},{\"name\":\"Veteran\",\"type\":\"Edm.String\"},{\"name\":\"WorkPhoneNumber\",\"type\":\"Edm.String\"},{\"name\":\"WorkPhoneNumberExtension\",\"type\":\"Edm.String\"}],\"navigationProperty\":[{\"name\":\"CurrencyCode\",\"type\":\"Cmc.Nexus.Models.Common.CurrencyCode\",\"referentialConstraint\":[{\"property\":\"CurrencyCodeId\",\"referencedProperty\":\"Id\"}]},{\"name\":\"Shift\",\"type\":\"Cmc.Nexus.Models.Academics.Shift\",\"referentialConstraint\":[{\"property\":\"ShiftId\",\"referencedProperty\":\"Id\"}]},{\"name\":\"SchoolStatus\",\"type\":\"Cmc.Nexus.Models.Common.SchoolStatus\",\"referentialConstraint\":[{\"property\":\"SchoolStatusId\",\"referencedProperty\":\"Id\"}]},{\"name\":\"Person\",\"type\":\"Cmc.Nexus.Models.Common.Person\",\"referentialConstraint\":[{\"property\":\"PersonId\",\"referencedProperty\":\"Id\"}]},{\"name\":\"Tasks\",\"type\":\"Collection(Cmc.Nexus.Models.Crm.Task)\"},{\"name\":\"StudentEthnicities\",\"type\":\"Collection(Cmc.Nexus.Models.Common.StudentEthnicity)\"},{\"name\":\"Documents\",\"type\":\"Collection(Cmc.Nexus.Models.Crm.Document)\"},{\"name\":\"EnrollmentPeriods\",\"type\":\"Collection(Cmc.Nexus.Models.Academics.StudentEnrollmentPeriod)\"},{\"name\":\"TermSummaries\",\"type\":\"Collection(Cmc.Nexus.Models.Academics.StudentEnrollmentTermSummary)\"},{\"name\":\"StudentCourses\",\"type\":\"Collection(Cmc.Nexus.Models.Academics.StudentCourse)\"},{\"name\":\"StudentCourseStatusChanges\",\"type\":\"Collection(Cmc.Nexus.Models.Academics.StudentCourseStatusChange)\"},{\"name\":\"StudentGPAs\",\"type\":\"Collection(Cmc.Nexus.Models.Academics.StudentGpa)\"},{\"name\":\"TransferCredits\",\"type\":\"Collection(Cmc.Nexus.Models.Admissions.StudentTransferCredit)\"},{\"name\":\"SecondaryLeadSources\",\"type\":\"Collection(Cmc.Nexus.Models.Admissions.ProspectInquiryLeadSource)\"},{\"name\":\"StudentPreviousEducation\",\"type\":\"Collection(Cmc.Nexus.Models.Admissions.StudentPreviousEducation)\"},{\"name\":\"TranscriptRequests\",\"type\":\"Collection(Cmc.Nexus.Models.Crm.TranscriptRequest)\"},{\"name\":\"ClearingHouseExportDetailRecords\",\"type\":\"Collection(Cmc.Nexus.Models.FinancialAid.ClearinghouseExportRecord)\"},{\"name\":\"PaidDisbursements\",\"type\":\"Collection(Cmc.Nexus.Models.FinancialAid.PaidDisbursement)\"},{\"name\":\"Advisors\",\"type\":\"Collection(Cmc.Nexus.Models.Common.StudentEnrollmentPeriodAdvisor)\"},{\"name\":\"FaAwards\",\"type\":\"Collection(Cmc.Nexus.Models.FinancialAid.StudentAward)\"},{\"name\":\"Campus\",\"type\":\"Cmc.Nexus.Models.Common.Campus\",\"referentialConstraint\":[{\"property\":\"CampusId\",\"referencedProperty\":\"Id\"}]},{\"name\":\"FaApplicationProcess\",\"type\":\"Collection(Cmc.Nexus.Models.FinancialAid.StudentAwardPell)\"},{\"name\":\"CollectionAccounts\",\"type\":\"Collection(Cmc.Nexus.Models.StudentAccounts.CollectionAccount)\"},{\"name\":\"StudentAccountTransactions\",\"type\":\"Collection(Cmc.Nexus.Models.StudentAccounts.StudentAccountTransaction)\"},{\"name\":\"StudentAccountPendingTransactions\",\"type\":\"Collection(Cmc.Nexus.Models.StudentAccounts.StudentAccountPendingTransaction)\"},{\"name\":\"ExtraCurricularActivities\",\"type\":\"Collection(Cmc.Nexus.Models.Admissions.StudentExtraCurricularActivity)\"},{\"name\":\"StudentRt4Calculation\",\"type\":\"Collection(Cmc.Nexus.Models.StudentAccounts.StudentRt4Calculation)\"},{\"name\":\"StipendSummary\",\"type\":\"Collection(Cmc.Nexus.Models.StudentAccounts.StipendSummary)\"},{\"name\":\"Employer\",\"type\":\"Cmc.Nexus.Models.CareerServices.Employer\",\"referentialConstraint\":[{\"property\":\"EmployerId\",\"referencedProperty\":\"Id\"}]},{\"name\":\"EmploymentStatus\",\"type\":\"Cmc.Nexus.Models.CareerServices.EmploymentStatus\",\"referentialConstraint\":[{\"property\":\"EmploymentStatusId\",\"referencedProperty\":\"Id\"}]},{\"name\":\"StudentPlacementSummary\",\"type\":\"Collection(Cmc.Nexus.Models.CareerServices.StudentPlacementSummary)\"},{\"name\":\"EnrollmentPeriodFees\",\"type\":\"Collection(Cmc.Nexus.Models.Academics.StudentEnrollmentPeriodFee)\"},{\"name\":\"StudentServiceTypes\",\"type\":\"Collection(Cmc.Nexus.Models.StudentServices.StudentServiceType)\"},{\"name\":\"VeteranDetails\",\"type\":\"Collection(Cmc.Nexus.Models.StudentServices.StudentVeteranDetail)\"},{\"name\":\"DisabilityDetails\",\"type\":\"Collection(Cmc.Nexus.Models.StudentServices.StudentDisabilityDetail)\"},{\"name\":\"SchoolStatusHistory\",\"type\":\"Collection(Cmc.Nexus.Models.Common.StudentSchoolStatusHistory)\"},{\"name\":\"SchoolDefinedFieldValues\",\"type\":\"Collection(Cmc.Nexus.Models.Common.StudentSchoolDefinedFieldValue)\"},{\"name\":\"StudentGroups\",\"type\":\"Collection(Cmc.Nexus.Models.Common.StudentGroupMember)\"},{\"name\":\"RegistrationRules\",\"type\":\"Collection(Cmc.Nexus.Models.Academics.RegistrationRule)\"},{\"name\":\"SmsServiceProvider\",\"type\":\"Cmc.Nexus.Models.Crm.SmsServiceProvider\",\"referentialConstraint\":[{\"property\":\"SmsServiceProviderId\",\"referencedProperty\":\"Id\"}]},{\"name\":\"Program\",\"type\":\"Cmc.Nexus.Models.Academics.Program\",\"referentialConstraint\":[{\"property\":\"ProgramId\",\"referencedProperty\":\"Id\"}]},{\"name\":\"AgencyBranches\",\"type\":\"Collection(Cmc.Nexus.Models.Common.StudentAgencyBranch)\"},{\"name\":\"Country\",\"type\":\"Cmc.Nexus.Models.Common.Country\",\"referentialConstraint\":[{\"property\":\"CountryId\",\"referencedProperty\":\"Id\"}]},{\"name\":\"County\",\"type\":\"Cmc.Nexus.Models.Common.County\",\"referentialConstraint\":[{\"property\":\"CountyId\",\"referencedProperty\":\"Id\"}]},{\"name\":\"DataChanges\",\"type\":\"Collection(Cmc.Nexus.Models.Common.StudentDataChange)\"},{\"name\":\"Title\",\"type\":\"Cmc.Nexus.Models.Common.Title\",\"referentialConstraint\":[{\"property\":\"TitleId\",\"referencedProperty\":\"Id\"}]}]},{\"name\":\"FirstName\",\"type\":\"Edm.String\"}],[{\"name\":\"Student\",\"key\":[{\"propertyRef\":[{\"name\":\"Id\"}]}],\"property\":[{\"name\":\"Id\",\"type\":\"Edm.Int32\"},{\"name\":\"AcgEligReasonCode\",\"type\":\"Edm.String\"},{\"name\":\"AgencyId\",\"type\":\"Edm.Int32\"},{\"name\":\"AlienNumber\",\"type\":\"Edm.String\"},{\"name\":\"ArAccountStatus\",\"type\":\"Edm.String\"},{\"name\":\"ArBalance\",\"type\":\"Edm.Decimal\"},{\"name\":\"ArNextTransactionNumber\",\"type\":\"Edm.Int16\"},{\"name\":\"AssignedAdmissionsRepId\",\"type\":\"Edm.Int32\"},{\"name\":\"AthleticIdentifier\",\"type\":\"Edm.String\"},{\"name\":\"BestTimeToContact\",\"type\":\"Edm.String\"},{\"name\":\"CampusId\",\"type\":\"Edm.Int32\"},{\"name\":\"CitizenId\",\"type\":\"Edm.Int32\"},{\"name\":\"City\",\"type\":\"Edm.String\"},{\"name\":\"CollegeId\",\"type\":\"Edm.Int32\"},{\"name\":\"CountryId\",\"type\":\"Edm.Int32\"},{\"name\":\"CountyId\",\"type\":\"Edm.Int32\"},{\"name\":\"CreatedDateTime\",\"type\":\"Edm.DateTimeOffset\"},{\"name\":\"CumulativeGpa\",\"type\":\"Edm.Decimal\"},{\"name\":\"CumulativeGpaPoints\",\"type\":\"Edm.Decimal\"},{\"name\":\"CurrencyCodeId\",\"type\":\"Edm.Int32\"},{\"name\":\"CurrentLda\",\"type\":\"Edm.DateTimeOffset\"},{\"name\":\"DataBlockIndicator\",\"type\":\"Edm.Boolean\"},{\"name\":\"DateOfBirth\",\"type\":\"Edm.DateTimeOffset\"},{\"name\":\"DbiModifiedDate\",\"type\":\"Edm.DateTimeOffset\"},{\"name\":\"DefaultAddressCode\",\"type\":\"Edm.String\"},{\"name\":\"DefaultMasterStudentAddressId\",\"type\":\"Edm.Int32\"},{\"name\":\"DefaultStudentAddressId\",\"type\":\"Edm.Int32\"},{\"name\":\"Disabled\",\"type\":\"Edm.String\"},{\"name\":\"DriverLicenseNumber\",\"type\":\"Edm.String\"},{\"name\":\"DriverLicenseState\",\"type\":\"Edm.String\"},{\"name\":\"EmailAddress\",\"type\":\"Edm.String\"},{\"name\":\"EmployerId\",\"type\":\"Edm.Int32\"},{\"name\":\"EmploymentStatusId\",\"type\":\"Edm.Int32\"},{\"name\":\"ExtraCurricularActivityId\",\"type\":\"Edm.Int32\"},{\"name\":\"FaGradPlusCounselingDate\",\"type\":\"Edm.DateTimeOffset\"},{\"name\":\"FaRigorousHighSchoolProgramCodeId\",\"type\":\"Edm.Int32\"},{\"name\":\"FirstName\",\"type\":\"Edm.String\"},{\"name\":\"FullName\",\"type\":\"Edm.String\"},{\"name\":\"GenderId\",\"type\":\"Edm.Int32\"},{\"name\":\"GpaCredits\",\"type\":\"Edm.Decimal\"},{\"name\":\"HispanicLatino\",\"type\":\"Edm.String\"},{\"name\":\"HsAcademicGpa\",\"type\":\"Edm.Decimal\"},{\"name\":\"IsActive\",\"type\":\"Edm.Boolean\"},{\"name\":\"IsAllowedBulkRegistrationByTrack\",\"type\":\"Edm.Boolean\"},{\"name\":\"IsBadAddress\",\"type\":\"Edm.Boolean\"},{\"name\":\"IsBadPhone\",\"type\":\"Edm.Boolean\"},{\"name\":\"IsDdVeteran\",\"type\":\"Edm.Boolean\"},{\"name\":\"IsEftDefaultForStipends\",\"type\":\"Edm.Boolean\"},{\"name\":\"IsExcludedCrmIntegration\",\"type\":\"Edm.Boolean\"},{\"name\":\"IsInDistrict\",\"type\":\"Edm.Boolean\"},{\"name\":\"IsSscrError11Received\",\"type\":\"Edm.Boolean\"},{\"name\":\"LastActivityDate\",\"type\":\"Edm.DateTimeOffset\"},{\"name\":\"LastInterestDate\",\"type\":\"Edm.DateTimeOffset\"},{\"name\":\"LastModifiedDateTime\",\"type\":\"Edm.DateTimeOffset\"},{\"name\":\"LastModifiedUserId\",\"type\":\"Edm.Int32\"},{\"name\":\"LastName\",\"type\":\"Edm.String\"},{\"name\":\"LastNameFirstFour\",\"type\":\"Edm.String\"},{\"name\":\"LastStatementBeginDate\",\"type\":\"Edm.DateTimeOffset\"},{\"name\":\"LastStatementCloseDate\",\"type\":\"Edm.DateTimeOffset\"},{\"name\":\"LastStatementDate\",\"type\":\"Edm.DateTimeOffset\"},{\"name\":\"LeadDate\",\"type\":\"Edm.DateTimeOffset\"},{\"name\":\"LeadSourceId\",\"type\":\"Edm.Int32\"},{\"name\":\"LeadTypeId\",\"type\":\"Edm.Int32\"},{\"name\":\"MaidenName\",\"type\":\"Edm.String\"},{\"name\":\"MaritalStatusId\",\"type\":\"Edm.Int32\"},{\"name\":\"Mi\",\"type\":\"Edm.String\"},{\"name\":\"MiddleName\",\"type\":\"Edm.String\"},{\"name\":\"MobilePhoneNumber\",\"type\":\"Edm.String\"},{\"name\":\"NationalityId\",\"type\":\"Edm.Int32\"},{\"name\":\"NickName\",\"type\":\"Edm.String\"},{\"name\":\"NiStudent\",\"type\":\"Edm.Boolean\"},{\"name\":\"Note\",\"type\":\"Edm.String\"},{\"name\":\"OriginalAssignedAdmissionsRepId\",\"type\":\"Edm.Int32\"},{\"name\":\"OriginalExpectedStartDate\",\"type\":\"Edm.DateTimeOffset\"},{\"name\":\"OriginalStartDate\",\"type\":\"Edm.DateTimeOffset\"},{\"name\":\"OtherEmailAddress\",\"type\":\"Edm.String\"},{\"name\":\"OtherPhoneNumber\",\"type\":\"Edm.String\"},{\"name\":\"PersonId\",\"type\":\"Edm.Int32\"},{\"name\":\"PhoneNumber\",\"type\":\"Edm.String\"},{\"name\":\"Pin\",\"type\":\"Edm.Decimal\"},{\"name\":\"PostalCode\",\"type\":\"Edm.String\"},{\"name\":\"PostalCodeFirstThree\",\"type\":\"Edm.String\"},{\"name\":\"PreviousEducationGpa\",\"type\":\"Edm.Decimal\"},{\"name\":\"PreviousEducationId\",\"type\":\"Edm.Int32\"},{\"name\":\"ProgramGroupId\",\"type\":\"Edm.Int32\"},{\"name\":\"ProgramId\",\"type\":\"Edm.Int32\"},{\"name\":\"RawFirstName\",\"type\":\"Edm.String\"},{\"name\":\"RawLastName\",\"type\":\"Edm.String\"},{\"name\":\"RawPhoneNumber\",\"type\":\"Edm.String\"},{\"name\":\"SchoolStatusId\",\"type\":\"Edm.Int32\"},{\"name\":\"ShiftId\",\"type\":\"Edm.Int32\"},{\"name\":\"SmsServiceProviderId\",\"type\":\"Edm.Int32\"},{\"name\":\"SourceSystem\",\"type\":\"Edm.String\"},{\"name\":\"Ssn\",\"type\":\"Edm.String\"},{\"name\":\"StartDate\",\"type\":\"Edm.DateTimeOffset\"},{\"name\":\"State\",\"type\":\"Edm.String\"},{\"name\":\"StatementComment\",\"type\":\"Edm.String\"},{\"name\":\"StreetAddress\",\"type\":\"Edm.String\"},{\"name\":\"StreetAddress2\",\"type\":\"Edm.String\"},{\"name\":\"StudentIdentifier\",\"type\":\"Edm.String\"},{\"name\":\"StudentNumber\",\"type\":\"Edm.String\"},{\"name\":\"SubscribeToSms\",\"type\":\"Edm.Boolean\"},{\"name\":\"Suffix\",\"type\":\"Edm.String\"},{\"name\":\"SuffixId\",\"type\":\"Edm.Int32\"},{\"name\":\"TitleId\",\"type\":\"Edm.Int32\"},{\"name\":\"Veteran\",\"type\":\"Edm.String\"},{\"name\":\"WorkPhoneNumber\",\"type\":\"Edm.String\"},{\"name\":\"WorkPhoneNumberExtension\",\"type\":\"Edm.String\"}],\"navigationProperty\":[{\"name\":\"CurrencyCode\",\"type\":\"Cmc.Nexus.Models.Common.CurrencyCode\",\"referentialConstraint\":[{\"property\":\"CurrencyCodeId\",\"referencedProperty\":\"Id\"}]},{\"name\":\"Shift\",\"type\":\"Cmc.Nexus.Models.Academics.Shift\",\"referentialConstraint\":[{\"property\":\"ShiftId\",\"referencedProperty\":\"Id\"}]},{\"name\":\"SchoolStatus\",\"type\":\"Cmc.Nexus.Models.Common.SchoolStatus\",\"referentialConstraint\":[{\"property\":\"SchoolStatusId\",\"referencedProperty\":\"Id\"}]},{\"name\":\"Person\",\"type\":\"Cmc.Nexus.Models.Common.Person\",\"referentialConstraint\":[{\"property\":\"PersonId\",\"referencedProperty\":\"Id\"}]},{\"name\":\"Tasks\",\"type\":\"Collection(Cmc.Nexus.Models.Crm.Task)\"},{\"name\":\"StudentEthnicities\",\"type\":\"Collection(Cmc.Nexus.Models.Common.StudentEthnicity)\"},{\"name\":\"Documents\",\"type\":\"Collection(Cmc.Nexus.Models.Crm.Document)\"},{\"name\":\"EnrollmentPeriods\",\"type\":\"Collection(Cmc.Nexus.Models.Academics.StudentEnrollmentPeriod)\"},{\"name\":\"TermSummaries\",\"type\":\"Collection(Cmc.Nexus.Models.Academics.StudentEnrollmentTermSummary)\"},{\"name\":\"StudentCourses\",\"type\":\"Collection(Cmc.Nexus.Models.Academics.StudentCourse)\"},{\"name\":\"StudentCourseStatusChanges\",\"type\":\"Collection(Cmc.Nexus.Models.Academics.StudentCourseStatusChange)\"},{\"name\":\"StudentGPAs\",\"type\":\"Collection(Cmc.Nexus.Models.Academics.StudentGpa)\"},{\"name\":\"TransferCredits\",\"type\":\"Collection(Cmc.Nexus.Models.Admissions.StudentTransferCredit)\"},{\"name\":\"SecondaryLeadSources\",\"type\":\"Collection(Cmc.Nexus.Models.Admissions.ProspectInquiryLeadSource)\"},{\"name\":\"StudentPreviousEducation\",\"type\":\"Collection(Cmc.Nexus.Models.Admissions.StudentPreviousEducation)\"},{\"name\":\"TranscriptRequests\",\"type\":\"Collection(Cmc.Nexus.Models.Crm.TranscriptRequest)\"},{\"name\":\"ClearingHouseExportDetailRecords\",\"type\":\"Collection(Cmc.Nexus.Models.FinancialAid.ClearinghouseExportRecord)\"},{\"name\":\"PaidDisbursements\",\"type\":\"Collection(Cmc.Nexus.Models.FinancialAid.PaidDisbursement)\"},{\"name\":\"Advisors\",\"type\":\"Collection(Cmc.Nexus.Models.Common.StudentEnrollmentPeriodAdvisor)\"},{\"name\":\"FaAwards\",\"type\":\"Collection(Cmc.Nexus.Models.FinancialAid.StudentAward)\"},{\"name\":\"Campus\",\"type\":\"Cmc.Nexus.Models.Common.Campus\",\"referentialConstraint\":[{\"property\":\"CampusId\",\"referencedProperty\":\"Id\"}]},{\"name\":\"FaApplicationProcess\",\"type\":\"Collection(Cmc.Nexus.Models.FinancialAid.StudentAwardPell)\"},{\"name\":\"CollectionAccounts\",\"type\":\"Collection(Cmc.Nexus.Models.StudentAccounts.CollectionAccount)\"},{\"name\":\"StudentAccountTransactions\",\"type\":\"Collection(Cmc.Nexus.Models.StudentAccounts.StudentAccountTransaction)\"},{\"name\":\"StudentAccountPendingTransactions\",\"type\":\"Collection(Cmc.Nexus.Models.StudentAccounts.StudentAccountPendingTransaction)\"},{\"name\":\"ExtraCurricularActivities\",\"type\":\"Collection(Cmc.Nexus.Models.Admissions.StudentExtraCurricularActivity)\"},{\"name\":\"StudentRt4Calculation\",\"type\":\"Collection(Cmc.Nexus.Models.StudentAccounts.StudentRt4Calculation)\"},{\"name\":\"StipendSummary\",\"type\":\"Collection(Cmc.Nexus.Models.StudentAccounts.StipendSummary)\"},{\"name\":\"Employer\",\"type\":\"Cmc.Nexus.Models.CareerServices.Employer\",\"referentialConstraint\":[{\"property\":\"EmployerId\",\"referencedProperty\":\"Id\"}]},{\"name\":\"EmploymentStatus\",\"type\":\"Cmc.Nexus.Models.CareerServices.EmploymentStatus\",\"referentialConstraint\":[{\"property\":\"EmploymentStatusId\",\"referencedProperty\":\"Id\"}]},{\"name\":\"StudentPlacementSummary\",\"type\":\"Collection(Cmc.Nexus.Models.CareerServices.StudentPlacementSummary)\"},{\"name\":\"EnrollmentPeriodFees\",\"type\":\"Collection(Cmc.Nexus.Models.Academics.StudentEnrollmentPeriodFee)\"},{\"name\":\"StudentServiceTypes\",\"type\":\"Collection(Cmc.Nexus.Models.StudentServices.StudentServiceType)\"},{\"name\":\"VeteranDetails\",\"type\":\"Collection(Cmc.Nexus.Models.StudentServices.StudentVeteranDetail)\"},{\"name\":\"DisabilityDetails\",\"type\":\"Collection(Cmc.Nexus.Models.StudentServices.StudentDisabilityDetail)\"},{\"name\":\"SchoolStatusHistory\",\"type\":\"Collection(Cmc.Nexus.Models.Common.StudentSchoolStatusHistory)\"},{\"name\":\"SchoolDefinedFieldValues\",\"type\":\"Collection(Cmc.Nexus.Models.Common.StudentSchoolDefinedFieldValue)\"},{\"name\":\"StudentGroups\",\"type\":\"Collection(Cmc.Nexus.Models.Common.StudentGroupMember)\"},{\"name\":\"RegistrationRules\",\"type\":\"Collection(Cmc.Nexus.Models.Academics.RegistrationRule)\"},{\"name\":\"SmsServiceProvider\",\"type\":\"Cmc.Nexus.Models.Crm.SmsServiceProvider\",\"referentialConstraint\":[{\"property\":\"SmsServiceProviderId\",\"referencedProperty\":\"Id\"}]},{\"name\":\"Program\",\"type\":\"Cmc.Nexus.Models.Academics.Program\",\"referentialConstraint\":[{\"property\":\"ProgramId\",\"referencedProperty\":\"Id\"}]},{\"name\":\"AgencyBranches\",\"type\":\"Collection(Cmc.Nexus.Models.Common.StudentAgencyBranch)\"},{\"name\":\"Country\",\"type\":\"Cmc.Nexus.Models.Common.Country\",\"referentialConstraint\":[{\"property\":\"CountryId\",\"referencedProperty\":\"Id\"}]},{\"name\":\"County\",\"type\":\"Cmc.Nexus.Models.Common.County\",\"referentialConstraint\":[{\"property\":\"CountyId\",\"referencedProperty\":\"Id\"}]},{\"name\":\"DataChanges\",\"type\":\"Collection(Cmc.Nexus.Models.Common.StudentDataChange)\"},{\"name\":\"Title\",\"type\":\"Cmc.Nexus.Models.Common.Title\",\"referentialConstraint\":[{\"property\":\"TitleId\",\"referencedProperty\":\"Id\"}]}]},{\"name\":\"FullName\",\"type\":\"Edm.String\"}],[{\"name\":\"Student\",\"key\":[{\"propertyRef\":[{\"name\":\"Id\"}]}],\"property\":[{\"name\":\"Id\",\"type\":\"Edm.Int32\"},{\"name\":\"AcgEligReasonCode\",\"type\":\"Edm.String\"},{\"name\":\"AgencyId\",\"type\":\"Edm.Int32\"},{\"name\":\"AlienNumber\",\"type\":\"Edm.String\"},{\"name\":\"ArAccountStatus\",\"type\":\"Edm.String\"},{\"name\":\"ArBalance\",\"type\":\"Edm.Decimal\"},{\"name\":\"ArNextTransactionNumber\",\"type\":\"Edm.Int16\"},{\"name\":\"AssignedAdmissionsRepId\",\"type\":\"Edm.Int32\"},{\"name\":\"AthleticIdentifier\",\"type\":\"Edm.String\"},{\"name\":\"BestTimeToContact\",\"type\":\"Edm.String\"},{\"name\":\"CampusId\",\"type\":\"Edm.Int32\"},{\"name\":\"CitizenId\",\"type\":\"Edm.Int32\"},{\"name\":\"City\",\"type\":\"Edm.String\"},{\"name\":\"CollegeId\",\"type\":\"Edm.Int32\"},{\"name\":\"CountryId\",\"type\":\"Edm.Int32\"},{\"name\":\"CountyId\",\"type\":\"Edm.Int32\"},{\"name\":\"CreatedDateTime\",\"type\":\"Edm.DateTimeOffset\"},{\"name\":\"CumulativeGpa\",\"type\":\"Edm.Decimal\"},{\"name\":\"CumulativeGpaPoints\",\"type\":\"Edm.Decimal\"},{\"name\":\"CurrencyCodeId\",\"type\":\"Edm.Int32\"},{\"name\":\"CurrentLda\",\"type\":\"Edm.DateTimeOffset\"},{\"name\":\"DataBlockIndicator\",\"type\":\"Edm.Boolean\"},{\"name\":\"DateOfBirth\",\"type\":\"Edm.DateTimeOffset\"},{\"name\":\"DbiModifiedDate\",\"type\":\"Edm.DateTimeOffset\"},{\"name\":\"DefaultAddressCode\",\"type\":\"Edm.String\"},{\"name\":\"DefaultMasterStudentAddressId\",\"type\":\"Edm.Int32\"},{\"name\":\"DefaultStudentAddressId\",\"type\":\"Edm.Int32\"},{\"name\":\"Disabled\",\"type\":\"Edm.String\"},{\"name\":\"DriverLicenseNumber\",\"type\":\"Edm.String\"},{\"name\":\"DriverLicenseState\",\"type\":\"Edm.String\"},{\"name\":\"EmailAddress\",\"type\":\"Edm.String\"},{\"name\":\"EmployerId\",\"type\":\"Edm.Int32\"},{\"name\":\"EmploymentStatusId\",\"type\":\"Edm.Int32\"},{\"name\":\"ExtraCurricularActivityId\",\"type\":\"Edm.Int32\"},{\"name\":\"FaGradPlusCounselingDate\",\"type\":\"Edm.DateTimeOffset\"},{\"name\":\"FaRigorousHighSchoolProgramCodeId\",\"type\":\"Edm.Int32\"},{\"name\":\"FirstName\",\"type\":\"Edm.String\"},{\"name\":\"FullName\",\"type\":\"Edm.String\"},{\"name\":\"GenderId\",\"type\":\"Edm.Int32\"},{\"name\":\"GpaCredits\",\"type\":\"Edm.Decimal\"},{\"name\":\"HispanicLatino\",\"type\":\"Edm.String\"},{\"name\":\"HsAcademicGpa\",\"type\":\"Edm.Decimal\"},{\"name\":\"IsActive\",\"type\":\"Edm.Boolean\"},{\"name\":\"IsAllowedBulkRegistrationByTrack\",\"type\":\"Edm.Boolean\"},{\"name\":\"IsBadAddress\",\"type\":\"Edm.Boolean\"},{\"name\":\"IsBadPhone\",\"type\":\"Edm.Boolean\"},{\"name\":\"IsDdVeteran\",\"type\":\"Edm.Boolean\"},{\"name\":\"IsEftDefaultForStipends\",\"type\":\"Edm.Boolean\"},{\"name\":\"IsExcludedCrmIntegration\",\"type\":\"Edm.Boolean\"},{\"name\":\"IsInDistrict\",\"type\":\"Edm.Boolean\"},{\"name\":\"IsSscrError11Received\",\"type\":\"Edm.Boolean\"},{\"name\":\"LastActivityDate\",\"type\":\"Edm.DateTimeOffset\"},{\"name\":\"LastInterestDate\",\"type\":\"Edm.DateTimeOffset\"},{\"name\":\"LastModifiedDateTime\",\"type\":\"Edm.DateTimeOffset\"},{\"name\":\"LastModifiedUserId\",\"type\":\"Edm.Int32\"},{\"name\":\"LastName\",\"type\":\"Edm.String\"},{\"name\":\"LastNameFirstFour\",\"type\":\"Edm.String\"},{\"name\":\"LastStatementBeginDate\",\"type\":\"Edm.DateTimeOffset\"},{\"name\":\"LastStatementCloseDate\",\"type\":\"Edm.DateTimeOffset\"},{\"name\":\"LastStatementDate\",\"type\":\"Edm.DateTimeOffset\"},{\"name\":\"LeadDate\",\"type\":\"Edm.DateTimeOffset\"},{\"name\":\"LeadSourceId\",\"type\":\"Edm.Int32\"},{\"name\":\"LeadTypeId\",\"type\":\"Edm.Int32\"},{\"name\":\"MaidenName\",\"type\":\"Edm.String\"},{\"name\":\"MaritalStatusId\",\"type\":\"Edm.Int32\"},{\"name\":\"Mi\",\"type\":\"Edm.String\"},{\"name\":\"MiddleName\",\"type\":\"Edm.String\"},{\"name\":\"MobilePhoneNumber\",\"type\":\"Edm.String\"},{\"name\":\"NationalityId\",\"type\":\"Edm.Int32\"},{\"name\":\"NickName\",\"type\":\"Edm.String\"},{\"name\":\"NiStudent\",\"type\":\"Edm.Boolean\"},{\"name\":\"Note\",\"type\":\"Edm.String\"},{\"name\":\"OriginalAssignedAdmissionsRepId\",\"type\":\"Edm.Int32\"},{\"name\":\"OriginalExpectedStartDate\",\"type\":\"Edm.DateTimeOffset\"},{\"name\":\"OriginalStartDate\",\"type\":\"Edm.DateTimeOffset\"},{\"name\":\"OtherEmailAddress\",\"type\":\"Edm.String\"},{\"name\":\"OtherPhoneNumber\",\"type\":\"Edm.String\"},{\"name\":\"PersonId\",\"type\":\"Edm.Int32\"},{\"name\":\"PhoneNumber\",\"type\":\"Edm.String\"},{\"name\":\"Pin\",\"type\":\"Edm.Decimal\"},{\"name\":\"PostalCode\",\"type\":\"Edm.String\"},{\"name\":\"PostalCodeFirstThree\",\"type\":\"Edm.String\"},{\"name\":\"PreviousEducationGpa\",\"type\":\"Edm.Decimal\"},{\"name\":\"PreviousEducationId\",\"type\":\"Edm.Int32\"},{\"name\":\"ProgramGroupId\",\"type\":\"Edm.Int32\"},{\"name\":\"ProgramId\",\"type\":\"Edm.Int32\"},{\"name\":\"RawFirstName\",\"type\":\"Edm.String\"},{\"name\":\"RawLastName\",\"type\":\"Edm.String\"},{\"name\":\"RawPhoneNumber\",\"type\":\"Edm.String\"},{\"name\":\"SchoolStatusId\",\"type\":\"Edm.Int32\"},{\"name\":\"ShiftId\",\"type\":\"Edm.Int32\"},{\"name\":\"SmsServiceProviderId\",\"type\":\"Edm.Int32\"},{\"name\":\"SourceSystem\",\"type\":\"Edm.String\"},{\"name\":\"Ssn\",\"type\":\"Edm.String\"},{\"name\":\"StartDate\",\"type\":\"Edm.DateTimeOffset\"},{\"name\":\"State\",\"type\":\"Edm.String\"},{\"name\":\"StatementComment\",\"type\":\"Edm.String\"},{\"name\":\"StreetAddress\",\"type\":\"Edm.String\"},{\"name\":\"StreetAddress2\",\"type\":\"Edm.String\"},{\"name\":\"StudentIdentifier\",\"type\":\"Edm.String\"},{\"name\":\"StudentNumber\",\"type\":\"Edm.String\"},{\"name\":\"SubscribeToSms\",\"type\":\"Edm.Boolean\"},{\"name\":\"Suffix\",\"type\":\"Edm.String\"},{\"name\":\"SuffixId\",\"type\":\"Edm.Int32\"},{\"name\":\"TitleId\",\"type\":\"Edm.Int32\"},{\"name\":\"Veteran\",\"type\":\"Edm.String\"},{\"name\":\"WorkPhoneNumber\",\"type\":\"Edm.String\"},{\"name\":\"WorkPhoneNumberExtension\",\"type\":\"Edm.String\"}],\"navigationProperty\":[{\"name\":\"CurrencyCode\",\"type\":\"Cmc.Nexus.Models.Common.CurrencyCode\",\"referentialConstraint\":[{\"property\":\"CurrencyCodeId\",\"referencedProperty\":\"Id\"}]},{\"name\":\"Shift\",\"type\":\"Cmc.Nexus.Models.Academics.Shift\",\"referentialConstraint\":[{\"property\":\"ShiftId\",\"referencedProperty\":\"Id\"}]},{\"name\":\"SchoolStatus\",\"type\":\"Cmc.Nexus.Models.Common.SchoolStatus\",\"referentialConstraint\":[{\"property\":\"SchoolStatusId\",\"referencedProperty\":\"Id\"}]},{\"name\":\"Person\",\"type\":\"Cmc.Nexus.Models.Common.Person\",\"referentialConstraint\":[{\"property\":\"PersonId\",\"referencedProperty\":\"Id\"}]},{\"name\":\"Tasks\",\"type\":\"Collection(Cmc.Nexus.Models.Crm.Task)\"},{\"name\":\"StudentEthnicities\",\"type\":\"Collection(Cmc.Nexus.Models.Common.StudentEthnicity)\"},{\"name\":\"Documents\",\"type\":\"Collection(Cmc.Nexus.Models.Crm.Document)\"},{\"name\":\"EnrollmentPeriods\",\"type\":\"Collection(Cmc.Nexus.Models.Academics.StudentEnrollmentPeriod)\"},{\"name\":\"TermSummaries\",\"type\":\"Collection(Cmc.Nexus.Models.Academics.StudentEnrollmentTermSummary)\"},{\"name\":\"StudentCourses\",\"type\":\"Collection(Cmc.Nexus.Models.Academics.StudentCourse)\"},{\"name\":\"StudentCourseStatusChanges\",\"type\":\"Collection(Cmc.Nexus.Models.Academics.StudentCourseStatusChange)\"},{\"name\":\"StudentGPAs\",\"type\":\"Collection(Cmc.Nexus.Models.Academics.StudentGpa)\"},{\"name\":\"TransferCredits\",\"type\":\"Collection(Cmc.Nexus.Models.Admissions.StudentTransferCredit)\"},{\"name\":\"SecondaryLeadSources\",\"type\":\"Collection(Cmc.Nexus.Models.Admissions.ProspectInquiryLeadSource)\"},{\"name\":\"StudentPreviousEducation\",\"type\":\"Collection(Cmc.Nexus.Models.Admissions.StudentPreviousEducation)\"},{\"name\":\"TranscriptRequests\",\"type\":\"Collection(Cmc.Nexus.Models.Crm.TranscriptRequest)\"},{\"name\":\"ClearingHouseExportDetailRecords\",\"type\":\"Collection(Cmc.Nexus.Models.FinancialAid.ClearinghouseExportRecord)\"},{\"name\":\"PaidDisbursements\",\"type\":\"Collection(Cmc.Nexus.Models.FinancialAid.PaidDisbursement)\"},{\"name\":\"Advisors\",\"type\":\"Collection(Cmc.Nexus.Models.Common.StudentEnrollmentPeriodAdvisor)\"},{\"name\":\"FaAwards\",\"type\":\"Collection(Cmc.Nexus.Models.FinancialAid.StudentAward)\"},{\"name\":\"Campus\",\"type\":\"Cmc.Nexus.Models.Common.Campus\",\"referentialConstraint\":[{\"property\":\"CampusId\",\"referencedProperty\":\"Id\"}]},{\"name\":\"FaApplicationProcess\",\"type\":\"Collection(Cmc.Nexus.Models.FinancialAid.StudentAwardPell)\"},{\"name\":\"CollectionAccounts\",\"type\":\"Collection(Cmc.Nexus.Models.StudentAccounts.CollectionAccount)\"},{\"name\":\"StudentAccountTransactions\",\"type\":\"Collection(Cmc.Nexus.Models.StudentAccounts.StudentAccountTransaction)\"},{\"name\":\"StudentAccountPendingTransactions\",\"type\":\"Collection(Cmc.Nexus.Models.StudentAccounts.StudentAccountPendingTransaction)\"},{\"name\":\"ExtraCurricularActivities\",\"type\":\"Collection(Cmc.Nexus.Models.Admissions.StudentExtraCurricularActivity)\"},{\"name\":\"StudentRt4Calculation\",\"type\":\"Collection(Cmc.Nexus.Models.StudentAccounts.StudentRt4Calculation)\"},{\"name\":\"StipendSummary\",\"type\":\"Collection(Cmc.Nexus.Models.StudentAccounts.StipendSummary)\"},{\"name\":\"Employer\",\"type\":\"Cmc.Nexus.Models.CareerServices.Employer\",\"referentialConstraint\":[{\"property\":\"EmployerId\",\"referencedProperty\":\"Id\"}]},{\"name\":\"EmploymentStatus\",\"type\":\"Cmc.Nexus.Models.CareerServices.EmploymentStatus\",\"referentialConstraint\":[{\"property\":\"EmploymentStatusId\",\"referencedProperty\":\"Id\"}]},{\"name\":\"StudentPlacementSummary\",\"type\":\"Collection(Cmc.Nexus.Models.CareerServices.StudentPlacementSummary)\"},{\"name\":\"EnrollmentPeriodFees\",\"type\":\"Collection(Cmc.Nexus.Models.Academics.StudentEnrollmentPeriodFee)\"},{\"name\":\"StudentServiceTypes\",\"type\":\"Collection(Cmc.Nexus.Models.StudentServices.StudentServiceType)\"},{\"name\":\"VeteranDetails\",\"type\":\"Collection(Cmc.Nexus.Models.StudentServices.StudentVeteranDetail)\"},{\"name\":\"DisabilityDetails\",\"type\":\"Collection(Cmc.Nexus.Models.StudentServices.StudentDisabilityDetail)\"},{\"name\":\"SchoolStatusHistory\",\"type\":\"Collection(Cmc.Nexus.Models.Common.StudentSchoolStatusHistory)\"},{\"name\":\"SchoolDefinedFieldValues\",\"type\":\"Collection(Cmc.Nexus.Models.Common.StudentSchoolDefinedFieldValue)\"},{\"name\":\"StudentGroups\",\"type\":\"Collection(Cmc.Nexus.Models.Common.StudentGroupMember)\"},{\"name\":\"RegistrationRules\",\"type\":\"Collection(Cmc.Nexus.Models.Academics.RegistrationRule)\"},{\"name\":\"SmsServiceProvider\",\"type\":\"Cmc.Nexus.Models.Crm.SmsServiceProvider\",\"referentialConstraint\":[{\"property\":\"SmsServiceProviderId\",\"referencedProperty\":\"Id\"}]},{\"name\":\"Program\",\"type\":\"Cmc.Nexus.Models.Academics.Program\",\"referentialConstraint\":[{\"property\":\"ProgramId\",\"referencedProperty\":\"Id\"}]},{\"name\":\"AgencyBranches\",\"type\":\"Collection(Cmc.Nexus.Models.Common.StudentAgencyBranch)\"},{\"name\":\"Country\",\"type\":\"Cmc.Nexus.Models.Common.Country\",\"referentialConstraint\":[{\"property\":\"CountryId\",\"referencedProperty\":\"Id\"}]},{\"name\":\"County\",\"type\":\"Cmc.Nexus.Models.Common.County\",\"referentialConstraint\":[{\"property\":\"CountyId\",\"referencedProperty\":\"Id\"}]},{\"name\":\"DataChanges\",\"type\":\"Collection(Cmc.Nexus.Models.Common.StudentDataChange)\"},{\"name\":\"Title\",\"type\":\"Cmc.Nexus.Models.Common.Title\",\"referentialConstraint\":[{\"property\":\"TitleId\",\"referencedProperty\":\"Id\"}]}]},{\"name\":\"LastName\",\"type\":\"Edm.String\"}],[{\"name\":\"Student\",\"key\":[{\"propertyRef\":[{\"name\":\"Id\"}]}],\"property\":[{\"name\":\"Id\",\"type\":\"Edm.Int32\"},{\"name\":\"AcgEligReasonCode\",\"type\":\"Edm.String\"},{\"name\":\"AgencyId\",\"type\":\"Edm.Int32\"},{\"name\":\"AlienNumber\",\"type\":\"Edm.String\"},{\"name\":\"ArAccountStatus\",\"type\":\"Edm.String\"},{\"name\":\"ArBalance\",\"type\":\"Edm.Decimal\"},{\"name\":\"ArNextTransactionNumber\",\"type\":\"Edm.Int16\"},{\"name\":\"AssignedAdmissionsRepId\",\"type\":\"Edm.Int32\"},{\"name\":\"AthleticIdentifier\",\"type\":\"Edm.String\"},{\"name\":\"BestTimeToContact\",\"type\":\"Edm.String\"},{\"name\":\"CampusId\",\"type\":\"Edm.Int32\"},{\"name\":\"CitizenId\",\"type\":\"Edm.Int32\"},{\"name\":\"City\",\"type\":\"Edm.String\"},{\"name\":\"CollegeId\",\"type\":\"Edm.Int32\"},{\"name\":\"CountryId\",\"type\":\"Edm.Int32\"},{\"name\":\"CountyId\",\"type\":\"Edm.Int32\"},{\"name\":\"CreatedDateTime\",\"type\":\"Edm.DateTimeOffset\"},{\"name\":\"CumulativeGpa\",\"type\":\"Edm.Decimal\"},{\"name\":\"CumulativeGpaPoints\",\"type\":\"Edm.Decimal\"},{\"name\":\"CurrencyCodeId\",\"type\":\"Edm.Int32\"},{\"name\":\"CurrentLda\",\"type\":\"Edm.DateTimeOffset\"},{\"name\":\"DataBlockIndicator\",\"type\":\"Edm.Boolean\"},{\"name\":\"DateOfBirth\",\"type\":\"Edm.DateTimeOffset\"},{\"name\":\"DbiModifiedDate\",\"type\":\"Edm.DateTimeOffset\"},{\"name\":\"DefaultAddressCode\",\"type\":\"Edm.String\"},{\"name\":\"DefaultMasterStudentAddressId\",\"type\":\"Edm.Int32\"},{\"name\":\"DefaultStudentAddressId\",\"type\":\"Edm.Int32\"},{\"name\":\"Disabled\",\"type\":\"Edm.String\"},{\"name\":\"DriverLicenseNumber\",\"type\":\"Edm.String\"},{\"name\":\"DriverLicenseState\",\"type\":\"Edm.String\"},{\"name\":\"EmailAddress\",\"type\":\"Edm.String\"},{\"name\":\"EmployerId\",\"type\":\"Edm.Int32\"},{\"name\":\"EmploymentStatusId\",\"type\":\"Edm.Int32\"},{\"name\":\"ExtraCurricularActivityId\",\"type\":\"Edm.Int32\"},{\"name\":\"FaGradPlusCounselingDate\",\"type\":\"Edm.DateTimeOffset\"},{\"name\":\"FaRigorousHighSchoolProgramCodeId\",\"type\":\"Edm.Int32\"},{\"name\":\"FirstName\",\"type\":\"Edm.String\"},{\"name\":\"FullName\",\"type\":\"Edm.String\"},{\"name\":\"GenderId\",\"type\":\"Edm.Int32\"},{\"name\":\"GpaCredits\",\"type\":\"Edm.Decimal\"},{\"name\":\"HispanicLatino\",\"type\":\"Edm.String\"},{\"name\":\"HsAcademicGpa\",\"type\":\"Edm.Decimal\"},{\"name\":\"IsActive\",\"type\":\"Edm.Boolean\"},{\"name\":\"IsAllowedBulkRegistrationByTrack\",\"type\":\"Edm.Boolean\"},{\"name\":\"IsBadAddress\",\"type\":\"Edm.Boolean\"},{\"name\":\"IsBadPhone\",\"type\":\"Edm.Boolean\"},{\"name\":\"IsDdVeteran\",\"type\":\"Edm.Boolean\"},{\"name\":\"IsEftDefaultForStipends\",\"type\":\"Edm.Boolean\"},{\"name\":\"IsExcludedCrmIntegration\",\"type\":\"Edm.Boolean\"},{\"name\":\"IsInDistrict\",\"type\":\"Edm.Boolean\"},{\"name\":\"IsSscrError11Received\",\"type\":\"Edm.Boolean\"},{\"name\":\"LastActivityDate\",\"type\":\"Edm.DateTimeOffset\"},{\"name\":\"LastInterestDate\",\"type\":\"Edm.DateTimeOffset\"},{\"name\":\"LastModifiedDateTime\",\"type\":\"Edm.DateTimeOffset\"},{\"name\":\"LastModifiedUserId\",\"type\":\"Edm.Int32\"},{\"name\":\"LastName\",\"type\":\"Edm.String\"},{\"name\":\"LastNameFirstFour\",\"type\":\"Edm.String\"},{\"name\":\"LastStatementBeginDate\",\"type\":\"Edm.DateTimeOffset\"},{\"name\":\"LastStatementCloseDate\",\"type\":\"Edm.DateTimeOffset\"},{\"name\":\"LastStatementDate\",\"type\":\"Edm.DateTimeOffset\"},{\"name\":\"LeadDate\",\"type\":\"Edm.DateTimeOffset\"},{\"name\":\"LeadSourceId\",\"type\":\"Edm.Int32\"},{\"name\":\"LeadTypeId\",\"type\":\"Edm.Int32\"},{\"name\":\"MaidenName\",\"type\":\"Edm.String\"},{\"name\":\"MaritalStatusId\",\"type\":\"Edm.Int32\"},{\"name\":\"Mi\",\"type\":\"Edm.String\"},{\"name\":\"MiddleName\",\"type\":\"Edm.String\"},{\"name\":\"MobilePhoneNumber\",\"type\":\"Edm.String\"},{\"name\":\"NationalityId\",\"type\":\"Edm.Int32\"},{\"name\":\"NickName\",\"type\":\"Edm.String\"},{\"name\":\"NiStudent\",\"type\":\"Edm.Boolean\"},{\"name\":\"Note\",\"type\":\"Edm.String\"},{\"name\":\"OriginalAssignedAdmissionsRepId\",\"type\":\"Edm.Int32\"},{\"name\":\"OriginalExpectedStartDate\",\"type\":\"Edm.DateTimeOffset\"},{\"name\":\"OriginalStartDate\",\"type\":\"Edm.DateTimeOffset\"},{\"name\":\"OtherEmailAddress\",\"type\":\"Edm.String\"},{\"name\":\"OtherPhoneNumber\",\"type\":\"Edm.String\"},{\"name\":\"PersonId\",\"type\":\"Edm.Int32\"},{\"name\":\"PhoneNumber\",\"type\":\"Edm.String\"},{\"name\":\"Pin\",\"type\":\"Edm.Decimal\"},{\"name\":\"PostalCode\",\"type\":\"Edm.String\"},{\"name\":\"PostalCodeFirstThree\",\"type\":\"Edm.String\"},{\"name\":\"PreviousEducationGpa\",\"type\":\"Edm.Decimal\"},{\"name\":\"PreviousEducationId\",\"type\":\"Edm.Int32\"},{\"name\":\"ProgramGroupId\",\"type\":\"Edm.Int32\"},{\"name\":\"ProgramId\",\"type\":\"Edm.Int32\"},{\"name\":\"RawFirstName\",\"type\":\"Edm.String\"},{\"name\":\"RawLastName\",\"type\":\"Edm.String\"},{\"name\":\"RawPhoneNumber\",\"type\":\"Edm.String\"},{\"name\":\"SchoolStatusId\",\"type\":\"Edm.Int32\"},{\"name\":\"ShiftId\",\"type\":\"Edm.Int32\"},{\"name\":\"SmsServiceProviderId\",\"type\":\"Edm.Int32\"},{\"name\":\"SourceSystem\",\"type\":\"Edm.String\"},{\"name\":\"Ssn\",\"type\":\"Edm.String\"},{\"name\":\"StartDate\",\"type\":\"Edm.DateTimeOffset\"},{\"name\":\"State\",\"type\":\"Edm.String\"},{\"name\":\"StatementComment\",\"type\":\"Edm.String\"},{\"name\":\"StreetAddress\",\"type\":\"Edm.String\"},{\"name\":\"StreetAddress2\",\"type\":\"Edm.String\"},{\"name\":\"StudentIdentifier\",\"type\":\"Edm.String\"},{\"name\":\"StudentNumber\",\"type\":\"Edm.String\"},{\"name\":\"SubscribeToSms\",\"type\":\"Edm.Boolean\"},{\"name\":\"Suffix\",\"type\":\"Edm.String\"},{\"name\":\"SuffixId\",\"type\":\"Edm.Int32\"},{\"name\":\"TitleId\",\"type\":\"Edm.Int32\"},{\"name\":\"Veteran\",\"type\":\"Edm.String\"},{\"name\":\"WorkPhoneNumber\",\"type\":\"Edm.String\"},{\"name\":\"WorkPhoneNumberExtension\",\"type\":\"Edm.String\"}],\"navigationProperty\":[{\"name\":\"CurrencyCode\",\"type\":\"Cmc.Nexus.Models.Common.CurrencyCode\",\"referentialConstraint\":[{\"property\":\"CurrencyCodeId\",\"referencedProperty\":\"Id\"}]},{\"name\":\"Shift\",\"type\":\"Cmc.Nexus.Models.Academics.Shift\",\"referentialConstraint\":[{\"property\":\"ShiftId\",\"referencedProperty\":\"Id\"}]},{\"name\":\"SchoolStatus\",\"type\":\"Cmc.Nexus.Models.Common.SchoolStatus\",\"referentialConstraint\":[{\"property\":\"SchoolStatusId\",\"referencedProperty\":\"Id\"}]},{\"name\":\"Person\",\"type\":\"Cmc.Nexus.Models.Common.Person\",\"referentialConstraint\":[{\"property\":\"PersonId\",\"referencedProperty\":\"Id\"}]},{\"name\":\"Tasks\",\"type\":\"Collection(Cmc.Nexus.Models.Crm.Task)\"},{\"name\":\"StudentEthnicities\",\"type\":\"Collection(Cmc.Nexus.Models.Common.StudentEthnicity)\"},{\"name\":\"Documents\",\"type\":\"Collection(Cmc.Nexus.Models.Crm.Document)\"},{\"name\":\"EnrollmentPeriods\",\"type\":\"Collection(Cmc.Nexus.Models.Academics.StudentEnrollmentPeriod)\"},{\"name\":\"TermSummaries\",\"type\":\"Collection(Cmc.Nexus.Models.Academics.StudentEnrollmentTermSummary)\"},{\"name\":\"StudentCourses\",\"type\":\"Collection(Cmc.Nexus.Models.Academics.StudentCourse)\"},{\"name\":\"StudentCourseStatusChanges\",\"type\":\"Collection(Cmc.Nexus.Models.Academics.StudentCourseStatusChange)\"},{\"name\":\"StudentGPAs\",\"type\":\"Collection(Cmc.Nexus.Models.Academics.StudentGpa)\"},{\"name\":\"TransferCredits\",\"type\":\"Collection(Cmc.Nexus.Models.Admissions.StudentTransferCredit)\"},{\"name\":\"SecondaryLeadSources\",\"type\":\"Collection(Cmc.Nexus.Models.Admissions.ProspectInquiryLeadSource)\"},{\"name\":\"StudentPreviousEducation\",\"type\":\"Collection(Cmc.Nexus.Models.Admissions.StudentPreviousEducation)\"},{\"name\":\"TranscriptRequests\",\"type\":\"Collection(Cmc.Nexus.Models.Crm.TranscriptRequest)\"},{\"name\":\"ClearingHouseExportDetailRecords\",\"type\":\"Collection(Cmc.Nexus.Models.FinancialAid.ClearinghouseExportRecord)\"},{\"name\":\"PaidDisbursements\",\"type\":\"Collection(Cmc.Nexus.Models.FinancialAid.PaidDisbursement)\"},{\"name\":\"Advisors\",\"type\":\"Collection(Cmc.Nexus.Models.Common.StudentEnrollmentPeriodAdvisor)\"},{\"name\":\"FaAwards\",\"type\":\"Collection(Cmc.Nexus.Models.FinancialAid.StudentAward)\"},{\"name\":\"Campus\",\"type\":\"Cmc.Nexus.Models.Common.Campus\",\"referentialConstraint\":[{\"property\":\"CampusId\",\"referencedProperty\":\"Id\"}]},{\"name\":\"FaApplicationProcess\",\"type\":\"Collection(Cmc.Nexus.Models.FinancialAid.StudentAwardPell)\"},{\"name\":\"CollectionAccounts\",\"type\":\"Collection(Cmc.Nexus.Models.StudentAccounts.CollectionAccount)\"},{\"name\":\"StudentAccountTransactions\",\"type\":\"Collection(Cmc.Nexus.Models.StudentAccounts.StudentAccountTransaction)\"},{\"name\":\"StudentAccountPendingTransactions\",\"type\":\"Collection(Cmc.Nexus.Models.StudentAccounts.StudentAccountPendingTransaction)\"},{\"name\":\"ExtraCurricularActivities\",\"type\":\"Collection(Cmc.Nexus.Models.Admissions.StudentExtraCurricularActivity)\"},{\"name\":\"StudentRt4Calculation\",\"type\":\"Collection(Cmc.Nexus.Models.StudentAccounts.StudentRt4Calculation)\"},{\"name\":\"StipendSummary\",\"type\":\"Collection(Cmc.Nexus.Models.StudentAccounts.StipendSummary)\"},{\"name\":\"Employer\",\"type\":\"Cmc.Nexus.Models.CareerServices.Employer\",\"referentialConstraint\":[{\"property\":\"EmployerId\",\"referencedProperty\":\"Id\"}]},{\"name\":\"EmploymentStatus\",\"type\":\"Cmc.Nexus.Models.CareerServices.EmploymentStatus\",\"referentialConstraint\":[{\"property\":\"EmploymentStatusId\",\"referencedProperty\":\"Id\"}]},{\"name\":\"StudentPlacementSummary\",\"type\":\"Collection(Cmc.Nexus.Models.CareerServices.StudentPlacementSummary)\"},{\"name\":\"EnrollmentPeriodFees\",\"type\":\"Collection(Cmc.Nexus.Models.Academics.StudentEnrollmentPeriodFee)\"},{\"name\":\"StudentServiceTypes\",\"type\":\"Collection(Cmc.Nexus.Models.StudentServices.StudentServiceType)\"},{\"name\":\"VeteranDetails\",\"type\":\"Collection(Cmc.Nexus.Models.StudentServices.StudentVeteranDetail)\"},{\"name\":\"DisabilityDetails\",\"type\":\"Collection(Cmc.Nexus.Models.StudentServices.StudentDisabilityDetail)\"},{\"name\":\"SchoolStatusHistory\",\"type\":\"Collection(Cmc.Nexus.Models.Common.StudentSchoolStatusHistory)\"},{\"name\":\"SchoolDefinedFieldValues\",\"type\":\"Collection(Cmc.Nexus.Models.Common.StudentSchoolDefinedFieldValue)\"},{\"name\":\"StudentGroups\",\"type\":\"Collection(Cmc.Nexus.Models.Common.StudentGroupMember)\"},{\"name\":\"RegistrationRules\",\"type\":\"Collection(Cmc.Nexus.Models.Academics.RegistrationRule)\"},{\"name\":\"SmsServiceProvider\",\"type\":\"Cmc.Nexus.Models.Crm.SmsServiceProvider\",\"referentialConstraint\":[{\"property\":\"SmsServiceProviderId\",\"referencedProperty\":\"Id\"}]},{\"name\":\"Program\",\"type\":\"Cmc.Nexus.Models.Academics.Program\",\"referentialConstraint\":[{\"property\":\"ProgramId\",\"referencedProperty\":\"Id\"}]},{\"name\":\"AgencyBranches\",\"type\":\"Collection(Cmc.Nexus.Models.Common.StudentAgencyBranch)\"},{\"name\":\"Country\",\"type\":\"Cmc.Nexus.Models.Common.Country\",\"referentialConstraint\":[{\"property\":\"CountryId\",\"referencedProperty\":\"Id\"}]},{\"name\":\"County\",\"type\":\"Cmc.Nexus.Models.Common.County\",\"referentialConstraint\":[{\"property\":\"CountyId\",\"referencedProperty\":\"Id\"}]},{\"name\":\"DataChanges\",\"type\":\"Collection(Cmc.Nexus.Models.Common.StudentDataChange)\"},{\"name\":\"Title\",\"type\":\"Cmc.Nexus.Models.Common.Title\",\"referentialConstraint\":[{\"property\":\"TitleId\",\"referencedProperty\":\"Id\"}]}]},{\"name\":\"Id\",\"type\":\"Edm.Int32\"}]]",
							"SelectedSortColumns": "[]",
							"Filters": "[{\"id\":\"35b0840f-3436-4a38-8986-6beea2eab594\",\"filter\":{\"code\":\"eq\",\"displayName\":\"equals\",\"stringFormat\":\"{0} eq '{1}'\",\"inputType\":\"string\",\"key\":0},\"filterValue\":\"nitin\",\"logicalOperator\":\"and\",\"propertyEdmPath\":[{\"name\":\"Student\",\"key\":[{\"propertyRef\":[{\"name\":\"Id\"}]}],\"property\":[{\"name\":\"Id\",\"type\":\"Edm.Int32\"},{\"name\":\"AcgEligReasonCode\",\"type\":\"Edm.String\"},{\"name\":\"AgencyId\",\"type\":\"Edm.Int32\"},{\"name\":\"AlienNumber\",\"type\":\"Edm.String\"},{\"name\":\"ArAccountStatus\",\"type\":\"Edm.String\"},{\"name\":\"ArBalance\",\"type\":\"Edm.Decimal\"},{\"name\":\"ArNextTransactionNumber\",\"type\":\"Edm.Int16\"},{\"name\":\"AssignedAdmissionsRepId\",\"type\":\"Edm.Int32\"},{\"name\":\"AthleticIdentifier\",\"type\":\"Edm.String\"},{\"name\":\"BestTimeToContact\",\"type\":\"Edm.String\"},{\"name\":\"CampusId\",\"type\":\"Edm.Int32\"},{\"name\":\"CitizenId\",\"type\":\"Edm.Int32\"},{\"name\":\"City\",\"type\":\"Edm.String\"},{\"name\":\"CollegeId\",\"type\":\"Edm.Int32\"},{\"name\":\"CountryId\",\"type\":\"Edm.Int32\"},{\"name\":\"CountyId\",\"type\":\"Edm.Int32\"},{\"name\":\"CreatedDateTime\",\"type\":\"Edm.DateTimeOffset\"},{\"name\":\"CumulativeGpa\",\"type\":\"Edm.Decimal\"},{\"name\":\"CumulativeGpaPoints\",\"type\":\"Edm.Decimal\"},{\"name\":\"CurrencyCodeId\",\"type\":\"Edm.Int32\"},{\"name\":\"CurrentLda\",\"type\":\"Edm.DateTimeOffset\"},{\"name\":\"DataBlockIndicator\",\"type\":\"Edm.Boolean\"},{\"name\":\"DateOfBirth\",\"type\":\"Edm.DateTimeOffset\"},{\"name\":\"DbiModifiedDate\",\"type\":\"Edm.DateTimeOffset\"},{\"name\":\"DefaultAddressCode\",\"type\":\"Edm.String\"},{\"name\":\"DefaultMasterStudentAddressId\",\"type\":\"Edm.Int32\"},{\"name\":\"DefaultStudentAddressId\",\"type\":\"Edm.Int32\"},{\"name\":\"Disabled\",\"type\":\"Edm.String\"},{\"name\":\"DriverLicenseNumber\",\"type\":\"Edm.String\"},{\"name\":\"DriverLicenseState\",\"type\":\"Edm.String\"},{\"name\":\"EmailAddress\",\"type\":\"Edm.String\"},{\"name\":\"EmployerId\",\"type\":\"Edm.Int32\"},{\"name\":\"EmploymentStatusId\",\"type\":\"Edm.Int32\"},{\"name\":\"ExtraCurricularActivityId\",\"type\":\"Edm.Int32\"},{\"name\":\"FaGradPlusCounselingDate\",\"type\":\"Edm.DateTimeOffset\"},{\"name\":\"FaRigorousHighSchoolProgramCodeId\",\"type\":\"Edm.Int32\"},{\"name\":\"FirstName\",\"type\":\"Edm.String\"},{\"name\":\"FullName\",\"type\":\"Edm.String\"},{\"name\":\"GenderId\",\"type\":\"Edm.Int32\"},{\"name\":\"GpaCredits\",\"type\":\"Edm.Decimal\"},{\"name\":\"HispanicLatino\",\"type\":\"Edm.String\"},{\"name\":\"HsAcademicGpa\",\"type\":\"Edm.Decimal\"},{\"name\":\"IsActive\",\"type\":\"Edm.Boolean\"},{\"name\":\"IsAllowedBulkRegistrationByTrack\",\"type\":\"Edm.Boolean\"},{\"name\":\"IsBadAddress\",\"type\":\"Edm.Boolean\"},{\"name\":\"IsBadPhone\",\"type\":\"Edm.Boolean\"},{\"name\":\"IsDdVeteran\",\"type\":\"Edm.Boolean\"},{\"name\":\"IsEftDefaultForStipends\",\"type\":\"Edm.Boolean\"},{\"name\":\"IsExcludedCrmIntegration\",\"type\":\"Edm.Boolean\"},{\"name\":\"IsInDistrict\",\"type\":\"Edm.Boolean\"},{\"name\":\"IsSscrError11Received\",\"type\":\"Edm.Boolean\"},{\"name\":\"LastActivityDate\",\"type\":\"Edm.DateTimeOffset\"},{\"name\":\"LastInterestDate\",\"type\":\"Edm.DateTimeOffset\"},{\"name\":\"LastModifiedDateTime\",\"type\":\"Edm.DateTimeOffset\"},{\"name\":\"LastModifiedUserId\",\"type\":\"Edm.Int32\"},{\"name\":\"LastName\",\"type\":\"Edm.String\"},{\"name\":\"LastNameFirstFour\",\"type\":\"Edm.String\"},{\"name\":\"LastStatementBeginDate\",\"type\":\"Edm.DateTimeOffset\"},{\"name\":\"LastStatementCloseDate\",\"type\":\"Edm.DateTimeOffset\"},{\"name\":\"LastStatementDate\",\"type\":\"Edm.DateTimeOffset\"},{\"name\":\"LeadDate\",\"type\":\"Edm.DateTimeOffset\"},{\"name\":\"LeadSourceId\",\"type\":\"Edm.Int32\"},{\"name\":\"LeadTypeId\",\"type\":\"Edm.Int32\"},{\"name\":\"MaidenName\",\"type\":\"Edm.String\"},{\"name\":\"MaritalStatusId\",\"type\":\"Edm.Int32\"},{\"name\":\"Mi\",\"type\":\"Edm.String\"},{\"name\":\"MiddleName\",\"type\":\"Edm.String\"},{\"name\":\"MobilePhoneNumber\",\"type\":\"Edm.String\"},{\"name\":\"NationalityId\",\"type\":\"Edm.Int32\"},{\"name\":\"NickName\",\"type\":\"Edm.String\"},{\"name\":\"NiStudent\",\"type\":\"Edm.Boolean\"},{\"name\":\"Note\",\"type\":\"Edm.String\"},{\"name\":\"OriginalAssignedAdmissionsRepId\",\"type\":\"Edm.Int32\"},{\"name\":\"OriginalExpectedStartDate\",\"type\":\"Edm.DateTimeOffset\"},{\"name\":\"OriginalStartDate\",\"type\":\"Edm.DateTimeOffset\"},{\"name\":\"OtherEmailAddress\",\"type\":\"Edm.String\"},{\"name\":\"OtherPhoneNumber\",\"type\":\"Edm.String\"},{\"name\":\"PersonId\",\"type\":\"Edm.Int32\"},{\"name\":\"PhoneNumber\",\"type\":\"Edm.String\"},{\"name\":\"Pin\",\"type\":\"Edm.Decimal\"},{\"name\":\"PostalCode\",\"type\":\"Edm.String\"},{\"name\":\"PostalCodeFirstThree\",\"type\":\"Edm.String\"},{\"name\":\"PreviousEducationGpa\",\"type\":\"Edm.Decimal\"},{\"name\":\"PreviousEducationId\",\"type\":\"Edm.Int32\"},{\"name\":\"ProgramGroupId\",\"type\":\"Edm.Int32\"},{\"name\":\"ProgramId\",\"type\":\"Edm.Int32\"},{\"name\":\"RawFirstName\",\"type\":\"Edm.String\"},{\"name\":\"RawLastName\",\"type\":\"Edm.String\"},{\"name\":\"RawPhoneNumber\",\"type\":\"Edm.String\"},{\"name\":\"SchoolStatusId\",\"type\":\"Edm.Int32\"},{\"name\":\"ShiftId\",\"type\":\"Edm.Int32\"},{\"name\":\"SmsServiceProviderId\",\"type\":\"Edm.Int32\"},{\"name\":\"SourceSystem\",\"type\":\"Edm.String\"},{\"name\":\"Ssn\",\"type\":\"Edm.String\"},{\"name\":\"StartDate\",\"type\":\"Edm.DateTimeOffset\"},{\"name\":\"State\",\"type\":\"Edm.String\"},{\"name\":\"StatementComment\",\"type\":\"Edm.String\"},{\"name\":\"StreetAddress\",\"type\":\"Edm.String\"},{\"name\":\"StreetAddress2\",\"type\":\"Edm.String\"},{\"name\":\"StudentIdentifier\",\"type\":\"Edm.String\"},{\"name\":\"StudentNumber\",\"type\":\"Edm.String\"},{\"name\":\"SubscribeToSms\",\"type\":\"Edm.Boolean\"},{\"name\":\"Suffix\",\"type\":\"Edm.String\"},{\"name\":\"SuffixId\",\"type\":\"Edm.Int32\"},{\"name\":\"TitleId\",\"type\":\"Edm.Int32\"},{\"name\":\"Veteran\",\"type\":\"Edm.String\"},{\"name\":\"WorkPhoneNumber\",\"type\":\"Edm.String\"},{\"name\":\"WorkPhoneNumberExtension\",\"type\":\"Edm.String\"}],\"navigationProperty\":[{\"name\":\"CurrencyCode\",\"type\":\"Cmc.Nexus.Models.Common.CurrencyCode\",\"referentialConstraint\":[{\"property\":\"CurrencyCodeId\",\"referencedProperty\":\"Id\"}]},{\"name\":\"Shift\",\"type\":\"Cmc.Nexus.Models.Academics.Shift\",\"referentialConstraint\":[{\"property\":\"ShiftId\",\"referencedProperty\":\"Id\"}]},{\"name\":\"SchoolStatus\",\"type\":\"Cmc.Nexus.Models.Common.SchoolStatus\",\"referentialConstraint\":[{\"property\":\"SchoolStatusId\",\"referencedProperty\":\"Id\"}]},{\"name\":\"Person\",\"type\":\"Cmc.Nexus.Models.Common.Person\",\"referentialConstraint\":[{\"property\":\"PersonId\",\"referencedProperty\":\"Id\"}]},{\"name\":\"Tasks\",\"type\":\"Collection(Cmc.Nexus.Models.Crm.Task)\"},{\"name\":\"StudentEthnicities\",\"type\":\"Collection(Cmc.Nexus.Models.Common.StudentEthnicity)\"},{\"name\":\"Documents\",\"type\":\"Collection(Cmc.Nexus.Models.Crm.Document)\"},{\"name\":\"EnrollmentPeriods\",\"type\":\"Collection(Cmc.Nexus.Models.Academics.StudentEnrollmentPeriod)\"},{\"name\":\"TermSummaries\",\"type\":\"Collection(Cmc.Nexus.Models.Academics.StudentEnrollmentTermSummary)\"},{\"name\":\"StudentCourses\",\"type\":\"Collection(Cmc.Nexus.Models.Academics.StudentCourse)\"},{\"name\":\"StudentCourseStatusChanges\",\"type\":\"Collection(Cmc.Nexus.Models.Academics.StudentCourseStatusChange)\"},{\"name\":\"StudentGPAs\",\"type\":\"Collection(Cmc.Nexus.Models.Academics.StudentGpa)\"},{\"name\":\"TransferCredits\",\"type\":\"Collection(Cmc.Nexus.Models.Admissions.StudentTransferCredit)\"},{\"name\":\"SecondaryLeadSources\",\"type\":\"Collection(Cmc.Nexus.Models.Admissions.ProspectInquiryLeadSource)\"},{\"name\":\"StudentPreviousEducation\",\"type\":\"Collection(Cmc.Nexus.Models.Admissions.StudentPreviousEducation)\"},{\"name\":\"TranscriptRequests\",\"type\":\"Collection(Cmc.Nexus.Models.Crm.TranscriptRequest)\"},{\"name\":\"ClearingHouseExportDetailRecords\",\"type\":\"Collection(Cmc.Nexus.Models.FinancialAid.ClearinghouseExportRecord)\"},{\"name\":\"PaidDisbursements\",\"type\":\"Collection(Cmc.Nexus.Models.FinancialAid.PaidDisbursement)\"},{\"name\":\"Advisors\",\"type\":\"Collection(Cmc.Nexus.Models.Common.StudentEnrollmentPeriodAdvisor)\"},{\"name\":\"FaAwards\",\"type\":\"Collection(Cmc.Nexus.Models.FinancialAid.StudentAward)\"},{\"name\":\"Campus\",\"type\":\"Cmc.Nexus.Models.Common.Campus\",\"referentialConstraint\":[{\"property\":\"CampusId\",\"referencedProperty\":\"Id\"}]},{\"name\":\"FaApplicationProcess\",\"type\":\"Collection(Cmc.Nexus.Models.FinancialAid.StudentAwardPell)\"},{\"name\":\"CollectionAccounts\",\"type\":\"Collection(Cmc.Nexus.Models.StudentAccounts.CollectionAccount)\"},{\"name\":\"StudentAccountTransactions\",\"type\":\"Collection(Cmc.Nexus.Models.StudentAccounts.StudentAccountTransaction)\"},{\"name\":\"StudentAccountPendingTransactions\",\"type\":\"Collection(Cmc.Nexus.Models.StudentAccounts.StudentAccountPendingTransaction)\"},{\"name\":\"ExtraCurricularActivities\",\"type\":\"Collection(Cmc.Nexus.Models.Admissions.StudentExtraCurricularActivity)\"},{\"name\":\"StudentRt4Calculation\",\"type\":\"Collection(Cmc.Nexus.Models.StudentAccounts.StudentRt4Calculation)\"},{\"name\":\"StipendSummary\",\"type\":\"Collection(Cmc.Nexus.Models.StudentAccounts.StipendSummary)\"},{\"name\":\"Employer\",\"type\":\"Cmc.Nexus.Models.CareerServices.Employer\",\"referentialConstraint\":[{\"property\":\"EmployerId\",\"referencedProperty\":\"Id\"}]},{\"name\":\"EmploymentStatus\",\"type\":\"Cmc.Nexus.Models.CareerServices.EmploymentStatus\",\"referentialConstraint\":[{\"property\":\"EmploymentStatusId\",\"referencedProperty\":\"Id\"}]},{\"name\":\"StudentPlacementSummary\",\"type\":\"Collection(Cmc.Nexus.Models.CareerServices.StudentPlacementSummary)\"},{\"name\":\"EnrollmentPeriodFees\",\"type\":\"Collection(Cmc.Nexus.Models.Academics.StudentEnrollmentPeriodFee)\"},{\"name\":\"StudentServiceTypes\",\"type\":\"Collection(Cmc.Nexus.Models.StudentServices.StudentServiceType)\"},{\"name\":\"VeteranDetails\",\"type\":\"Collection(Cmc.Nexus.Models.StudentServices.StudentVeteranDetail)\"},{\"name\":\"DisabilityDetails\",\"type\":\"Collection(Cmc.Nexus.Models.StudentServices.StudentDisabilityDetail)\"},{\"name\":\"SchoolStatusHistory\",\"type\":\"Collection(Cmc.Nexus.Models.Common.StudentSchoolStatusHistory)\"},{\"name\":\"SchoolDefinedFieldValues\",\"type\":\"Collection(Cmc.Nexus.Models.Common.StudentSchoolDefinedFieldValue)\"},{\"name\":\"StudentGroups\",\"type\":\"Collection(Cmc.Nexus.Models.Common.StudentGroupMember)\"},{\"name\":\"RegistrationRules\",\"type\":\"Collection(Cmc.Nexus.Models.Academics.RegistrationRule)\"},{\"name\":\"SmsServiceProvider\",\"type\":\"Cmc.Nexus.Models.Crm.SmsServiceProvider\",\"referentialConstraint\":[{\"property\":\"SmsServiceProviderId\",\"referencedProperty\":\"Id\"}]},{\"name\":\"Program\",\"type\":\"Cmc.Nexus.Models.Academics.Program\",\"referentialConstraint\":[{\"property\":\"ProgramId\",\"referencedProperty\":\"Id\"}]},{\"name\":\"AgencyBranches\",\"type\":\"Collection(Cmc.Nexus.Models.Common.StudentAgencyBranch)\"},{\"name\":\"Country\",\"type\":\"Cmc.Nexus.Models.Common.Country\",\"referentialConstraint\":[{\"property\":\"CountryId\",\"referencedProperty\":\"Id\"}]},{\"name\":\"County\",\"type\":\"Cmc.Nexus.Models.Common.County\",\"referentialConstraint\":[{\"property\":\"CountyId\",\"referencedProperty\":\"Id\"}]},{\"name\":\"DataChanges\",\"type\":\"Collection(Cmc.Nexus.Models.Common.StudentDataChange)\"},{\"name\":\"Title\",\"type\":\"Cmc.Nexus.Models.Common.Title\",\"referentialConstraint\":[{\"property\":\"TitleId\",\"referencedProperty\":\"Id\"}]}]},{\"name\":\"FirstName\",\"type\":\"Edm.String\"}]}]",
							"FilterGroups": "[]",
							"IsPinned": false,
							"IsCampusQuery": false,
							"DataContextId": "974971ab-a0b4-49eb-89b4-a4b56c9f7f44",
							"DataViews": [{
								"DisplayStyle": 1,
								"DisplaySettings": "{\"rootEntity\":\"Student\",\"grid\":{\"prefix\":\"\",\"name\":\"Grid\",\"columns\":[{\"encoded\":true,\"field\":\"DateOfBirth\",\"title\":\"Date of Birth\",\"format\":\"{0:d}\",\"headerAttributes\":{},\"attributes\":{\"class\":\"#= data && data.dirty && data.dirtyFields && data.dirtyFields['DateOfBirth'] ? ' k-dirty-cell' : '' #\"}},{\"encoded\":true,\"field\":\"FirstName\",\"title\":\"First Name\",\"headerAttributes\":{},\"attributes\":{\"class\":\"#= data && data.dirty && data.dirtyFields && data.dirtyFields['FirstName'] ? ' k-dirty-cell' : '' #\"}},{\"encoded\":true,\"field\":\"FullName\",\"title\":\"Full Name\",\"headerAttributes\":{},\"attributes\":{\"class\":\"#= data && data.dirty && data.dirtyFields && data.dirtyFields['FullName'] ? ' k-dirty-cell' : '' #\"}},{\"encoded\":true,\"field\":\"LastName\",\"title\":\"Last Name\",\"headerAttributes\":{},\"attributes\":{\"class\":\"#= data && data.dirty && data.dirtyFields && data.dirtyFields['LastName'] ? ' k-dirty-cell' : '' #\"}},{\"encoded\":true,\"hidden\":true,\"field\":\"Id\",\"title\":\"Id\",\"attributes\":{\"style\":\"display:none\",\"class\":\"#= data && data.dirty && data.dirtyFields && data.dirtyFields['Id'] ? ' k-dirty-cell' : '' #\"},\"footerAttributes\":{\"style\":\"display:none\"},\"headerAttributes\":{\"style\":\"display:none\"}}],\"toolbar\":null,\"autoBind\":true,\"filterable\":{\"messages\":{\"isTrue\":\"is Yes\",\"isFalse\":\"is No\"}},\"scrollable\":true,\"sortable\":{\"mode\":\"multiple\",\"allowUnsort\":true},\"selectable\":\"multiple, row\",\"allowCopy\":false,\"navigatable\":true,\"pageable\":{\"refresh\":true,\"buttonCount\":5,\"pageSizes\":[10,25,50,100,500,1000]},\"persistSelection\":false,\"editable\":false,\"groupable\":false,\"rowTemplate\":\"\",\"altRowTemplate\":\"\",\"noRecords\":false,\"dataSource\":{\"data\":null,\"schema\":{\"type\":\"json\",\"model\":{\"id\":\"Id\",\"fields\":{\"Id\":{\"type\":\"number\"},\"DateOfBirth\":{\"type\":\"date\"},\"FirstName\":{\"type\":\"string\"},\"FullName\":{\"type\":\"string\"},\"LastName\":{\"type\":\"string\"}}},\"errors\":\"error\"},\"offlineStorage\":null,\"serverSorting\":true,\"serverPaging\":true,\"serverFiltering\":true,\"serverGrouping\":false,\"serverAggregates\":false,\"batch\":false,\"inPlaceSort\":false,\"type\":\"odata-v4\",\"transport\":{\"read\":{\"url\":\"/ds/campusnexus/Students?$select=DateOfBirth,FirstName,FullName,LastName,Id\"},\"dataSource\":null},\"pageSize\":50,\"page\":1,\"group\":[]},\"height\":\"100%\",\"resizable\":true,\"reorderable\":true,\"columnMenu\":{\"columns\":false,\"filterable\":true},\"detailTemplate\":null,\"columnResizeHandleWidth\":3,\"mobile\":\"\",\"messages\":{\"editable\":{\"cancelDelete\":\"Cancel\",\"confirmation\":\"Are you sure you want to delete this record?\",\"confirmDelete\":\"Delete\"},\"commands\":{\"create\":\"Add new record\",\"cancel\":\"Cancel changes\",\"save\":\"Save changes\",\"destroy\":\"Delete\",\"edit\":\"Edit\",\"update\":\"Update\",\"canceledit\":\"Cancel\",\"excel\":\"Export to Excel\",\"pdf\":\"Export to PDF\"},\"noRecords\":\"No records available.\",\"expandCollapseColumnHeader\":\"\"},\"excel\":{\"proxyURL\":\"/home/export\",\"allPages\":false,\"filterable\":true,\"fileName\":\"NewQuery.xlsx\"},\"pdf\":{\"fileName\":\"NewQuery.pdf\",\"proxyURL\":\"/home/export\",\"paperSize\":\"auto\",\"allPages\":false,\"landscape\":false,\"margin\":null,\"title\":null,\"author\":null,\"subject\":null,\"keywords\":null,\"creator\":\"Kendo UI PDF Generator v.2018.2.516\",\"date\":null},\"detailInit\":null,\"rootEntity\":\"Student\"}}",
								"IsActiveView": true,
								"IsHidden": false,
								"ChildViews": []
							}, {
								"DisplayStyle": 3,
								"DisplaySettings": "{\"chartType\":\"bar\",\"model\":{\"chartType\":\"bar\",\"chartTitlePosition\":\"top\",\"showTooltip\":true,\"explodeColumns\":[],\"showDataLabel\":false,\"dataLabelAlignment\":\"\",\"legend\":{\"visible\":true,\"position\":\"top\",\"orientation\":\"vertical\"},\"categoryAxis\":[{\"title\":{\"text\":\"Category Axis\"},\"type\":\"category\",\"min\":null,\"max\":null,\"baseUnit\":\"fit\",\"labels\":{\"visible\":true,\"rotation\":\"0\",\"step\":\"1\"}}],\"valueAxis\":[{\"title\":{\"text\":\"Value Axis\"},\"type\":\"normal\",\"min\":\"\",\"max\":\"\",\"labels\":{\"visible\":true,\"rotation\":\"0\",\"step\":\"1\"}}],\"series\":[],\"stackType\":\"none\"}}",
								"IsHidden": false,
								"ChildViews": [],
								"RootDataViewId": null,
								"DataViewEntityHierarchy": []
							}, {
								"DisplayStyle": 4,
								"DisplaySettings": "",
								"IsHidden": false,
								"ChildViews": [],
								"RootDataViewId": null,
								"DataViewEntityHierarchy": []
							}],
							"IsAllStaffAllowed": false
						},
        "ResponseStatus": 201,
        "ResponseTimeMs": 25000,
        "ResponseBody": {}
      },
      {
        "RequestId": "d78dd099-6263-4fb5-a04e-c9e294e776d4",
        "RequestMethod": "GET",
        "RequestUrl": "/ds/views/DataQueryGroups?$select=Id,Name,IsShared,SortOrder&$filter=IsHidden ne true and DataQueries/any(x:x/DataQueryGroupId eq {{gDataQueryGroupId}})&$expand=DataQueries($filter=Id eq {{gViewId}};$select=Id,Name,IsPinned,IsCampusQuery,Query,CreatedUserId,DynamicEmployerGroupId,DynamicStudentGroupId)",
        "RequestBody": null,
        "ResponseStatus": 200,
        "ResponseTimeMs": 15000,
        "ResponseBody": "{\"value\":[]}"
      }
    ]
  }
]