[
  {
    "Type": "AdvancedDataFile",
    "Version": "2.0",
    "TestDescription": "CourseFeeScheduleDelete",
    "Globals": {
      "CourseCode": "Cou002"
    },
    "Apis": [
      {
        "RequestId": "30a0390f-0980-42bf-ae89-f8d8dab41094",
        "RequestMethod": "GET",
        "RequestUrl": "/ds/campusnexus/Courses?$select=Id,Name,Code&$filter=Code eq '{{gCourseCode}}'",
        "RequestBody": null,
        "ResponseStatus": 200,
        "ResponseTimeMs": 15000,
        "ResponseBody": "{\"value\":[]}"
      },
      {
        "RequestId": "30a0390f-0980-42bf-ae89-f8d8dab41104",
        "RequestMethod": "GET",
        "RequestUrl": "/ds/campusnexus/CourseFeeSchedules/CampusNexus.GetCourseFeeSchedulesForCourse(courseId={{gCourseId}})",
        "RequestBody": null,
        "ResponseStatus": 200,
        "ResponseTimeMs": 15000,
        "ResponseBody": "{\"value\":[]}"
      },
      {
        "RequestId": "5ac9b659-15a8-4858-8412-896dfea4fd36",
        "RequestMethod": "POST",
        "RequestUrl": "/api/commands/Academics/CourseFeeSchedule/DeleteCourseFeeSchedule",
        "RequestBody": "{}",
        "ResponseStatus": 200,
        "ResponseTimeMs": 25000,
        "ResponseBody": {
          "payload": {
            "data": {
              "validationMessages": []
            }
          }
        }
      }
    ]
  }
]