[{
	"Type": "AdvancedDataFile",
	"Version": "2.0",
	"TestDescription": "This API will delete a Pronoun (Config-CM-Pronoun)",
	"Globals": {
		"Name": "PronounName",
		"Code": "PCode"
	},
	"Apis": [{
			"RequestId": "00000000-0000-0000-0000-000000000000",
			"RequestMethod": "GET",
			"RequestUrl": "/ds/campusnexus/GenderPronouns?$filter=Name eq '{{gName}}'",
			"RequestBody": null,
			"ResponseStatus": 200,
			"ResponseTimeMs": 10000,
			"ResponseBody": "{\"value\":[]}"
		},
		{
			"RequestId": "00000000-0000-0000-0000-000000000001",
			"RequestMethod": "POST",
			"RequestUrl": "/api/commands/Common/GenderPronoun/Get",
			"RequestBody": {
				"payload": {}
			},
			"ResponseStatus": 200,
			"ResponseTimeMs": 5000,
			"ResponseBody": {}
		},
		{
			"RequestId": "00000000-0000-0000-0000-000000000002",
			"RequestMethod": "POST",
			"RequestUrl": "/api/commands/Common/GenderPronoun/Delete",
			"RequestBody": {},
			"ResponseStatus": 200,
			"ResponseTimeMs": 5000,
			"ResponseBody": {
				"payload": {
					"deleted": true
				}
			}
		}
	]
}]