[{
	"Type": "AdvancedDataFile",
	"Version": "2.0",
	"TestDescription": "This API will create an Skill (Config-CS-Skill)",
	"Globals": {
		"Name": "JobBenName1",
		"Code": "JBCODE1",
		"UpdatedName": "JBNameUpdate1"
	},
	"Apis": [{
			"RequestId": "00000000-0000-0000-0000-000000000000",
			"RequestMethod": "GET",
			"RequestUrl": "/ds/campusnexus/Staff/CampusNexus.GetCurrentLoggedInUserStaff?$select=Id,DefaultSyCampusId,PersonId,CampusGroupId",
			"RequestBody": null,
			"ResponseStatus": 200,
			"ResponseTimeMs": 5000,
			"ResponseBody": "{\"value\":[]}"
		},
		{
			"RequestId": "00000000-0000-0000-0000-000000000001",
			"RequestMethod": "POST",
			"RequestUrl": "/api/commands/CareerServices/EmployerAttribute/Create",
			"RequestBody": "{}",
			"ResponseStatus": 200,
			"ResponseTimeMs": 5000,
			"ResponseBody": {
				"payload": {}
			}
		},
		{
			"RequestId": "00000000-0000-0000-0000-000000000002",
			"RequestMethod": "POST",
			"RequestUrl": "/api/commands/CareerServices/EmployerAttribute/SaveNew",
			"RequestBody": {
				"payload": {
					"code": "{{gCode}}",
					"name": "{{gName}}",
					"id": -1,
					"createdDateTime": "@DateNow",
					"isActive": true,
					"extendedProperties": [],
					"entityState": 0,
					"entityDirty": true
				}
			},
			"ResponseStatus": 200,
			"ResponseTimeMs": 5000,
			"ResponseBody": {}
		},
		{
			"RequestId": "00000000-0000-0000-0000-000000000003",
			"RequestMethod": "POST",
			"RequestUrl": "/api/commands/CareerServices/EmployerAttribute/Get",
			"RequestBody": {
				"payload": {}
			},
			"ResponseStatus": 200,
			"ResponseTimeMs": 5000,
			"ResponseBody": {}
		},
		{
			"RequestId": "00000000-0000-0000-0000-000000000004",
			"RequestMethod": "POST",
			"RequestUrl": "/api/commands/CareerServices/EmployerAttribute/Save",
			"RequestBody": {
				"payload": {
					"name": "{{gUpdatedName}}"
				}
			},
			"ResponseStatus": 200,
			"ResponseTimeMs": 5000,
			"ResponseBody": {
				"payload": {
					"data": {
						"name": "JBNameUpdate1"
					}
				}
			}
		},
		{
			"RequestId": "00000000-0000-0000-0000-000000000005",
			"RequestMethod": "POST",
			"RequestUrl": "/api/commands/CareerServices/EmployerAttribute/Delete",
			"RequestBody": {
				"payload": {}
			},
			"ResponseStatus": 200,
			"ResponseTimeMs": 5000,
			"ResponseBody": {
				"payload": {
					"deleted": true
				}
			}
		}
	]
}]