{
	"info": {
		"_postman_id": "c9d29f56-3372-4ac9-9b13-54e1e69e7024",
		"name": "CheckCalcFieldsforClockHourandSchedHoursYesforPV",
		"description": "<metadata>\n<testcase adoid='1495189,1495190,1495191,2277725'/>\n</metadata>",
		"schema": "https://schema.getpostman.com/json/collection/v2.1.0/collection.json",
		"_exporter_id": "14532473"
	},
	"item": [
		{
			"name": "UpdateProgramVersiontoClockHour",
			"item": [],
			"description": "<metadata>\n<pre-request name='UpdateProgramVersion'/>\n<environmentfile name='StudentDPAAPIEnvironment'/>\n<data name='UpdatePV1toClockHour'/>\n</metadata>"
		},
		{
			"name": "UpdateAcademicCalendarforPV",
			"item": [],
			"description": "<metadata>\n<pre-request name='UpdateAcademicCalendarforPV'/>\n<environmentfile name='StudentDPAAPIEnvironment'/>\n<data name='UpdateAcademicCalendarto5forPV1'/>\n</metadata>"
		},
		{
			"name": "AddCoursetoStudent",
			"item": [],
			"description": "<metadata>\n<pre-request name='AddCoursetoStudent'/>\n<environmentfile name='StudentDPAAPIEnvironment'/>\n<data name='AddCoursetoStudent'/>\n</metadata>"
		},
		{
			"name": "RegisterCoursetoStudent",
			"item": [],
			"description": "<metadata>\n<pre-request name='RegisterCoursetoStudentforDPAStudent'/>\n<environmentfile name='StudentDPAAPIEnvironment'/>\n<data name='RegisterCoursetoStudent'/>\n</metadata>"
		},
		{
			"name": "PostAttendancetoRegisteredCourse",
			"item": [],
			"description": "<metadata>\n<pre-request name='PostingAttendanceforDPAStudent'/>\n<environmentfile name='StudentDPAAPIEnvironment'/>\n<data name='PostAttendanceforRegisteredCourses'/>\n</metadata>"
		},
		{
			"name": "CheckCurrentandScheduledCreditsafterPostingAttendance",
			"item": [
				{
					"name": "Initialize",
					"event": [
						{
							"listen": "prerequest",
							"script": {
								"exec": [
									"/********************DO NOT MODIFY THIS CODE********************/",
									"pm.globals.unset(\"gApiUtility\");",
									"pm.globals.unset(\"gApiUrl\");",
									"pm.globals.unset(\"gAuthHeaderKey\");",
									"pm.globals.unset(\"gAuthHeaderValue\");",
									"pm.globals.unset(\"gUrl\");",
									"pm.globals.unset(\"gRequestBody\");",
									"pm.globals.unset(\"gIndex\");",
									"pm.globals.set(\"gIndex\", 0);",
									"",
									"// Setup URL, if web host is not set in the environment use default",
									"var apiUtilityHost = \"\";",
									"if (!pm.environment.has(\"envApiUtilityHost\")) {",
									"     apiUtilityHost = \"hdev22.dev.int:9000\";",
									"} else {",
									"     apiUtilityHost = pm.environment.get(\"envApiUtilityHost\");",
									"}",
									"var requestUrl = \"http://\" + apiUtilityHost + \"/automation/apiUtility.js\";",
									"pm.globals.set(\"gUrl\", requestUrl);",
									"//console.log(pm.globals.get(\"gUrl\"));",
									"/*****************END DO NOT MODIFY THIS CODE*******************/"
								],
								"type": "text/javascript"
							}
						},
						{
							"listen": "test",
							"script": {
								"exec": [
									"/********************CHAIN DEFINITION***************************/",
									"let chainDefinitionArray = [",
									"    {",
									"        \"RequestId\": \"a89a78ae-ffaa-479a-8c2d-1685e73055c0\",",
									"        \"RequestMethod\": \"Get\",",
									"        \"RequestUrl\": \"/ds/campusnexus/Students?$filter=Ssn eq '{{gStudentSsn}}'\",",
									"        \"ChainSource\": [",
									"            \"response.value[0].Id\"",
									"        ],",
									"        \"Chain\": [",
									"        ]",
									"    },",
									"    {",
									"         \"RequestId\"     : \"05febb5e-f716-4402-9b26-6a4adecf5fba\",",
									"         \"RequestMethod\" : \"GET\",",
									"         \"RequestUrl\"    : \"/ds/campusnexus/StudentEnrollmentPeriodDetails/CampusNexus.GetStudentEnrollmentPeriodList(studentId={{gStudentId}})?$select=Id,ProgramVersionId,ProgramId,ProgramVersionName&$filter = ProgramVersionName eq '{{gEnrollmentPVName}}'\",",
									"         \"ChainSource\"   : [",
									"               \"response.value[0].Id\"",
									"         ],",
									"         \"Chain\"         : [",
									"             ",
									"            {  ",
									"                \"SourceApiKey\":\"a89a78ae-ffaa-479a-8c2d-1685e73055c0\", ",
									"                \"SourcePath\": \"response.value[0].Id\", ",
									"                \"TargetPath\": \"globals.gStudentId\" ",
									"           }",
									"         ]",
									"    },",
									"    {",
									"         \"RequestId\"     : \"05febb5e-f716-4402-9b26-6a4adecf5fbb\",",
									"         \"RequestMethod\" : \"GET\",",
									"         \"RequestUrl\"    : \"/ds/campusnexus/StudentEnrollmentPeriods/CampusNexus.GetStudentEnrollmentPeriodWithChildDetails(studentEnrollmentPeriodId={{gStudentEnrollmentPeriodId}})?$expand=Program,Campus,EnrollmentStatus,StartTerm,SAPStatus,StatusChangeReason,ProgramVersion,SchoolStatus($expand=SystemSchoolStatus),Shift,GradeScale,Student($select=FirstName,Id,LastName;$expand=Person($select=FullName,Id))\",",
									"         \"ChainSource\"   : [",
									"         ],",
									"         \"Chain\"         : [             ",
									"            {  ",
									"                \"SourceApiKey\":\"05febb5e-f716-4402-9b26-6a4adecf5fba\", ",
									"                \"SourcePath\": \"response.value[0].Id\", ",
									"                \"TargetPath\": \"globals.gStudentEnrollmentPeriodId\" ",
									"            }",
									"         ]",
									"    },",
									"    {",
									"         \"RequestId\"     : \"05febb5e-f716-4402-9b26-6a4adecf5fbc\",",
									"         \"RequestMethod\" : \"GET\",",
									"         \"RequestUrl\"    : \"/ds/campusnexus/StudentCourseSchedules/CampusNexus.GetStudentCourseSchedule(studentEnrollmentPeriodId={{gStudentEnrollmentPeriodId}},studentId={{gStudentId}},termId=0,status='S')\",",
									"         \"ChainSource\"   : [",
									"         ],",
									"         \"Chain\"         : [             ",
									"         ]",
									"    },",
									"    {",
									"         \"RequestId\"     : \"05febb5e-f716-4402-9b26-6a4adecf5fbd\",",
									"         \"RequestMethod\" : \"GET\",",
									"         \"RequestUrl\"    : \"/ds/campusnexus/StudentCourseSchedules/CampusNexus.GetStudentCourseSchedule(studentEnrollmentPeriodId={{gStudentEnrollmentPeriodId}},studentId={{gStudentId}},termId=0,status='C')\",",
									"         \"ChainSource\"   : [",
									"         ],",
									"         \"Chain\"         : [             ",
									"         ]",
									"    },",
									"    {",
									"         \"RequestId\"     : \"8a8b0db0-8a03-40ad-baa0-7eae87f4a159\",",
									"         \"RequestMethod\" : \"GET\",",
									"         \"RequestUrl\"    : \"/api/dpa/v1/studentenrollmentperiods/{{gEnrollmentID}}/enrollmentsummary\",",
									"         \"ChainSource\"   : [",
									"               \"response.value[0].Id\"",
									"         ],",
									"         \"Chain\"         : [",
									"             {",
									"                   \"SourceApiKey\" : \"05febb5e-f716-4402-9b26-6a4adecf5fba\",",
									"                   \"SourcePath\"   : \"response.value[0].Id\",",
									"                   \"TargetPath\"   : \"globals.gEnrollmentID\"",
									"              }",
									"     ]",
									"    }",
									"];",
									"/********************END CHAIN DEFINITION***********************/",
									"/********************DO NOT MODIFY THIS CODE********************/",
									"// Verify status.",
									"pm.test(\"Verify response status is \" + 200, function() {",
									"    pm.expect(pm.response.code).to.equal(200);",
									"});",
									"",
									"// Load utility code framework",
									"pm.globals.set(\"gApiUtility\", responseBody);",
									"try {",
									"    eval(pm.globals.get(\"gApiUtility\"));",
									"    pm.test(\"Load framework\", function() {",
									"        pm.expect(typeof apiUtility).to.be.equal('object');",
									"    });",
									"} catch(e) { ",
									"    pm.test(\"Load framework - eval\", function() { pm.expect.fail() });",
									"}",
									"",
									"// Resolve global macros",
									"apiUtility.resolveMacros(data.Globals);",
									"",
									"// Read the data file globals section, and setup postman globals.",
									"for(var p in data.Globals) {",
									"  // If Globals own property, set global variable",
									"  if(data.Globals.hasOwnProperty(p)) { ",
									"    var gName = \"g\" + p;",
									"    pm.globals.set(gName, data.Globals[p]);",
									"    //console.log('setting global ' + gName);",
									"  }",
									"}",
									"",
									"// Save data file globals in postman global for chaining purposes.",
									"if(Object.entries(data.Globals).length > 0) {",
									"    let str = \"dataGlobals\";",
									"    apiUtility.globalStoreWrite(str, data.Globals); ",
									"}",
									"",
									"// Validate chain and Api configuration.",
									"let validationStatus = apiUtility.validateChain(data.Globals, data.Apis, chainDefinitionArray);",
									"if(!validationStatus.isValid) {",
									"    let FailFunction = function() { pm.expect.fail() };",
									"    for(let index = 0; index < validationStatus.msgs.length; ++ index) {",
									"        pm.test(\"Chain validation - \" + validationStatus.msgs[index], FailFunction);",
									"    }",
									"}",
									"",
									"// Merge data file API section with chain definition, and setup postman global",
									"if(validationStatus.isValid) {",
									"    let apis  = {};",
									"    for(let index = 0; index < data.Apis.length; ++index) {",
									"        apis[data.Apis[index].RequestId] = data.Apis[index];",
									"    }",
									"    for(let index = 0; index < chainDefinitionArray.length; ++index) {",
									"        apis[chainDefinitionArray[index].RequestId].RequestUrl = chainDefinitionArray[index].RequestUrl;",
									"        apis[chainDefinitionArray[index].RequestId].ChainSource = chainDefinitionArray[index].ChainSource;",
									"        apis[chainDefinitionArray[index].RequestId].Chain = chainDefinitionArray[index].Chain;",
									"        apis[chainDefinitionArray[index].RequestId].Index = index;",
									"    }",
									"    pm.globals.set(\"gApis\", apis);",
									"    //console.log(pm.globals.get(\"gApis\"));",
									"}",
									"",
									"// If chainging is not valid end the collection.",
									"if(!validationStatus.isValid) {",
									"    console.log(\"Chaining is invalid, terminating the test collection\");",
									"    for(let index = 0; index < validationStatus.msgs.length; ++ index) {",
									"        console.log(\"Chain validation - \" + validationStatus.msgs[index]);",
									"    }",
									"    postman.setNextRequest(null);",
									"}",
									"/*****************END DO NOT MODIFY THIS CODE*******************/",
									"",
									"console.log(\"--------------------------------------------------------------------------------------\");",
									""
								],
								"type": "text/javascript"
							}
						}
					],
					"request": {
						"auth": {
							"type": "noauth"
						},
						"method": "GET",
						"header": [
							{
								"key": "Content-Type",
								"value": "application/json"
							}
						],
						"url": {
							"raw": "{{gUrl}}",
							"host": [
								"{{gUrl}}"
							]
						}
					},
					"response": []
				},
				{
					"name": "Get Student Id by SSN",
					"event": [
						{
							"listen": "prerequest",
							"script": {
								"exec": [
									"",
									"/********************DO NOT MODIFY THIS CODE********************/",
									"// Load API utility code",
									"eval(postman.getGlobalVariable(\"gApiUtility\"));",
									"",
									"// Get API settings",
									"let apiId = \"a89a78ae-ffaa-479a-8c2d-1685e73055c0\";",
									"let reqIndex = pm.globals.get(\"gIndex\");",
									"let API = pm.globals.get(\"gApis\")[apiId];",
									"if (API === undefined || API.Index !== reqIndex) {",
									"    console.log(\"ERROR - API not found for the specified apiId, \" + apiId);",
									"    pm.globals.set(\"gReqApi\", null);",
									"} else {",
									"    pm.globals.set(\"gReqApi\", API);",
									"    pm.globals.set(\"gIndex\", Number(pm.globals.get(\"gIndex\")) + 1);",
									"}",
									"//console.log(API);",
									"",
									"// Make authorization header",
									"var hdr = apiUtility.makeAuthorization(null, null, null, pm.environment.get(\"envApiKey\"),",
									"    pm.environment.get(\"envAuthUser\"), pm.environment.get(\"envAuthPassword\"));",
									"pm.globals.set(\"gAuthHeaderKey\", hdr.key);",
									"pm.globals.set(\"gAuthHeaderValue\", hdr.value);",
									"//console.log(pm.globals.get(\"gAuthHeaderKey\"));",
									"//console.log(pm.globals.get(\"gAuthHeaderValue\"));",
									"",
									"// Make request body by combining chained properties and data file request body",
									"if (API !== undefined) {",
									"    var request = {};",
									"    apiUtility.setChainProps(API.Chain, request);",
									"    var req = apiUtility.mergeRequestBody(request, API.RequestBody);",
									"    pm.globals.set(\"gRequestBody\", JSON.stringify(req));",
									"    //console.log(pm.globals.get(\"gRequestBody\"));",
									"}",
									"",
									"// Make URL",
									"if (API !== undefined) {",
									"    pm.globals.set(\"gUrl\", apiUtility.makeUrl(pm.environment.get(\"envWebScheme\"), pm.environment.get(\"envWebHost\"), API.RequestUrl));",
									"} else {",
									"    pm.globals.set(\"gUrl\", \"http://127.0.0.1\");",
									"}",
									"",
									"//console.log(pm.globals.get(\"gUrl\"));",
									"/*****************END DO NOT MODIFY THIS CODE*******************/"
								],
								"type": "text/javascript"
							}
						},
						{
							"listen": "test",
							"script": {
								"exec": [
									"/********************DO NOT MODIFY THIS CODE********************/",
									"// Load API utility code",
									"eval(postman.getGlobalVariable(\"gApiUtility\"));",
									"",
									"// Get API settings",
									"let API = pm.globals.get(\"gReqApi\");",
									"if (API === null) {",
									"    postman.setNextRequest(null);",
									"    pm.test(\"API not found for the Request ID, using fallback URL and ending the test\", function() { pm.expect.fail() });",
									"    return;",
									"}",
									"//console.log(API);",
									"",
									"// Save properties for chaining, ignore exceptions because the test will fail later anyways",
									"try {",
									"   var rb = pm.response.json();",
									"   if (API.ChainSource.length > 0) {",
									"      let str = API.RequestId + \".response\";",
									"      apiUtility.globalStoreWrite(str, rb);",
									"   }",
									"} catch(e) { console.log(\"Exception was raised during chainging, Msg -\" + e); }",
									"/*****************END DO NOT MODIFY THIS CODE*******************/",
									"",
									"// --- TEST VERIFICATIONS ---",
									"// --- Add your custom tests in this block ---",
									"pm.test(\"Verify response status is \" + API.ResponseStatus, function() { ",
									"     pm.expect(pm.response.code).to.equal(API.ResponseStatus);",
									"});",
									"pm.test(\"Verify response time is less than \" + API.ResponseTimeMs, function() { ",
									"     pm.expect(pm.response.responseTime).to.be.below(API.ResponseTimeMs);",
									"});",
									"pm.test(\"Verify response body matches expected response \", function() { ",
									"     pm.expect(apiUtility.verifyResponse(API.ResponseBody, pm.response.json())).to.be.true;",
									"});",
									"",
									"pm.test(\"Verify response value is not empty \", function() {",
									"    pm.expect(pm.response.json().value.length).to.not.equal(0);",
									"});",
									"// --- END TEST VERIFICATIONS ---",
									"console.log(\"--------------------------------------------------------------------------------------\");"
								],
								"type": "text/javascript"
							}
						}
					],
					"request": {
						"auth": {
							"type": "noauth"
						},
						"method": "GET",
						"header": [
							{
								"key": "Content-Type",
								"value": "application/json"
							},
							{
								"key": "{{gAuthHeaderKey}}",
								"value": "{{gAuthHeaderValue}}"
							}
						],
						"url": {
							"raw": "{{gUrl}}",
							"host": [
								"{{gUrl}}"
							]
						}
					},
					"response": []
				},
				{
					"name": "Get Enrollment ID",
					"event": [
						{
							"listen": "prerequest",
							"script": {
								"exec": [
									"",
									"/********************DO NOT MODIFY THIS CODE********************/",
									"// Load API utility code",
									"eval(postman.getGlobalVariable(\"gApiUtility\"));",
									"",
									"// Get API settings",
									"let apiId = \"05febb5e-f716-4402-9b26-6a4adecf5fba\";",
									"let reqIndex = pm.globals.get(\"gIndex\");",
									"let API = pm.globals.get(\"gApis\")[apiId];",
									"if (API === undefined || API.Index !== reqIndex) {",
									"    console.log(\"ERROR - API not found for the specified apiId, \" + apiId);",
									"    pm.globals.set(\"gReqApi\", null);",
									"} else {",
									"    pm.globals.set(\"gReqApi\", API);",
									"    pm.globals.set(\"gIndex\", Number(pm.globals.get(\"gIndex\")) + 1);",
									"}",
									"//console.log(API);",
									"",
									"// Make authorization header",
									"var hdr = apiUtility.makeAuthorization(null, null, null,  pm.environment.get(\"envApiKey\"), ",
									"                                           pm.environment.get(\"envAuthUser\"), pm.environment.get(\"envAuthPassword\"));",
									"pm.globals.set(\"gAuthHeaderKey\", hdr.key);",
									"pm.globals.set(\"gAuthHeaderValue\", hdr.value);",
									"//console.log(pm.globals.get(\"gAuthHeaderKey\"));",
									"//console.log(pm.globals.get(\"gAuthHeaderValue\"));",
									"",
									"// Make request body by combining chained properties and data file request body",
									"if (API !== undefined) {",
									"    var request = { };",
									"    apiUtility.setChainProps(API.Chain, request);",
									"    var req = apiUtility.mergeRequestBody(request, API.RequestBody);",
									"    pm.globals.set(\"gRequestBody\", JSON.stringify(req));",
									"    //console.log(pm.globals.get(\"gRequestBody\"));",
									"}",
									"",
									"// Make URL",
									"if(API !== undefined) {",
									"    pm.globals.set(\"gUrl\", apiUtility.makeUrl(pm.environment.get(\"envWebScheme\"), pm.environment.get(\"envWebHost\"), API.RequestUrl));",
									"} else {",
									"    pm.globals.set(\"gUrl\", \"http://127.0.0.1\");",
									"}",
									"//console.log(pm.globals.get(\"gUrl\"));",
									"/*****************END DO NOT MODIFY THIS CODE*******************/"
								],
								"type": "text/javascript"
							}
						},
						{
							"listen": "test",
							"script": {
								"exec": [
									"/********************DO NOT MODIFY THIS CODE********************/",
									"// Load API utility code",
									"eval(postman.getGlobalVariable(\"gApiUtility\"));",
									"",
									"// Get API settings",
									"let API = pm.globals.get(\"gReqApi\");",
									"if (API === null) {",
									"    postman.setNextRequest(null);",
									"    pm.test(\"API not found for the Request ID, using fallback URL and ending the test\", function() { pm.expect.fail() });",
									"    return;",
									"}",
									"//console.log(API);",
									"",
									"// Save properties for chaining, ignore exceptions because the test will fail later anyways",
									"try {",
									"   var rb = pm.response.json();",
									"   if (API.ChainSource.length > 0) {",
									"      let str = API.RequestId + \".response\";",
									"      apiUtility.globalStoreWrite(str, rb);",
									"   }",
									"} catch(e) { console.log(\"Exception was raised during chainging, Msg -\" + e); }",
									"/*****************END DO NOT MODIFY THIS CODE*******************/",
									"",
									"// --- TEST VERIFICATIONS ---",
									"// --- Add your custom tests in this block ---",
									"pm.test(\"Verify response status is \" + API.ResponseStatus, function() { ",
									"     pm.expect(pm.response.code).to.equal(API.ResponseStatus);",
									"});",
									"pm.test(\"Verify response time is less than \" + API.ResponseTimeMs, function() { ",
									"     pm.expect(pm.response.responseTime).to.be.below(API.ResponseTimeMs);",
									"});",
									"pm.test(\"Verify response body matches expected response \", function() { ",
									"     pm.expect(apiUtility.verifyResponse(API.ResponseBody, pm.response.json())).to.be.true;",
									"});",
									"pm.test(\"Verify response value is not empty\",function(){",
									"    pm.expect(pm.response.json().value.length).to.not.equal(0);",
									"});",
									"// --- END TEST VERIFICATIONS ---",
									"console.log(\"--------------------------------------------------------------------------------------\");"
								],
								"type": "text/javascript"
							}
						}
					],
					"request": {
						"auth": {
							"type": "noauth"
						},
						"method": "GET",
						"header": [
							{
								"key": "Content-Type",
								"value": "application/json"
							},
							{
								"key": "{{gAuthHeaderKey}}",
								"value": "{{gAuthHeaderValue}}"
							}
						],
						"url": {
							"raw": "{{gUrl}}",
							"host": [
								"{{gUrl}}"
							]
						}
					},
					"response": []
				},
				{
					"name": "GetStudentEnrollmentPeriodWithChildDetails",
					"event": [
						{
							"listen": "prerequest",
							"script": {
								"exec": [
									"",
									"/********************DO NOT MODIFY THIS CODE********************/",
									"// Load API utility code",
									"eval(postman.getGlobalVariable(\"gApiUtility\"));",
									"",
									"// Get API settings",
									"let apiId = \"05febb5e-f716-4402-9b26-6a4adecf5fbb\";",
									"let reqIndex = pm.globals.get(\"gIndex\");",
									"let API = pm.globals.get(\"gApis\")[apiId];",
									"if (API === undefined || API.Index !== reqIndex) {",
									"    console.log(\"ERROR - API not found for the specified apiId, \" + apiId);",
									"    pm.globals.set(\"gReqApi\", null);",
									"} else {",
									"    pm.globals.set(\"gReqApi\", API);",
									"    pm.globals.set(\"gIndex\", Number(pm.globals.get(\"gIndex\")) + 1);",
									"}",
									"//console.log(API);",
									"",
									"// Make authorization header",
									"var hdr = apiUtility.makeAuthorization(null, null, null,  pm.environment.get(\"envApiKey\"), ",
									"                                           pm.environment.get(\"envAuthUser\"), pm.environment.get(\"envAuthPassword\"));",
									"pm.globals.set(\"gAuthHeaderKey\", hdr.key);",
									"pm.globals.set(\"gAuthHeaderValue\", hdr.value);",
									"//console.log(pm.globals.get(\"gAuthHeaderKey\"));",
									"//console.log(pm.globals.get(\"gAuthHeaderValue\"));",
									"",
									"// Make request body by combining chained properties and data file request body",
									"if (API !== undefined) {",
									"    var request = { };",
									"    apiUtility.setChainProps(API.Chain, request);",
									"    var req = apiUtility.mergeRequestBody(request, API.RequestBody);",
									"    pm.globals.set(\"gRequestBody\", JSON.stringify(req));",
									"    //console.log(pm.globals.get(\"gRequestBody\"));",
									"}",
									"",
									"// Make URL",
									"if(API !== undefined) {",
									"    pm.globals.set(\"gUrl\", apiUtility.makeUrl(pm.environment.get(\"envWebScheme\"), pm.environment.get(\"envWebHost\"), API.RequestUrl));",
									"} else {",
									"    pm.globals.set(\"gUrl\", \"http://127.0.0.1\");",
									"}",
									"//console.log(pm.globals.get(\"gUrl\"));",
									"/*****************END DO NOT MODIFY THIS CODE*******************/"
								],
								"type": "text/javascript"
							}
						},
						{
							"listen": "test",
							"script": {
								"exec": [
									"/********************DO NOT MODIFY THIS CODE********************/",
									"// Load API utility code",
									"eval(postman.getGlobalVariable(\"gApiUtility\"));",
									"",
									"// Get API settings",
									"let API = pm.globals.get(\"gReqApi\");",
									"if (API === null) {",
									"    postman.setNextRequest(null);",
									"    pm.test(\"API not found for the Request ID, using fallback URL and ending the test\", function() { pm.expect.fail() });",
									"    return;",
									"}",
									"//console.log(API);",
									"",
									"// Save properties for chaining, ignore exceptions because the test will fail later anyways",
									"try {",
									"   var rb = pm.response.json();",
									"   if (API.ChainSource.length > 0) {",
									"      let str = API.RequestId + \".response\";",
									"      apiUtility.globalStoreWrite(str, rb);",
									"   }",
									"} catch(e) { console.log(\"Exception was raised during chainging, Msg -\" + e); }",
									"/*****************END DO NOT MODIFY THIS CODE*******************/",
									"",
									"// --- TEST VERIFICATIONS ---",
									"// --- Add your custom tests in this block ---",
									"pm.test(\"Verify response status is \" + API.ResponseStatus, function() { ",
									"     pm.expect(pm.response.code).to.equal(API.ResponseStatus);",
									"});",
									"pm.test(\"Verify response time is less than \" + API.ResponseTimeMs, function() { ",
									"     pm.expect(pm.response.responseTime).to.be.below(API.ResponseTimeMs);",
									"});",
									"pm.test(\"Verify response body matches expected response \", function() { ",
									"     pm.expect(apiUtility.verifyResponse(API.ResponseBody, pm.response.json())).to.be.true;",
									"});",
									"pm.test(\"Verify response value is not empty\",function(){",
									"    pm.expect(pm.response.json().value.length).to.not.equal(0);",
									"});",
									"",
									"//create a new varaiable to get the details",
									"var PVCode = rb.value[0].ProgramVersion.Code;",
									"var DegreeId = rb.value[0].ProgramVersion.DegreeId;",
									"var ProgramVersionUnitType = rb.value[0].ProgramVersion.ProgramVersionUnitType;",
									"var CatalogYearId = rb.value[0].CatalogYearId;",
									"",
									"//set the varaiables to globals",
									"pm.globals.set(\"gPVCode\",PVCode);",
									"pm.globals.set(\"gDegreeId\",DegreeId);",
									"pm.globals.set(\"gProgramVersionUnitType\",ProgramVersionUnitType);",
									"pm.globals.set(\"gCatalogYearId\",CatalogYearId);",
									"",
									"// --- END TEST VERIFICATIONS ---",
									"console.log(\"--------------------------------------------------------------------------------------\");"
								],
								"type": "text/javascript"
							}
						}
					],
					"request": {
						"auth": {
							"type": "noauth"
						},
						"method": "GET",
						"header": [
							{
								"key": "Content-Type",
								"value": "application/json"
							},
							{
								"key": "{{gAuthHeaderKey}}",
								"value": "{{gAuthHeaderValue}}"
							}
						],
						"url": {
							"raw": "{{gUrl}}",
							"host": [
								"{{gUrl}}"
							]
						}
					},
					"response": []
				},
				{
					"name": "GetStudentCourseDetailsforScheduledState",
					"event": [
						{
							"listen": "prerequest",
							"script": {
								"exec": [
									"",
									"/********************DO NOT MODIFY THIS CODE********************/",
									"// Load API utility code",
									"eval(postman.getGlobalVariable(\"gApiUtility\"));",
									"",
									"// Get API settings",
									"let apiId = \"05febb5e-f716-4402-9b26-6a4adecf5fbc\";",
									"let reqIndex = pm.globals.get(\"gIndex\");",
									"let API = pm.globals.get(\"gApis\")[apiId];",
									"if (API === undefined || API.Index !== reqIndex) {",
									"    console.log(\"ERROR - API not found for the specified apiId, \" + apiId);",
									"    pm.globals.set(\"gReqApi\", null);",
									"} else {",
									"    pm.globals.set(\"gReqApi\", API);",
									"    pm.globals.set(\"gIndex\", Number(pm.globals.get(\"gIndex\")) + 1);",
									"}",
									"//console.log(API);",
									"",
									"// Make authorization header",
									"var hdr = apiUtility.makeAuthorization(null, null, null,  pm.environment.get(\"envApiKey\"), ",
									"                                           pm.environment.get(\"envAuthUser\"), pm.environment.get(\"envAuthPassword\"));",
									"pm.globals.set(\"gAuthHeaderKey\", hdr.key);",
									"pm.globals.set(\"gAuthHeaderValue\", hdr.value);",
									"//console.log(pm.globals.get(\"gAuthHeaderKey\"));",
									"//console.log(pm.globals.get(\"gAuthHeaderValue\"));",
									"",
									"// Make request body by combining chained properties and data file request body",
									"if (API !== undefined) {",
									"    var request = { };",
									"    apiUtility.setChainProps(API.Chain, request);",
									"    var req = apiUtility.mergeRequestBody(request, API.RequestBody);",
									"    pm.globals.set(\"gRequestBody\", JSON.stringify(req));",
									"    //console.log(pm.globals.get(\"gRequestBody\"));",
									"}",
									"",
									"// Make URL",
									"if(API !== undefined) {",
									"    pm.globals.set(\"gUrl\", apiUtility.makeUrl(pm.environment.get(\"envWebScheme\"), pm.environment.get(\"envWebHost\"), API.RequestUrl));",
									"} else {",
									"    pm.globals.set(\"gUrl\", \"http://127.0.0.1\");",
									"}",
									"//console.log(pm.globals.get(\"gUrl\"));",
									"/*****************END DO NOT MODIFY THIS CODE*******************/"
								],
								"type": "text/javascript"
							}
						},
						{
							"listen": "test",
							"script": {
								"exec": [
									"/********************DO NOT MODIFY THIS CODE********************/",
									"// Load API utility code",
									"eval(postman.getGlobalVariable(\"gApiUtility\"));",
									"",
									"// Get API settings",
									"let API = pm.globals.get(\"gReqApi\");",
									"if (API === null) {",
									"    postman.setNextRequest(null);",
									"    pm.test(\"API not found for the Request ID, using fallback URL and ending the test\", function () { pm.expect.fail() });",
									"    return;",
									"}",
									"//console.log(API);",
									"",
									"// Save properties for chaining, ignore exceptions because the test will fail later anyways",
									"try {",
									"    var rb = pm.response.json();",
									"    if (API.ChainSource.length > 0) {",
									"        let str = API.RequestId + \".response\";",
									"        apiUtility.globalStoreWrite(str, rb);",
									"    }",
									"} catch (e) { console.log(\"Exception was raised during chainging, Msg -\" + e); }",
									"/*****************END DO NOT MODIFY THIS CODE*******************/",
									"",
									"// --- TEST VERIFICATIONS ---",
									"// --- Add your custom tests in this block ---",
									"pm.test(\"Verify response status is \" + API.ResponseStatus, function () {",
									"    pm.expect(pm.response.code).to.equal(API.ResponseStatus);",
									"});",
									"pm.test(\"Verify response time is less than \" + API.ResponseTimeMs, function () {",
									"    pm.expect(pm.response.responseTime).to.be.below(API.ResponseTimeMs);",
									"});",
									"pm.test(\"Verify response body matches expected response \", function () {",
									"    pm.expect(apiUtility.verifyResponse(API.ResponseBody, pm.response.json())).to.be.true;",
									"});",
									"// pm.test(\"Verify response value is not empty\", function () {",
									"//     pm.expect(pm.response.json().value.length).to.not.equal(0);",
									"// });",
									"//Getting the clock hours for all the scheduled state courses and adding them for check on Enrollment summary",
									"var length = pm.response.json().value.length;",
									"console.log(length)",
									"var Hours = 0;",
									"var MinutesAttended = 0;",
									"var MinutesAbsent = 0;",
									"for (; length > 0;){",
									"length--",
									"a = pm.response.json().value[length].ClockHours;",
									"Hours = Hours + a;",
									"",
									"b = pm.response.json().value[length].MinutesAttended;",
									"MinutesAttended = MinutesAttended + b;",
									"",
									"c = pm.response.json().value[length].MinutesAbsent;",
									"MinutesAbsent = MinutesAbsent + c;",
									"}",
									"console.log(Hours);",
									"pm.globals.set(\"gScheduledCourseHours\", Hours);",
									"pm.globals.set(\"gAttendedMinutes\", MinutesAttended);",
									"pm.globals.set(\"gMinutesAbsent\", MinutesAbsent);",
									"var RTSH = MinutesAttended + MinutesAbsent",
									"pm.globals.set(\"gRTSH\", RTSH);",
									"",
									"",
									"// --- END TEST VERIFICATIONS ---",
									"console.log(\"--------------------------------------------------------------------------------------\");"
								],
								"type": "text/javascript"
							}
						}
					],
					"request": {
						"auth": {
							"type": "noauth"
						},
						"method": "GET",
						"header": [
							{
								"key": "Content-Type",
								"value": "application/json"
							},
							{
								"key": "{{gAuthHeaderKey}}",
								"value": "{{gAuthHeaderValue}}"
							}
						],
						"url": {
							"raw": "{{gUrl}}",
							"host": [
								"{{gUrl}}"
							]
						}
					},
					"response": []
				},
				{
					"name": "GetStudentCourseDetailsforCurrentState",
					"event": [
						{
							"listen": "prerequest",
							"script": {
								"exec": [
									"",
									"/********************DO NOT MODIFY THIS CODE********************/",
									"// Load API utility code",
									"eval(postman.getGlobalVariable(\"gApiUtility\"));",
									"",
									"// Get API settings",
									"let apiId = \"05febb5e-f716-4402-9b26-6a4adecf5fbd\";",
									"let reqIndex = pm.globals.get(\"gIndex\");",
									"let API = pm.globals.get(\"gApis\")[apiId];",
									"if (API === undefined || API.Index !== reqIndex) {",
									"    console.log(\"ERROR - API not found for the specified apiId, \" + apiId);",
									"    pm.globals.set(\"gReqApi\", null);",
									"} else {",
									"    pm.globals.set(\"gReqApi\", API);",
									"    pm.globals.set(\"gIndex\", Number(pm.globals.get(\"gIndex\")) + 1);",
									"}",
									"//console.log(API);",
									"",
									"// Make authorization header",
									"var hdr = apiUtility.makeAuthorization(null, null, null,  pm.environment.get(\"envApiKey\"), ",
									"                                           pm.environment.get(\"envAuthUser\"), pm.environment.get(\"envAuthPassword\"));",
									"pm.globals.set(\"gAuthHeaderKey\", hdr.key);",
									"pm.globals.set(\"gAuthHeaderValue\", hdr.value);",
									"//console.log(pm.globals.get(\"gAuthHeaderKey\"));",
									"//console.log(pm.globals.get(\"gAuthHeaderValue\"));",
									"",
									"// Make request body by combining chained properties and data file request body",
									"if (API !== undefined) {",
									"    var request = { };",
									"    apiUtility.setChainProps(API.Chain, request);",
									"    var req = apiUtility.mergeRequestBody(request, API.RequestBody);",
									"    pm.globals.set(\"gRequestBody\", JSON.stringify(req));",
									"    //console.log(pm.globals.get(\"gRequestBody\"));",
									"}",
									"",
									"// Make URL",
									"if(API !== undefined) {",
									"    pm.globals.set(\"gUrl\", apiUtility.makeUrl(pm.environment.get(\"envWebScheme\"), pm.environment.get(\"envWebHost\"), API.RequestUrl));",
									"} else {",
									"    pm.globals.set(\"gUrl\", \"http://127.0.0.1\");",
									"}",
									"//console.log(pm.globals.get(\"gUrl\"));",
									"/*****************END DO NOT MODIFY THIS CODE*******************/"
								],
								"type": "text/javascript"
							}
						},
						{
							"listen": "test",
							"script": {
								"exec": [
									"/********************DO NOT MODIFY THIS CODE********************/",
									"// Load API utility code",
									"eval(postman.getGlobalVariable(\"gApiUtility\"));",
									"",
									"// Get API settings",
									"let API = pm.globals.get(\"gReqApi\");",
									"if (API === null) {",
									"    postman.setNextRequest(null);",
									"    pm.test(\"API not found for the Request ID, using fallback URL and ending the test\", function () { pm.expect.fail() });",
									"    return;",
									"}",
									"//console.log(API);",
									"",
									"// Save properties for chaining, ignore exceptions because the test will fail later anyways",
									"try {",
									"    var rb = pm.response.json();",
									"    if (API.ChainSource.length > 0) {",
									"        let str = API.RequestId + \".response\";",
									"        apiUtility.globalStoreWrite(str, rb);",
									"    }",
									"} catch (e) { console.log(\"Exception was raised during chainging, Msg -\" + e); }",
									"/*****************END DO NOT MODIFY THIS CODE*******************/",
									"",
									"// --- TEST VERIFICATIONS ---",
									"// --- Add your custom tests in this block ---",
									"pm.test(\"Verify response status is \" + API.ResponseStatus, function () {",
									"    pm.expect(pm.response.code).to.equal(API.ResponseStatus);",
									"});",
									"pm.test(\"Verify response time is less than \" + API.ResponseTimeMs, function () {",
									"    pm.expect(pm.response.responseTime).to.be.below(API.ResponseTimeMs);",
									"});",
									"pm.test(\"Verify response body matches expected response \", function () {",
									"    pm.expect(apiUtility.verifyResponse(API.ResponseBody, pm.response.json())).to.be.true;",
									"});",
									"// pm.test(\"Verify response value is not empty\", function () {",
									"//     pm.expect(pm.response.json().value.length).to.not.equal(0);",
									"// });",
									"//Getting the Clock Hours for all the scheduled state courses and adding them for check on Enrollment summary",
									"var length = pm.response.json().value.length;",
									"console.log(length)",
									"var Hours = 0;",
									"var ScheduledMinutesAttended = pm.globals.get(\"gAttendedMinutes\");",
									"var ScheduledMinutesAbsent = pm.globals.get(\"gMinutesAbsent\");",
									"for (; length > 0;){",
									"length--",
									"a = pm.response.json().value[length].ClockHours;",
									"Hours = Hours + a;",
									"",
									"b = pm.response.json().value[length].MinutesAttended;",
									"ScheduledMinutesAttended = ScheduledMinutesAttended + b;",
									"",
									"c = pm.response.json().value[length].MinutesAbsent;",
									"ScheduledMinutesAbsent = ScheduledMinutesAbsent + c;",
									"}",
									"console.log(Hours);",
									"pm.globals.set(\"gCurrentCourseHours\", Hours);",
									"console.log(ScheduledMinutesAttended);",
									"console.log(ScheduledMinutesAbsent);",
									"pm.globals.set(\"gScheduledMinutesAttended\", ScheduledMinutesAttended);",
									"pm.globals.set(\"gScheduledMinutesAbsent\", ScheduledMinutesAbsent);",
									"CompleteRTSH = ScheduledMinutesAttended + ScheduledMinutesAbsent",
									"pm.globals.set(\"gCompleteRTSH\", CompleteRTSH);",
									"",
									"",
									"",
									"// --- END TEST VERIFICATIONS ---",
									"console.log(\"--------------------------------------------------------------------------------------\");"
								],
								"type": "text/javascript"
							}
						}
					],
					"request": {
						"auth": {
							"type": "noauth"
						},
						"method": "GET",
						"header": [
							{
								"key": "Content-Type",
								"value": "application/json"
							},
							{
								"key": "{{gAuthHeaderKey}}",
								"value": "{{gAuthHeaderValue}}"
							}
						],
						"url": {
							"raw": "{{gUrl}}",
							"host": [
								"{{gUrl}}"
							]
						}
					},
					"response": []
				},
				{
					"name": "Get DPA Enrollment Summary Details",
					"event": [
						{
							"listen": "prerequest",
							"script": {
								"exec": [
									"",
									"/********************DO NOT MODIFY THIS CODE********************/",
									"// Load API utility code",
									"eval(postman.getGlobalVariable(\"gApiUtility\"));",
									"",
									"// Get API settings",
									"let apiId = \"8a8b0db0-8a03-40ad-baa0-7eae87f4a159\";",
									"let reqIndex = pm.globals.get(\"gIndex\");",
									"let API = pm.globals.get(\"gApis\")[apiId];",
									"if (API === undefined || API.Index !== reqIndex) {",
									"    console.log(\"ERROR - API not found for the specified apiId, \" + apiId);",
									"    pm.globals.set(\"gReqApi\", null);",
									"} else {",
									"    pm.globals.set(\"gReqApi\", API);",
									"    pm.globals.set(\"gIndex\", Number(pm.globals.get(\"gIndex\")) + 1);",
									"}",
									"//console.log(API);",
									"",
									"// Make authorization header",
									"var hdr = apiUtility.makeAuthorization(null, null, null,  pm.environment.get(\"envApiKey\"), ",
									"                                           pm.environment.get(\"envAuthUser\"), pm.environment.get(\"envAuthPassword\"));",
									"pm.globals.set(\"gAuthHeaderKey\", hdr.key);",
									"pm.globals.set(\"gAuthHeaderValue\", hdr.value);",
									"//console.log(pm.globals.get(\"gAuthHeaderKey\"));",
									"//console.log(pm.globals.get(\"gAuthHeaderValue\"));",
									"",
									"// Make request body by combining chained properties and data file request body",
									"if (API !== undefined) {",
									"    var request = { };",
									"    apiUtility.setChainProps(API.Chain, request);",
									"    var req = apiUtility.mergeRequestBody(request, API.RequestBody);",
									"    pm.globals.set(\"gRequestBody\", JSON.stringify(req));",
									"    //console.log(pm.globals.get(\"gRequestBody\"));",
									"}",
									"",
									"// Make URL",
									"if(API !== undefined) {",
									"    pm.globals.set(\"gUrl\", apiUtility.makeUrl(pm.environment.get(\"envWebScheme\"), pm.environment.get(\"envWebHost\"), API.RequestUrl));",
									"} else {",
									"    pm.globals.set(\"gUrl\", \"http://127.0.0.1\");",
									"}",
									"//console.log(pm.globals.get(\"gUrl\"));",
									"/*****************END DO NOT MODIFY THIS CODE*******************/"
								],
								"type": "text/javascript"
							}
						},
						{
							"listen": "test",
							"script": {
								"exec": [
									"/********************DO NOT MODIFY THIS CODE********************/",
									"// Load API utility code",
									"eval(postman.getGlobalVariable(\"gApiUtility\"));",
									"",
									"// Get API settings",
									"let API = pm.globals.get(\"gReqApi\");",
									"if (API === null) {",
									"    postman.setNextRequest(null);",
									"    pm.test(\"API not found for the Request ID, using fallback URL and ending the test\", function() { pm.expect.fail() });",
									"    return;",
									"}",
									"//console.log(API);",
									"",
									"// Save properties for chaining, ignore exceptions because the test will fail later anyways",
									"try {",
									"   var rb = pm.response.json();",
									"   if (API.ChainSource.length > 0) {",
									"      let str = API.RequestId + \".response\";",
									"      apiUtility.globalStoreWrite(str, rb);",
									"   }",
									"} catch(e) { console.log(\"Exception was raised during chainging, Msg -\" + e); }",
									"/*****************END DO NOT MODIFY THIS CODE*******************/",
									"",
									"// --- TEST VERIFICATIONS ---",
									"// --- Add your custom tests in this block ---",
									"pm.test(\"Verify response status is \" + API.ResponseStatus, function() { ",
									"     pm.expect(pm.response.code).to.equal(API.ResponseStatus);",
									"});",
									"pm.test(\"Verify response time is less than \" + API.ResponseTimeMs, function() { ",
									"     pm.expect(pm.response.responseTime).to.be.below(API.ResponseTimeMs);",
									"});",
									"// pm.test(\"Verify response value is not empty\",function(){",
									"//     pm.expect(pm.response.json()).to.not.equal(0);",
									"// });",
									"var ScheduledMinutesAttended = pm.globals.get(\"gScheduledMinutesAttended\");",
									"var CompleteRTSH = pm.globals.get(\"gCompleteRTSH\");",
									"console.log(ScheduledMinutesAttended)",
									"console.log(CompleteRTSH)",
									"pm.test(\"Verify Current Hours is null\",function(){",
									"    pm.expect(pm.response.json().calculatedTotals.currentUnits).to.equal(null);",
									"});",
									"pm.test(\"Verify Scheduled Hours is null\",function(){",
									"    pm.expect(pm.response.json().calculatedTotals.scheduledUnits).to.equal(null);",
									"});",
									"pm.test(\"Verify Real Time Scheduled Minutes is matching\",function(){",
									"    pm.expect(pm.response.json().calculatedTotals.realTimeScheduledMinutes).to.equal(CompleteRTSH);",
									"});",
									"pm.test(\"Verify Attended Minutes is matching\",function(){",
									"    pm.expect(pm.response.json().calculatedTotals.attendedMinutes).to.equal(ScheduledMinutesAttended);",
									"});",
									"// --- END TEST VERIFICATIONS ---",
									"console.log(\"--------------------------------------------------------------------------------------\");"
								],
								"type": "text/javascript"
							}
						}
					],
					"request": {
						"auth": {
							"type": "noauth"
						},
						"method": "GET",
						"header": [
							{
								"key": "Content-Type",
								"value": "application/json"
							},
							{
								"key": "{{gAuthHeaderKey}}",
								"value": "{{gAuthHeaderValue}}"
							}
						],
						"url": {
							"raw": "{{gUrl}}",
							"host": [
								"{{gUrl}}"
							]
						}
					},
					"response": []
				}
			],
			"description": "<metadata>\n<environmentfile name='StudentDPAAPIEnvironment'/>\n<data name='CheckCurrentandScheduledCreditsafterPostingAttendance'/>\n</metadata>"
		},
		{
			"name": "PostFinalGradeforCurrentCourse",
			"item": [],
			"description": "<metadata>\n<pre-request name='PostFinalGradeforDPAStudent'/>\n<environmentfile name='StudentDPAAPIEnvironment'/>\n<data name='PostFinalGradeforCurrentCourses'/>\n</metadata>"
		},
		{
			"name": "CheckCurrentandScheduledCreditsafterCompletingtheCourse",
			"item": [
				{
					"name": "Initialize",
					"event": [
						{
							"listen": "prerequest",
							"script": {
								"exec": [
									"/********************DO NOT MODIFY THIS CODE********************/",
									"pm.globals.unset(\"gApiUtility\");",
									"pm.globals.unset(\"gApiUrl\");",
									"pm.globals.unset(\"gAuthHeaderKey\");",
									"pm.globals.unset(\"gAuthHeaderValue\");",
									"pm.globals.unset(\"gUrl\");",
									"pm.globals.unset(\"gRequestBody\");",
									"pm.globals.unset(\"gIndex\");",
									"pm.globals.set(\"gIndex\", 0);",
									"",
									"// Setup URL, if web host is not set in the environment use default",
									"var apiUtilityHost = \"\";",
									"if (!pm.environment.has(\"envApiUtilityHost\")) {",
									"     apiUtilityHost = \"hdev22.dev.int:9000\";",
									"} else {",
									"     apiUtilityHost = pm.environment.get(\"envApiUtilityHost\");",
									"}",
									"var requestUrl = \"http://\" + apiUtilityHost + \"/automation/apiUtility.js\";",
									"pm.globals.set(\"gUrl\", requestUrl);",
									"//console.log(pm.globals.get(\"gUrl\"));",
									"/*****************END DO NOT MODIFY THIS CODE*******************/"
								],
								"type": "text/javascript"
							}
						},
						{
							"listen": "test",
							"script": {
								"exec": [
									"/********************CHAIN DEFINITION***************************/",
									"let chainDefinitionArray = [",
									"    {",
									"        \"RequestId\": \"a89a78ae-ffaa-479a-8c2d-1685e73055c0\",",
									"        \"RequestMethod\": \"Get\",",
									"        \"RequestUrl\": \"/ds/campusnexus/Students?$filter=Ssn eq '{{gStudentSsn}}'\",",
									"        \"ChainSource\": [",
									"            \"response.value[0].Id\"",
									"        ],",
									"        \"Chain\": [",
									"        ]",
									"    },",
									"    {",
									"         \"RequestId\"     : \"05febb5e-f716-4402-9b26-6a4adecf5fba\",",
									"         \"RequestMethod\" : \"GET\",",
									"         \"RequestUrl\"    : \"/ds/campusnexus/StudentEnrollmentPeriodDetails/CampusNexus.GetStudentEnrollmentPeriodList(studentId={{gStudentId}})?$select=Id,ProgramVersionId,ProgramId,ProgramVersionName&$filter = ProgramVersionName eq '{{gEnrollmentPVName}}'\",",
									"         \"ChainSource\"   : [",
									"               \"response.value[0].Id\"",
									"         ],",
									"         \"Chain\"         : [",
									"             ",
									"            {  ",
									"                \"SourceApiKey\":\"a89a78ae-ffaa-479a-8c2d-1685e73055c0\", ",
									"                \"SourcePath\": \"response.value[0].Id\", ",
									"                \"TargetPath\": \"globals.gStudentId\" ",
									"           }",
									"         ]",
									"    },",
									"    {",
									"         \"RequestId\"     : \"05febb5e-f716-4402-9b26-6a4adecf5fbb\",",
									"         \"RequestMethod\" : \"GET\",",
									"         \"RequestUrl\"    : \"/ds/campusnexus/StudentEnrollmentPeriods/CampusNexus.GetStudentEnrollmentPeriodWithChildDetails(studentEnrollmentPeriodId={{gStudentEnrollmentPeriodId}})?$expand=Program,Campus,EnrollmentStatus,StartTerm,SAPStatus,StatusChangeReason,ProgramVersion,SchoolStatus($expand=SystemSchoolStatus),Shift,GradeScale,Student($select=FirstName,Id,LastName;$expand=Person($select=FullName,Id))\",",
									"         \"ChainSource\"   : [",
									"         ],",
									"         \"Chain\"         : [             ",
									"            {  ",
									"                \"SourceApiKey\":\"05febb5e-f716-4402-9b26-6a4adecf5fba\", ",
									"                \"SourcePath\": \"response.value[0].Id\", ",
									"                \"TargetPath\": \"globals.gStudentEnrollmentPeriodId\" ",
									"            }",
									"         ]",
									"    },",
									"    {",
									"         \"RequestId\"     : \"05febb5e-f716-4402-9b26-6a4adecf5fbc\",",
									"         \"RequestMethod\" : \"GET\",",
									"         \"RequestUrl\"    : \"/ds/campusnexus/StudentCourseSchedules/CampusNexus.GetStudentCourseSchedule(studentEnrollmentPeriodId={{gStudentEnrollmentPeriodId}},studentId={{gStudentId}},termId=0,status='S')\",",
									"         \"ChainSource\"   : [",
									"         ],",
									"         \"Chain\"         : [             ",
									"         ]",
									"    },",
									"    {",
									"         \"RequestId\"     : \"05febb5e-f716-4402-9b26-6a4adecf5fbd\",",
									"         \"RequestMethod\" : \"GET\",",
									"         \"RequestUrl\"    : \"/ds/campusnexus/StudentCourseSchedules/CampusNexus.GetStudentCourseSchedule(studentEnrollmentPeriodId={{gStudentEnrollmentPeriodId}},studentId={{gStudentId}},termId=0,status='C')\",",
									"         \"ChainSource\"   : [",
									"         ],",
									"         \"Chain\"         : [             ",
									"         ]",
									"    },",
									"     {",
									"         \"RequestId\"     : \"05febb5e-f716-4402-9b26-6a4adecf5fbe\",",
									"         \"RequestMethod\" : \"GET\",",
									"         \"RequestUrl\"    : \"/ds/campusnexus/StudentCourseSchedules/CampusNexus.GetStudentCourseSchedule(studentEnrollmentPeriodId={{gStudentEnrollmentPeriodId}},studentId={{gStudentId}},termId=0,status='P')\",",
									"         \"ChainSource\"   : [",
									"         ],",
									"         \"Chain\"         : [             ",
									"         ]",
									"    },",
									"    {",
									"         \"RequestId\"     : \"8a8b0db0-8a03-40ad-baa0-7eae87f4a159\",",
									"         \"RequestMethod\" : \"GET\",",
									"         \"RequestUrl\"    : \"/api/dpa/v1/studentenrollmentperiods/{{gEnrollmentID}}/enrollmentsummary\",",
									"         \"ChainSource\"   : [",
									"               \"response.value[0].Id\"",
									"         ],",
									"         \"Chain\"         : [",
									"             {",
									"                   \"SourceApiKey\" : \"05febb5e-f716-4402-9b26-6a4adecf5fba\",",
									"                   \"SourcePath\"   : \"response.value[0].Id\",",
									"                   \"TargetPath\"   : \"globals.gEnrollmentID\"",
									"              }",
									"     ]",
									"    }",
									"];",
									"/********************END CHAIN DEFINITION***********************/",
									"/********************DO NOT MODIFY THIS CODE********************/",
									"// Verify status.",
									"pm.test(\"Verify response status is \" + 200, function() {",
									"    pm.expect(pm.response.code).to.equal(200);",
									"});",
									"",
									"// Load utility code framework",
									"pm.globals.set(\"gApiUtility\", responseBody);",
									"try {",
									"    eval(pm.globals.get(\"gApiUtility\"));",
									"    pm.test(\"Load framework\", function() {",
									"        pm.expect(typeof apiUtility).to.be.equal('object');",
									"    });",
									"} catch(e) { ",
									"    pm.test(\"Load framework - eval\", function() { pm.expect.fail() });",
									"}",
									"",
									"// Resolve global macros",
									"apiUtility.resolveMacros(data.Globals);",
									"",
									"// Read the data file globals section, and setup postman globals.",
									"for(var p in data.Globals) {",
									"  // If Globals own property, set global variable",
									"  if(data.Globals.hasOwnProperty(p)) { ",
									"    var gName = \"g\" + p;",
									"    pm.globals.set(gName, data.Globals[p]);",
									"    //console.log('setting global ' + gName);",
									"  }",
									"}",
									"",
									"// Save data file globals in postman global for chaining purposes.",
									"if(Object.entries(data.Globals).length > 0) {",
									"    let str = \"dataGlobals\";",
									"    apiUtility.globalStoreWrite(str, data.Globals); ",
									"}",
									"",
									"// Validate chain and Api configuration.",
									"let validationStatus = apiUtility.validateChain(data.Globals, data.Apis, chainDefinitionArray);",
									"if(!validationStatus.isValid) {",
									"    let FailFunction = function() { pm.expect.fail() };",
									"    for(let index = 0; index < validationStatus.msgs.length; ++ index) {",
									"        pm.test(\"Chain validation - \" + validationStatus.msgs[index], FailFunction);",
									"    }",
									"}",
									"",
									"// Merge data file API section with chain definition, and setup postman global",
									"if(validationStatus.isValid) {",
									"    let apis  = {};",
									"    for(let index = 0; index < data.Apis.length; ++index) {",
									"        apis[data.Apis[index].RequestId] = data.Apis[index];",
									"    }",
									"    for(let index = 0; index < chainDefinitionArray.length; ++index) {",
									"        apis[chainDefinitionArray[index].RequestId].RequestUrl = chainDefinitionArray[index].RequestUrl;",
									"        apis[chainDefinitionArray[index].RequestId].ChainSource = chainDefinitionArray[index].ChainSource;",
									"        apis[chainDefinitionArray[index].RequestId].Chain = chainDefinitionArray[index].Chain;",
									"        apis[chainDefinitionArray[index].RequestId].Index = index;",
									"    }",
									"    pm.globals.set(\"gApis\", apis);",
									"    //console.log(pm.globals.get(\"gApis\"));",
									"}",
									"",
									"// If chainging is not valid end the collection.",
									"if(!validationStatus.isValid) {",
									"    console.log(\"Chaining is invalid, terminating the test collection\");",
									"    for(let index = 0; index < validationStatus.msgs.length; ++ index) {",
									"        console.log(\"Chain validation - \" + validationStatus.msgs[index]);",
									"    }",
									"    postman.setNextRequest(null);",
									"}",
									"/*****************END DO NOT MODIFY THIS CODE*******************/",
									"",
									"console.log(\"--------------------------------------------------------------------------------------\");",
									""
								],
								"type": "text/javascript"
							}
						}
					],
					"request": {
						"auth": {
							"type": "noauth"
						},
						"method": "GET",
						"header": [
							{
								"key": "Content-Type",
								"value": "application/json"
							}
						],
						"url": {
							"raw": "{{gUrl}}",
							"host": [
								"{{gUrl}}"
							]
						}
					},
					"response": []
				},
				{
					"name": "Get Student Id by SSN",
					"event": [
						{
							"listen": "prerequest",
							"script": {
								"exec": [
									"",
									"/********************DO NOT MODIFY THIS CODE********************/",
									"// Load API utility code",
									"eval(postman.getGlobalVariable(\"gApiUtility\"));",
									"",
									"// Get API settings",
									"let apiId = \"a89a78ae-ffaa-479a-8c2d-1685e73055c0\";",
									"let reqIndex = pm.globals.get(\"gIndex\");",
									"let API = pm.globals.get(\"gApis\")[apiId];",
									"if (API === undefined || API.Index !== reqIndex) {",
									"    console.log(\"ERROR - API not found for the specified apiId, \" + apiId);",
									"    pm.globals.set(\"gReqApi\", null);",
									"} else {",
									"    pm.globals.set(\"gReqApi\", API);",
									"    pm.globals.set(\"gIndex\", Number(pm.globals.get(\"gIndex\")) + 1);",
									"}",
									"//console.log(API);",
									"",
									"// Make authorization header",
									"var hdr = apiUtility.makeAuthorization(null, null, null, pm.environment.get(\"envApiKey\"),",
									"    pm.environment.get(\"envAuthUser\"), pm.environment.get(\"envAuthPassword\"));",
									"pm.globals.set(\"gAuthHeaderKey\", hdr.key);",
									"pm.globals.set(\"gAuthHeaderValue\", hdr.value);",
									"//console.log(pm.globals.get(\"gAuthHeaderKey\"));",
									"//console.log(pm.globals.get(\"gAuthHeaderValue\"));",
									"",
									"// Make request body by combining chained properties and data file request body",
									"if (API !== undefined) {",
									"    var request = {};",
									"    apiUtility.setChainProps(API.Chain, request);",
									"    var req = apiUtility.mergeRequestBody(request, API.RequestBody);",
									"    pm.globals.set(\"gRequestBody\", JSON.stringify(req));",
									"    //console.log(pm.globals.get(\"gRequestBody\"));",
									"}",
									"",
									"// Make URL",
									"if (API !== undefined) {",
									"    pm.globals.set(\"gUrl\", apiUtility.makeUrl(pm.environment.get(\"envWebScheme\"), pm.environment.get(\"envWebHost\"), API.RequestUrl));",
									"} else {",
									"    pm.globals.set(\"gUrl\", \"http://127.0.0.1\");",
									"}",
									"",
									"//console.log(pm.globals.get(\"gUrl\"));",
									"/*****************END DO NOT MODIFY THIS CODE*******************/"
								],
								"type": "text/javascript"
							}
						},
						{
							"listen": "test",
							"script": {
								"exec": [
									"/********************DO NOT MODIFY THIS CODE********************/",
									"// Load API utility code",
									"eval(postman.getGlobalVariable(\"gApiUtility\"));",
									"",
									"// Get API settings",
									"let API = pm.globals.get(\"gReqApi\");",
									"if (API === null) {",
									"    postman.setNextRequest(null);",
									"    pm.test(\"API not found for the Request ID, using fallback URL and ending the test\", function() { pm.expect.fail() });",
									"    return;",
									"}",
									"//console.log(API);",
									"",
									"// Save properties for chaining, ignore exceptions because the test will fail later anyways",
									"try {",
									"   var rb = pm.response.json();",
									"   if (API.ChainSource.length > 0) {",
									"      let str = API.RequestId + \".response\";",
									"      apiUtility.globalStoreWrite(str, rb);",
									"   }",
									"} catch(e) { console.log(\"Exception was raised during chainging, Msg -\" + e); }",
									"/*****************END DO NOT MODIFY THIS CODE*******************/",
									"",
									"// --- TEST VERIFICATIONS ---",
									"// --- Add your custom tests in this block ---",
									"pm.test(\"Verify response status is \" + API.ResponseStatus, function() { ",
									"     pm.expect(pm.response.code).to.equal(API.ResponseStatus);",
									"});",
									"pm.test(\"Verify response time is less than \" + API.ResponseTimeMs, function() { ",
									"     pm.expect(pm.response.responseTime).to.be.below(API.ResponseTimeMs);",
									"});",
									"pm.test(\"Verify response body matches expected response \", function() { ",
									"     pm.expect(apiUtility.verifyResponse(API.ResponseBody, pm.response.json())).to.be.true;",
									"});",
									"",
									"pm.test(\"Verify response value is not empty \", function() {",
									"    pm.expect(pm.response.json().value.length).to.not.equal(0);",
									"});",
									"// --- END TEST VERIFICATIONS ---",
									"console.log(\"--------------------------------------------------------------------------------------\");"
								],
								"type": "text/javascript"
							}
						}
					],
					"request": {
						"auth": {
							"type": "noauth"
						},
						"method": "GET",
						"header": [
							{
								"key": "Content-Type",
								"value": "application/json"
							},
							{
								"key": "{{gAuthHeaderKey}}",
								"value": "{{gAuthHeaderValue}}"
							}
						],
						"url": {
							"raw": "{{gUrl}}",
							"host": [
								"{{gUrl}}"
							]
						}
					},
					"response": []
				},
				{
					"name": "Get Enrollment ID",
					"event": [
						{
							"listen": "prerequest",
							"script": {
								"exec": [
									"",
									"/********************DO NOT MODIFY THIS CODE********************/",
									"// Load API utility code",
									"eval(postman.getGlobalVariable(\"gApiUtility\"));",
									"",
									"// Get API settings",
									"let apiId = \"05febb5e-f716-4402-9b26-6a4adecf5fba\";",
									"let reqIndex = pm.globals.get(\"gIndex\");",
									"let API = pm.globals.get(\"gApis\")[apiId];",
									"if (API === undefined || API.Index !== reqIndex) {",
									"    console.log(\"ERROR - API not found for the specified apiId, \" + apiId);",
									"    pm.globals.set(\"gReqApi\", null);",
									"} else {",
									"    pm.globals.set(\"gReqApi\", API);",
									"    pm.globals.set(\"gIndex\", Number(pm.globals.get(\"gIndex\")) + 1);",
									"}",
									"//console.log(API);",
									"",
									"// Make authorization header",
									"var hdr = apiUtility.makeAuthorization(null, null, null,  pm.environment.get(\"envApiKey\"), ",
									"                                           pm.environment.get(\"envAuthUser\"), pm.environment.get(\"envAuthPassword\"));",
									"pm.globals.set(\"gAuthHeaderKey\", hdr.key);",
									"pm.globals.set(\"gAuthHeaderValue\", hdr.value);",
									"//console.log(pm.globals.get(\"gAuthHeaderKey\"));",
									"//console.log(pm.globals.get(\"gAuthHeaderValue\"));",
									"",
									"// Make request body by combining chained properties and data file request body",
									"if (API !== undefined) {",
									"    var request = { };",
									"    apiUtility.setChainProps(API.Chain, request);",
									"    var req = apiUtility.mergeRequestBody(request, API.RequestBody);",
									"    pm.globals.set(\"gRequestBody\", JSON.stringify(req));",
									"    //console.log(pm.globals.get(\"gRequestBody\"));",
									"}",
									"",
									"// Make URL",
									"if(API !== undefined) {",
									"    pm.globals.set(\"gUrl\", apiUtility.makeUrl(pm.environment.get(\"envWebScheme\"), pm.environment.get(\"envWebHost\"), API.RequestUrl));",
									"} else {",
									"    pm.globals.set(\"gUrl\", \"http://127.0.0.1\");",
									"}",
									"//console.log(pm.globals.get(\"gUrl\"));",
									"/*****************END DO NOT MODIFY THIS CODE*******************/"
								],
								"type": "text/javascript"
							}
						},
						{
							"listen": "test",
							"script": {
								"exec": [
									"/********************DO NOT MODIFY THIS CODE********************/",
									"// Load API utility code",
									"eval(postman.getGlobalVariable(\"gApiUtility\"));",
									"",
									"// Get API settings",
									"let API = pm.globals.get(\"gReqApi\");",
									"if (API === null) {",
									"    postman.setNextRequest(null);",
									"    pm.test(\"API not found for the Request ID, using fallback URL and ending the test\", function() { pm.expect.fail() });",
									"    return;",
									"}",
									"//console.log(API);",
									"",
									"// Save properties for chaining, ignore exceptions because the test will fail later anyways",
									"try {",
									"   var rb = pm.response.json();",
									"   if (API.ChainSource.length > 0) {",
									"      let str = API.RequestId + \".response\";",
									"      apiUtility.globalStoreWrite(str, rb);",
									"   }",
									"} catch(e) { console.log(\"Exception was raised during chainging, Msg -\" + e); }",
									"/*****************END DO NOT MODIFY THIS CODE*******************/",
									"",
									"// --- TEST VERIFICATIONS ---",
									"// --- Add your custom tests in this block ---",
									"pm.test(\"Verify response status is \" + API.ResponseStatus, function() { ",
									"     pm.expect(pm.response.code).to.equal(API.ResponseStatus);",
									"});",
									"pm.test(\"Verify response time is less than \" + API.ResponseTimeMs, function() { ",
									"     pm.expect(pm.response.responseTime).to.be.below(API.ResponseTimeMs);",
									"});",
									"pm.test(\"Verify response body matches expected response \", function() { ",
									"     pm.expect(apiUtility.verifyResponse(API.ResponseBody, pm.response.json())).to.be.true;",
									"});",
									"pm.test(\"Verify response value is not empty\",function(){",
									"    pm.expect(pm.response.json().value.length).to.not.equal(0);",
									"});",
									"// --- END TEST VERIFICATIONS ---",
									"console.log(\"--------------------------------------------------------------------------------------\");"
								],
								"type": "text/javascript"
							}
						}
					],
					"request": {
						"auth": {
							"type": "noauth"
						},
						"method": "GET",
						"header": [
							{
								"key": "Content-Type",
								"value": "application/json"
							},
							{
								"key": "{{gAuthHeaderKey}}",
								"value": "{{gAuthHeaderValue}}"
							}
						],
						"url": {
							"raw": "{{gUrl}}",
							"host": [
								"{{gUrl}}"
							]
						}
					},
					"response": []
				},
				{
					"name": "GetStudentEnrollmentPeriodWithChildDetails",
					"event": [
						{
							"listen": "prerequest",
							"script": {
								"exec": [
									"",
									"/********************DO NOT MODIFY THIS CODE********************/",
									"// Load API utility code",
									"eval(postman.getGlobalVariable(\"gApiUtility\"));",
									"",
									"// Get API settings",
									"let apiId = \"05febb5e-f716-4402-9b26-6a4adecf5fbb\";",
									"let reqIndex = pm.globals.get(\"gIndex\");",
									"let API = pm.globals.get(\"gApis\")[apiId];",
									"if (API === undefined || API.Index !== reqIndex) {",
									"    console.log(\"ERROR - API not found for the specified apiId, \" + apiId);",
									"    pm.globals.set(\"gReqApi\", null);",
									"} else {",
									"    pm.globals.set(\"gReqApi\", API);",
									"    pm.globals.set(\"gIndex\", Number(pm.globals.get(\"gIndex\")) + 1);",
									"}",
									"//console.log(API);",
									"",
									"// Make authorization header",
									"var hdr = apiUtility.makeAuthorization(null, null, null,  pm.environment.get(\"envApiKey\"), ",
									"                                           pm.environment.get(\"envAuthUser\"), pm.environment.get(\"envAuthPassword\"));",
									"pm.globals.set(\"gAuthHeaderKey\", hdr.key);",
									"pm.globals.set(\"gAuthHeaderValue\", hdr.value);",
									"//console.log(pm.globals.get(\"gAuthHeaderKey\"));",
									"//console.log(pm.globals.get(\"gAuthHeaderValue\"));",
									"",
									"// Make request body by combining chained properties and data file request body",
									"if (API !== undefined) {",
									"    var request = { };",
									"    apiUtility.setChainProps(API.Chain, request);",
									"    var req = apiUtility.mergeRequestBody(request, API.RequestBody);",
									"    pm.globals.set(\"gRequestBody\", JSON.stringify(req));",
									"    //console.log(pm.globals.get(\"gRequestBody\"));",
									"}",
									"",
									"// Make URL",
									"if(API !== undefined) {",
									"    pm.globals.set(\"gUrl\", apiUtility.makeUrl(pm.environment.get(\"envWebScheme\"), pm.environment.get(\"envWebHost\"), API.RequestUrl));",
									"} else {",
									"    pm.globals.set(\"gUrl\", \"http://127.0.0.1\");",
									"}",
									"//console.log(pm.globals.get(\"gUrl\"));",
									"/*****************END DO NOT MODIFY THIS CODE*******************/"
								],
								"type": "text/javascript"
							}
						},
						{
							"listen": "test",
							"script": {
								"exec": [
									"/********************DO NOT MODIFY THIS CODE********************/",
									"// Load API utility code",
									"eval(postman.getGlobalVariable(\"gApiUtility\"));",
									"",
									"// Get API settings",
									"let API = pm.globals.get(\"gReqApi\");",
									"if (API === null) {",
									"    postman.setNextRequest(null);",
									"    pm.test(\"API not found for the Request ID, using fallback URL and ending the test\", function() { pm.expect.fail() });",
									"    return;",
									"}",
									"//console.log(API);",
									"",
									"// Save properties for chaining, ignore exceptions because the test will fail later anyways",
									"try {",
									"   var rb = pm.response.json();",
									"   if (API.ChainSource.length > 0) {",
									"      let str = API.RequestId + \".response\";",
									"      apiUtility.globalStoreWrite(str, rb);",
									"   }",
									"} catch(e) { console.log(\"Exception was raised during chainging, Msg -\" + e); }",
									"/*****************END DO NOT MODIFY THIS CODE*******************/",
									"",
									"// --- TEST VERIFICATIONS ---",
									"// --- Add your custom tests in this block ---",
									"pm.test(\"Verify response status is \" + API.ResponseStatus, function() { ",
									"     pm.expect(pm.response.code).to.equal(API.ResponseStatus);",
									"});",
									"pm.test(\"Verify response time is less than \" + API.ResponseTimeMs, function() { ",
									"     pm.expect(pm.response.responseTime).to.be.below(API.ResponseTimeMs);",
									"});",
									"pm.test(\"Verify response body matches expected response \", function() { ",
									"     pm.expect(apiUtility.verifyResponse(API.ResponseBody, pm.response.json())).to.be.true;",
									"});",
									"pm.test(\"Verify response value is not empty\",function(){",
									"    pm.expect(pm.response.json().value.length).to.not.equal(0);",
									"});",
									"",
									"//create a new varaiable to get the details",
									"var PVCode = rb.value[0].ProgramVersion.Code;",
									"var DegreeId = rb.value[0].ProgramVersion.DegreeId;",
									"var ProgramVersionUnitType = rb.value[0].ProgramVersion.ProgramVersionUnitType;",
									"var CatalogYearId = rb.value[0].CatalogYearId;",
									"",
									"//set the varaiables to globals",
									"pm.globals.set(\"gPVCode\",PVCode);",
									"pm.globals.set(\"gDegreeId\",DegreeId);",
									"pm.globals.set(\"gProgramVersionUnitType\",ProgramVersionUnitType);",
									"pm.globals.set(\"gCatalogYearId\",CatalogYearId);",
									"",
									"// --- END TEST VERIFICATIONS ---",
									"console.log(\"--------------------------------------------------------------------------------------\");"
								],
								"type": "text/javascript"
							}
						}
					],
					"request": {
						"auth": {
							"type": "noauth"
						},
						"method": "GET",
						"header": [
							{
								"key": "Content-Type",
								"value": "application/json"
							},
							{
								"key": "{{gAuthHeaderKey}}",
								"value": "{{gAuthHeaderValue}}"
							}
						],
						"url": {
							"raw": "{{gUrl}}",
							"host": [
								"{{gUrl}}"
							]
						}
					},
					"response": []
				},
				{
					"name": "GetStudentCourseDetailsforScheduledState",
					"event": [
						{
							"listen": "prerequest",
							"script": {
								"exec": [
									"",
									"/********************DO NOT MODIFY THIS CODE********************/",
									"// Load API utility code",
									"eval(postman.getGlobalVariable(\"gApiUtility\"));",
									"",
									"// Get API settings",
									"let apiId = \"05febb5e-f716-4402-9b26-6a4adecf5fbc\";",
									"let reqIndex = pm.globals.get(\"gIndex\");",
									"let API = pm.globals.get(\"gApis\")[apiId];",
									"if (API === undefined || API.Index !== reqIndex) {",
									"    console.log(\"ERROR - API not found for the specified apiId, \" + apiId);",
									"    pm.globals.set(\"gReqApi\", null);",
									"} else {",
									"    pm.globals.set(\"gReqApi\", API);",
									"    pm.globals.set(\"gIndex\", Number(pm.globals.get(\"gIndex\")) + 1);",
									"}",
									"//console.log(API);",
									"",
									"// Make authorization header",
									"var hdr = apiUtility.makeAuthorization(null, null, null,  pm.environment.get(\"envApiKey\"), ",
									"                                           pm.environment.get(\"envAuthUser\"), pm.environment.get(\"envAuthPassword\"));",
									"pm.globals.set(\"gAuthHeaderKey\", hdr.key);",
									"pm.globals.set(\"gAuthHeaderValue\", hdr.value);",
									"//console.log(pm.globals.get(\"gAuthHeaderKey\"));",
									"//console.log(pm.globals.get(\"gAuthHeaderValue\"));",
									"",
									"// Make request body by combining chained properties and data file request body",
									"if (API !== undefined) {",
									"    var request = { };",
									"    apiUtility.setChainProps(API.Chain, request);",
									"    var req = apiUtility.mergeRequestBody(request, API.RequestBody);",
									"    pm.globals.set(\"gRequestBody\", JSON.stringify(req));",
									"    //console.log(pm.globals.get(\"gRequestBody\"));",
									"}",
									"",
									"// Make URL",
									"if(API !== undefined) {",
									"    pm.globals.set(\"gUrl\", apiUtility.makeUrl(pm.environment.get(\"envWebScheme\"), pm.environment.get(\"envWebHost\"), API.RequestUrl));",
									"} else {",
									"    pm.globals.set(\"gUrl\", \"http://127.0.0.1\");",
									"}",
									"//console.log(pm.globals.get(\"gUrl\"));",
									"/*****************END DO NOT MODIFY THIS CODE*******************/"
								],
								"type": "text/javascript"
							}
						},
						{
							"listen": "test",
							"script": {
								"exec": [
									"/********************DO NOT MODIFY THIS CODE********************/",
									"// Load API utility code",
									"eval(postman.getGlobalVariable(\"gApiUtility\"));",
									"",
									"// Get API settings",
									"let API = pm.globals.get(\"gReqApi\");",
									"if (API === null) {",
									"    postman.setNextRequest(null);",
									"    pm.test(\"API not found for the Request ID, using fallback URL and ending the test\", function () { pm.expect.fail() });",
									"    return;",
									"}",
									"//console.log(API);",
									"",
									"// Save properties for chaining, ignore exceptions because the test will fail later anyways",
									"try {",
									"    var rb = pm.response.json();",
									"    if (API.ChainSource.length > 0) {",
									"        let str = API.RequestId + \".response\";",
									"        apiUtility.globalStoreWrite(str, rb);",
									"    }",
									"} catch (e) { console.log(\"Exception was raised during chainging, Msg -\" + e); }",
									"/*****************END DO NOT MODIFY THIS CODE*******************/",
									"",
									"// --- TEST VERIFICATIONS ---",
									"// --- Add your custom tests in this block ---",
									"pm.test(\"Verify response status is \" + API.ResponseStatus, function () {",
									"    pm.expect(pm.response.code).to.equal(API.ResponseStatus);",
									"});",
									"pm.test(\"Verify response time is less than \" + API.ResponseTimeMs, function () {",
									"    pm.expect(pm.response.responseTime).to.be.below(API.ResponseTimeMs);",
									"});",
									"pm.test(\"Verify response body matches expected response \", function () {",
									"    pm.expect(apiUtility.verifyResponse(API.ResponseBody, pm.response.json())).to.be.true;",
									"});",
									"// pm.test(\"Verify response value is not empty\", function () {",
									"//     pm.expect(pm.response.json().value.length).to.not.equal(0);",
									"// });",
									"//Getting the clock hours for all the scheduled state courses and adding them for check on Enrollment summary",
									"var length = pm.response.json().value.length;",
									"console.log(length)",
									"var Hours = 0;",
									"var MinutesAttended = 0;",
									"var MinutesAbsent = 0;",
									"for (; length > 0;){",
									"length--",
									"a = pm.response.json().value[length].ClockHours;",
									"Hours = Hours + a;",
									"",
									"b = pm.response.json().value[length].MinutesAttended;",
									"MinutesAttended = MinutesAttended + b;",
									"",
									"c = pm.response.json().value[length].MinutesAbsent;",
									"MinutesAbsent = MinutesAbsent + c;",
									"}",
									"console.log(Hours);",
									"console.log(MinutesAttended);",
									"console.log(MinutesAbsent);",
									"pm.globals.set(\"gScheduledCourseHours\", Hours);",
									"pm.globals.set(\"gAttendedMinutes\", MinutesAttended);",
									"pm.globals.set(\"gMinutesAbsent\", MinutesAbsent);",
									"var RTSH = MinutesAttended + MinutesAbsent",
									"pm.globals.set(\"gRTSH\", RTSH);",
									"",
									"",
									"",
									"// --- END TEST VERIFICATIONS ---",
									"console.log(\"--------------------------------------------------------------------------------------\");"
								],
								"type": "text/javascript"
							}
						}
					],
					"request": {
						"auth": {
							"type": "noauth"
						},
						"method": "GET",
						"header": [
							{
								"key": "Content-Type",
								"value": "application/json"
							},
							{
								"key": "{{gAuthHeaderKey}}",
								"value": "{{gAuthHeaderValue}}"
							}
						],
						"url": {
							"raw": "{{gUrl}}",
							"host": [
								"{{gUrl}}"
							]
						}
					},
					"response": []
				},
				{
					"name": "GetStudentCourseDetailsforCurrentState",
					"event": [
						{
							"listen": "prerequest",
							"script": {
								"exec": [
									"",
									"/********************DO NOT MODIFY THIS CODE********************/",
									"// Load API utility code",
									"eval(postman.getGlobalVariable(\"gApiUtility\"));",
									"",
									"// Get API settings",
									"let apiId = \"05febb5e-f716-4402-9b26-6a4adecf5fbd\";",
									"let reqIndex = pm.globals.get(\"gIndex\");",
									"let API = pm.globals.get(\"gApis\")[apiId];",
									"if (API === undefined || API.Index !== reqIndex) {",
									"    console.log(\"ERROR - API not found for the specified apiId, \" + apiId);",
									"    pm.globals.set(\"gReqApi\", null);",
									"} else {",
									"    pm.globals.set(\"gReqApi\", API);",
									"    pm.globals.set(\"gIndex\", Number(pm.globals.get(\"gIndex\")) + 1);",
									"}",
									"//console.log(API);",
									"",
									"// Make authorization header",
									"var hdr = apiUtility.makeAuthorization(null, null, null,  pm.environment.get(\"envApiKey\"), ",
									"                                           pm.environment.get(\"envAuthUser\"), pm.environment.get(\"envAuthPassword\"));",
									"pm.globals.set(\"gAuthHeaderKey\", hdr.key);",
									"pm.globals.set(\"gAuthHeaderValue\", hdr.value);",
									"//console.log(pm.globals.get(\"gAuthHeaderKey\"));",
									"//console.log(pm.globals.get(\"gAuthHeaderValue\"));",
									"",
									"// Make request body by combining chained properties and data file request body",
									"if (API !== undefined) {",
									"    var request = { };",
									"    apiUtility.setChainProps(API.Chain, request);",
									"    var req = apiUtility.mergeRequestBody(request, API.RequestBody);",
									"    pm.globals.set(\"gRequestBody\", JSON.stringify(req));",
									"    //console.log(pm.globals.get(\"gRequestBody\"));",
									"}",
									"",
									"// Make URL",
									"if(API !== undefined) {",
									"    pm.globals.set(\"gUrl\", apiUtility.makeUrl(pm.environment.get(\"envWebScheme\"), pm.environment.get(\"envWebHost\"), API.RequestUrl));",
									"} else {",
									"    pm.globals.set(\"gUrl\", \"http://127.0.0.1\");",
									"}",
									"//console.log(pm.globals.get(\"gUrl\"));",
									"/*****************END DO NOT MODIFY THIS CODE*******************/"
								],
								"type": "text/javascript"
							}
						},
						{
							"listen": "test",
							"script": {
								"exec": [
									"/********************DO NOT MODIFY THIS CODE********************/",
									"// Load API utility code",
									"eval(postman.getGlobalVariable(\"gApiUtility\"));",
									"",
									"// Get API settings",
									"let API = pm.globals.get(\"gReqApi\");",
									"if (API === null) {",
									"    postman.setNextRequest(null);",
									"    pm.test(\"API not found for the Request ID, using fallback URL and ending the test\", function () { pm.expect.fail() });",
									"    return;",
									"}",
									"//console.log(API);",
									"",
									"// Save properties for chaining, ignore exceptions because the test will fail later anyways",
									"try {",
									"    var rb = pm.response.json();",
									"    if (API.ChainSource.length > 0) {",
									"        let str = API.RequestId + \".response\";",
									"        apiUtility.globalStoreWrite(str, rb);",
									"    }",
									"} catch (e) { console.log(\"Exception was raised during chainging, Msg -\" + e); }",
									"/*****************END DO NOT MODIFY THIS CODE*******************/",
									"",
									"// --- TEST VERIFICATIONS ---",
									"// --- Add your custom tests in this block ---",
									"pm.test(\"Verify response status is \" + API.ResponseStatus, function () {",
									"    pm.expect(pm.response.code).to.equal(API.ResponseStatus);",
									"});",
									"pm.test(\"Verify response time is less than \" + API.ResponseTimeMs, function () {",
									"    pm.expect(pm.response.responseTime).to.be.below(API.ResponseTimeMs);",
									"});",
									"pm.test(\"Verify response body matches expected response \", function () {",
									"    pm.expect(apiUtility.verifyResponse(API.ResponseBody, pm.response.json())).to.be.true;",
									"});",
									"// pm.test(\"Verify response value is not empty\", function () {",
									"//     pm.expect(pm.response.json().value.length).to.not.equal(0);",
									"// });",
									"//Getting the Clock Hours for all the scheduled state courses and adding them for check on Enrollment summary",
									"var length = pm.response.json().value.length;",
									"console.log(length)",
									"var Hours = 0;",
									"var ScheduledMinutesAttended = pm.globals.get(\"gAttendedMinutes\");",
									"var ScheduledMinutesAbsent = pm.globals.get(\"gMinutesAbsent\");",
									"for (; length > 0;){",
									"length--",
									"a = pm.response.json().value[length].ClockHours;",
									"Hours = Hours + a;",
									"",
									"b = pm.response.json().value[length].MinutesAttended;",
									"ScheduledMinutesAttended = ScheduledMinutesAttended + b;",
									"",
									"c = pm.response.json().value[length].MinutesAbsent;",
									"ScheduledMinutesAbsent = ScheduledMinutesAbsent + c;",
									"}",
									"console.log(Hours);",
									"console.log(ScheduledMinutesAttended);",
									"console.log(ScheduledMinutesAbsent);",
									"pm.globals.set(\"gCurrentCourseHours\", Hours);",
									"pm.globals.set(\"gScheduledMinutesAttended\", ScheduledMinutesAttended);",
									"pm.globals.set(\"gScheduledMinutesAbsent\", ScheduledMinutesAbsent);",
									"var RTSH = ScheduledMinutesAttended + ScheduledMinutesAbsent",
									"pm.globals.set(\"gRTSH\", RTSH);",
									"",
									"",
									"",
									"// --- END TEST VERIFICATIONS ---",
									"console.log(\"--------------------------------------------------------------------------------------\");"
								],
								"type": "text/javascript"
							}
						}
					],
					"request": {
						"auth": {
							"type": "noauth"
						},
						"method": "GET",
						"header": [
							{
								"key": "Content-Type",
								"value": "application/json"
							},
							{
								"key": "{{gAuthHeaderKey}}",
								"value": "{{gAuthHeaderValue}}"
							}
						],
						"url": {
							"raw": "{{gUrl}}",
							"host": [
								"{{gUrl}}"
							]
						}
					},
					"response": []
				},
				{
					"name": "GetStudentCourseDetailsforCompleteState",
					"event": [
						{
							"listen": "prerequest",
							"script": {
								"exec": [
									"",
									"/********************DO NOT MODIFY THIS CODE********************/",
									"// Load API utility code",
									"eval(postman.getGlobalVariable(\"gApiUtility\"));",
									"",
									"// Get API settings",
									"let apiId = \"05febb5e-f716-4402-9b26-6a4adecf5fbe\";",
									"let reqIndex = pm.globals.get(\"gIndex\");",
									"let API = pm.globals.get(\"gApis\")[apiId];",
									"if (API === undefined || API.Index !== reqIndex) {",
									"    console.log(\"ERROR - API not found for the specified apiId, \" + apiId);",
									"    pm.globals.set(\"gReqApi\", null);",
									"} else {",
									"    pm.globals.set(\"gReqApi\", API);",
									"    pm.globals.set(\"gIndex\", Number(pm.globals.get(\"gIndex\")) + 1);",
									"}",
									"//console.log(API);",
									"",
									"// Make authorization header",
									"var hdr = apiUtility.makeAuthorization(null, null, null,  pm.environment.get(\"envApiKey\"), ",
									"                                           pm.environment.get(\"envAuthUser\"), pm.environment.get(\"envAuthPassword\"));",
									"pm.globals.set(\"gAuthHeaderKey\", hdr.key);",
									"pm.globals.set(\"gAuthHeaderValue\", hdr.value);",
									"//console.log(pm.globals.get(\"gAuthHeaderKey\"));",
									"//console.log(pm.globals.get(\"gAuthHeaderValue\"));",
									"",
									"// Make request body by combining chained properties and data file request body",
									"if (API !== undefined) {",
									"    var request = { };",
									"    apiUtility.setChainProps(API.Chain, request);",
									"    var req = apiUtility.mergeRequestBody(request, API.RequestBody);",
									"    pm.globals.set(\"gRequestBody\", JSON.stringify(req));",
									"    //console.log(pm.globals.get(\"gRequestBody\"));",
									"}",
									"",
									"// Make URL",
									"if(API !== undefined) {",
									"    pm.globals.set(\"gUrl\", apiUtility.makeUrl(pm.environment.get(\"envWebScheme\"), pm.environment.get(\"envWebHost\"), API.RequestUrl));",
									"} else {",
									"    pm.globals.set(\"gUrl\", \"http://127.0.0.1\");",
									"}",
									"//console.log(pm.globals.get(\"gUrl\"));",
									"/*****************END DO NOT MODIFY THIS CODE*******************/"
								],
								"type": "text/javascript"
							}
						},
						{
							"listen": "test",
							"script": {
								"exec": [
									"/********************DO NOT MODIFY THIS CODE********************/",
									"// Load API utility code",
									"eval(postman.getGlobalVariable(\"gApiUtility\"));",
									"",
									"// Get API settings",
									"let API = pm.globals.get(\"gReqApi\");",
									"if (API === null) {",
									"    postman.setNextRequest(null);",
									"    pm.test(\"API not found for the Request ID, using fallback URL and ending the test\", function () { pm.expect.fail() });",
									"    return;",
									"}",
									"//console.log(API);",
									"",
									"// Save properties for chaining, ignore exceptions because the test will fail later anyways",
									"try {",
									"    var rb = pm.response.json();",
									"    if (API.ChainSource.length > 0) {",
									"        let str = API.RequestId + \".response\";",
									"        apiUtility.globalStoreWrite(str, rb);",
									"    }",
									"} catch (e) { console.log(\"Exception was raised during chainging, Msg -\" + e); }",
									"/*****************END DO NOT MODIFY THIS CODE*******************/",
									"",
									"// --- TEST VERIFICATIONS ---",
									"// --- Add your custom tests in this block ---",
									"pm.test(\"Verify response status is \" + API.ResponseStatus, function () {",
									"    pm.expect(pm.response.code).to.equal(API.ResponseStatus);",
									"});",
									"pm.test(\"Verify response time is less than \" + API.ResponseTimeMs, function () {",
									"    pm.expect(pm.response.responseTime).to.be.below(API.ResponseTimeMs);",
									"});",
									"pm.test(\"Verify response body matches expected response \", function () {",
									"    pm.expect(apiUtility.verifyResponse(API.ResponseBody, pm.response.json())).to.be.true;",
									"});",
									"// pm.test(\"Verify response value is not empty\", function () {",
									"//     pm.expect(pm.response.json().value.length).to.not.equal(0);",
									"// });",
									"//Getting the Clock Hours for all the scheduled state courses and adding them for check on Enrollment summary",
									"var length = pm.response.json().value.length;",
									"console.log(length)",
									"var CompletedMinutesAttended = pm.globals.get(\"gScheduledMinutesAttended\");",
									"var CompletedMinutesAbsent = pm.globals.get(\"gScheduledMinutesAbsent\");",
									"for (; length > 0;){",
									"length--",
									"c = pm.response.json().value[length].MinutesAttended;",
									"CompletedMinutesAttended = CompletedMinutesAttended + c;",
									"",
									"d = pm.response.json().value[length].MinutesAbsent;",
									"CompletedMinutesAbsent = CompletedMinutesAbsent + d;",
									"}",
									"console.log(CompletedMinutesAttended);",
									"console.log(CompletedMinutesAbsent);",
									"pm.globals.set(\"gCompletedMinutesAttended\", CompletedMinutesAttended);",
									"pm.globals.set(\"gCompletedMinutesAbsent\", CompletedMinutesAbsent);",
									"CompleteRTSH = CompletedMinutesAttended + CompletedMinutesAbsent",
									"pm.globals.set(\"gCompleteRTSH\", CompleteRTSH);",
									"",
									"",
									"// --- END TEST VERIFICATIONS ---",
									"console.log(\"--------------------------------------------------------------------------------------\");"
								],
								"type": "text/javascript"
							}
						}
					],
					"request": {
						"auth": {
							"type": "noauth"
						},
						"method": "GET",
						"header": [
							{
								"key": "Content-Type",
								"value": "application/json"
							},
							{
								"key": "{{gAuthHeaderKey}}",
								"value": "{{gAuthHeaderValue}}"
							}
						],
						"url": {
							"raw": "{{gUrl}}",
							"host": [
								"{{gUrl}}"
							]
						}
					},
					"response": []
				},
				{
					"name": "Get DPA Enrollment Summary Details",
					"event": [
						{
							"listen": "prerequest",
							"script": {
								"exec": [
									"",
									"/********************DO NOT MODIFY THIS CODE********************/",
									"// Load API utility code",
									"eval(postman.getGlobalVariable(\"gApiUtility\"));",
									"",
									"// Get API settings",
									"let apiId = \"8a8b0db0-8a03-40ad-baa0-7eae87f4a159\";",
									"let reqIndex = pm.globals.get(\"gIndex\");",
									"let API = pm.globals.get(\"gApis\")[apiId];",
									"if (API === undefined || API.Index !== reqIndex) {",
									"    console.log(\"ERROR - API not found for the specified apiId, \" + apiId);",
									"    pm.globals.set(\"gReqApi\", null);",
									"} else {",
									"    pm.globals.set(\"gReqApi\", API);",
									"    pm.globals.set(\"gIndex\", Number(pm.globals.get(\"gIndex\")) + 1);",
									"}",
									"//console.log(API);",
									"",
									"// Make authorization header",
									"var hdr = apiUtility.makeAuthorization(null, null, null,  pm.environment.get(\"envApiKey\"), ",
									"                                           pm.environment.get(\"envAuthUser\"), pm.environment.get(\"envAuthPassword\"));",
									"pm.globals.set(\"gAuthHeaderKey\", hdr.key);",
									"pm.globals.set(\"gAuthHeaderValue\", hdr.value);",
									"//console.log(pm.globals.get(\"gAuthHeaderKey\"));",
									"//console.log(pm.globals.get(\"gAuthHeaderValue\"));",
									"",
									"// Make request body by combining chained properties and data file request body",
									"if (API !== undefined) {",
									"    var request = { };",
									"    apiUtility.setChainProps(API.Chain, request);",
									"    var req = apiUtility.mergeRequestBody(request, API.RequestBody);",
									"    pm.globals.set(\"gRequestBody\", JSON.stringify(req));",
									"    //console.log(pm.globals.get(\"gRequestBody\"));",
									"}",
									"",
									"// Make URL",
									"if(API !== undefined) {",
									"    pm.globals.set(\"gUrl\", apiUtility.makeUrl(pm.environment.get(\"envWebScheme\"), pm.environment.get(\"envWebHost\"), API.RequestUrl));",
									"} else {",
									"    pm.globals.set(\"gUrl\", \"http://127.0.0.1\");",
									"}",
									"//console.log(pm.globals.get(\"gUrl\"));",
									"/*****************END DO NOT MODIFY THIS CODE*******************/"
								],
								"type": "text/javascript"
							}
						},
						{
							"listen": "test",
							"script": {
								"exec": [
									"/********************DO NOT MODIFY THIS CODE********************/",
									"// Load API utility code",
									"eval(postman.getGlobalVariable(\"gApiUtility\"));",
									"",
									"// Get API settings",
									"let API = pm.globals.get(\"gReqApi\");",
									"if (API === null) {",
									"    postman.setNextRequest(null);",
									"    pm.test(\"API not found for the Request ID, using fallback URL and ending the test\", function() { pm.expect.fail() });",
									"    return;",
									"}",
									"//console.log(API);",
									"",
									"// Save properties for chaining, ignore exceptions because the test will fail later anyways",
									"try {",
									"   var rb = pm.response.json();",
									"   if (API.ChainSource.length > 0) {",
									"      let str = API.RequestId + \".response\";",
									"      apiUtility.globalStoreWrite(str, rb);",
									"   }",
									"} catch(e) { console.log(\"Exception was raised during chainging, Msg -\" + e); }",
									"/*****************END DO NOT MODIFY THIS CODE*******************/",
									"",
									"// --- TEST VERIFICATIONS ---",
									"// --- Add your custom tests in this block ---",
									"pm.test(\"Verify response status is \" + API.ResponseStatus, function() { ",
									"     pm.expect(pm.response.code).to.equal(API.ResponseStatus);",
									"});",
									"pm.test(\"Verify response time is less than \" + API.ResponseTimeMs, function() { ",
									"     pm.expect(pm.response.responseTime).to.be.below(API.ResponseTimeMs);",
									"});",
									"// pm.test(\"Verify response value is not empty\",function(){",
									"//     pm.expect(pm.response.json()).to.not.equal(0);",
									"// });",
									"var TotalMinutesAttended = pm.globals.get(\"gCompletedMinutesAttended\");",
									"var CompleteRTSH = pm.globals.get(\"gCompleteRTSH\");",
									"console.log(TotalMinutesAttended)",
									"console.log(CompleteRTSH)",
									"pm.test(\"Verify Current Hours is null\",function(){",
									"    pm.expect(pm.response.json().calculatedTotals.currentUnits).to.equal(null);",
									"});",
									"pm.test(\"Verify Scheduled Hours is null\",function(){",
									"    pm.expect(pm.response.json().calculatedTotals.scheduledUnits).to.equal(null);",
									"});",
									"pm.test(\"Verify Real Time Scheduled Minutes is matching\",function(){",
									"    pm.expect(pm.response.json().calculatedTotals.realTimeScheduledMinutes).to.equal(CompleteRTSH);",
									"});",
									"pm.test(\"Verify Attended Minutes is matching\",function(){",
									"    pm.expect(pm.response.json().calculatedTotals.attendedMinutes).to.equal(TotalMinutesAttended);",
									"});",
									"// --- END TEST VERIFICATIONS ---",
									"console.log(\"--------------------------------------------------------------------------------------\");"
								],
								"type": "text/javascript"
							}
						}
					],
					"request": {
						"auth": {
							"type": "noauth"
						},
						"method": "GET",
						"header": [
							{
								"key": "Content-Type",
								"value": "application/json"
							},
							{
								"key": "{{gAuthHeaderKey}}",
								"value": "{{gAuthHeaderValue}}"
							}
						],
						"url": {
							"raw": "{{gUrl}}",
							"host": [
								"{{gUrl}}"
							]
						}
					},
					"response": []
				}
			],
			"description": "<metadata>\n<environmentfile name='StudentDPAAPIEnvironment'/>\n<data name='CheckCurrentandScheduledCreditsafterCompletingtheCourse'/>\n</metadata>"
		},
		{
			"name": "DeleteCoursefromStudent",
			"item": [],
			"description": "<metadata>\n<postrun name='DeleteCoursefromStudent'/>\n<environmentfile name='StudentDPAAPIEnvironment'/>\n<data name='DeleteCoursefromStudent'/>\n</metadata>"
		},
		{
			"name": "DeleteEnrollment",
			"item": [],
			"description": "<metadata>\n<postrun name='DeleteEnrollmentfromStudent'/>\n<environmentfile name='StudentDPAAPIEnvironment'/>\n<data name='DeleteEnrollment'/>\n</metadata>"
		}
	]
}